Workbook

Sheet PTM
B2: INVERSIONES AÑO 2026 | V2: Abonó Int L10mil el 26/06/2026 | AK2: =2433.92+2433.95 -> 4867.87 | AN2: 7301.89 | AO2: 2433.95 | AP2: =AN2-AO2 -> 4867.94
C4: PRESTAMO 1 | G4: 0.05 | K4: PRESTAMO 2 | O4: 0.03 | T4: PRESTAMO 3 | W4: 0.02 | AB4: PRESTAMO 4 | AD4: 0.02 | AJ4: PRESTAMO 5 | AL4: 0.04 | AR4: PRESTAMO 6 | AT4: 0.035 | AZ4: PRESTAMO 7 | BC4: 0.035 | BH4: PRESTAMO 8 | BJ4: 0.045 | BO4: PRESTAMO 9 | BQ4: 0.045 | BW4: PRESTAMO 10 | BZ4: 0.05 | CF4: 0 | CH4: 0.045 | CM4: 0 | CQ4: 0.04 | CU4: 0 | CX4: 0.045 | DD4: 0 | DF4: 0.045 | DL4: 0 | DO4: 0.04 | DS4: 0 | DV4: 0.038 | EA4: 0 | EE4: 0.045 | EJ4: 0 | EL4: 0.045 | ER4: 0 | EU4: 0.045 | EY4: 0 | FB4: 0.045 | FG4: 0 | FK4: 0.04 | FO4: 0 | FS4: 0.045 | FW4: 0 | GA4: 0.025 | GE4: 0 | GI4: 0.045 | GM4: 0 | GQ4: 0.045 | GU4: 0 | GX4: 0.04 | HC4: 0 | HK4: 0 | HO4: 0.045 | HT4: 0 | IB4: 0 | IJ4: 0 | IR4: 0 | IZ4: 0 | JG4: 0 | JP4: 0 | JW4: 0 | KE4: 0 | KM4: 0 | KU4: 0 | LC4: 0 | LK4: 0 | LS4: 0 | MA4: 0 | MI4: 0 | MQ4: 0 | MY4: 0 | NG4: 0 | NO4: 0 | NW4: 0 | OE4: 0 | OM4: 0 | OU4: 0 | PC4: 0 | PK4: 0 | PS4: 0 | QA4: 0 | QI4: 0 | QQ4: 0 | QY4: 0 | RG4: 0 | RO4: 0 | RW4: 0 | SE4: 0 | SM4: 0 | SU4: 0 | TC4: 0 | TK4: 0 | TS4: 0 | UA4: 0 | UI4: 0 | UQ4: 0 | UY4: 0 | VG4: 0 | VO4: 0 | VW4: 0 | WE4: 0 | WM4: 0 | WU4: 0 | XC4: 0 | XK4: 0 | XS4: 0 | YA4: 0 | YI4: 0 | YQ4: 0 | YY4: 0 | ZG4: 0 | ZO4: 0 | ZW4: 0 | AAE4: 0 | AAM4: 0 | AAU4: 0 | ABC4: 0 | ABK4: 0 | ABS4: 0 | ACA4: 0
A5: =C4 -> PRESTAMO 1 | I5: =K4 -> PRESTAMO 2 | Q5: =T4 -> PRESTAMO 3 | Y5: =AB4 -> PRESTAMO 4 | AG5: =AJ4 -> PRESTAMO 5 | AO5: =AR4 -> PRESTAMO 6 | AW5: =AZ4 -> PRESTAMO 7 | BE5: =BH4 -> PRESTAMO 8 | BM5: =BO4 -> PRESTAMO 9 | BU5: =BW4 -> PRESTAMO 10 | CC5: =CF4 -> 0 | CK5: =CM4 -> 0 | CS5: =CU4 -> 0 | DA5: =DD4 -> 0 | DI5: =DL4 -> 0 | DQ5: =DS4 -> 0 | DY5: =EA4 -> 0 | EG5: =EJ4 -> 0 | EO5: =ER4 -> 0 | EW5: =EY4 -> 0 | FE5: =FG4 -> 0 | FM5: =FO4 -> 0 | FU5: =FW4 -> 0 | GC5: =GE4 -> 0 | GK5: =GM4 -> 0 | GS5: =GU4 -> 0 | HA5: =HC4 -> 0 | HI5: =HK4 -> 0 | HQ5: =HT4 -> 0 | HY5: =IB4 -> 0 | IG5: =IJ4 -> 0 | IR5: =IR4 -> 0 | IZ5: =IZ4 -> 0 | JE5: =JG4 -> 0 | JM5: =JP4 -> 0 | JU5: =JW4 -> 0 | KC5: =KE4 -> 0 | KK5: =KM4 -> 0 | KS5: =KU4 -> 0 | LA5: =LC4 -> 0 | LI5: =LK4 -> 0 | LS5: =LS4 -> 0 | MA5: =MA4 -> 0 | MI5: =MI4 -> 0 | MQ5: =MQ4 -> 0 | MY5: =MY4 -> 0 | NG5: =NG4 -> 0 | NO5: =NO4 -> 0 | NW5: =NW4 -> 0 | OE5: =OE4 -> 0 | OM5: =OM4 -> 0 | OU5: =OU4 -> 0 | PC5: =PC4 -> 0 | PK5: =PK4 -> 0 | PS5: =PS4 -> 0 | QA5: =QA4 -> 0 | QI5: =QI4 -> 0 | QQ5: =QQ4 -> 0 | QY5: =QY4 -> 0 | RG5: =RG4 -> 0 | RO5: =RO4 -> 0 | RW5: =RW4 -> 0 | SE5: =SE4 -> 0 | SM5: =SM4 -> 0 | SU5: =SU4 -> 0 | TC5: =TC4 -> 0 | TK5: =TK4 -> 0 | TS5: =TS4 -> 0 | UA5: =UA4 -> 0 | UI5: =UI4 -> 0 | UQ5: =UQ4 -> 0 | UY5: =UY4 -> 0 | VG5: =VG4 -> 0 | VO5: =VO4 -> 0 | VW5: =VW4 -> 0 | WE5: =WE4 -> 0 | WM5: =WM4 -> 0 | WU5: =WU4 -> 0 | XC5: =XC4 -> 0 | XK5: =XK4 -> 0 | XS5: =XS4 -> 0 | YA5: =YA4 -> 0 | YI5: =YI4 -> 0 | YQ5: =YQ4 -> 0 | YY5: =YY4 -> 0 | ZG5: =ZG4 -> 0 | ZO5: =ZO4 -> 0 | ZW5: =ZW4 -> 0 | AAE5: =AAE4 -> 0 | AAM5: =AAM4 -> 0 | AAU5: =AAU4 -> 0 | ABC5: =ABC4 -> 0 | ABK5: =ABK4 -> 0 | ABS5: =ABS4 -> 0 | ACA5: =ACA4 -> 0
A6: FECHA | B6: PRESTAMOS | C6: ABONO | D6: NUEVO | E6: FECHA DE | F6: INTERSES | G6: INTERESES | I6: FECHA | J6: PRESTAMOS | K6: ABONO | L6: NUEVO | M6: FECHA DE | N6: INTERSES | O6: INTERESES | Q6: FECHA | R6: PRESTAMOS | S6: ABONO | T6: NUEVO | U6: FECHA DE | V6: INTERSES | W6: INTERESES | Y6: FECHA | Z6: PRESTAMOS | AA6: ABONO | AB6: NUEVO | AC6: FECHA DE | AD6: INTERSES | AE6: INTERESES | AG6: FECHA | AH6: PRESTAMOS | AI6: ABONO | AJ6: NUEVO | AK6: FECHA DE | AL6: INTERSES | AM6: INTERESES | AO6: FECHA | AP6: PRESTAMOS | AQ6: ABONO | AR6: NUEVO | AS6: FECHA DE | AT6: INTERSES | AU6: INTERESES | AW6: FECHA | AX6: PRESTAMOS | AY6: ABONO | AZ6: NUEVO | BA6: FECHA DE | BB6: INTERSES | BC6: INTERESES | BE6: FECHA | BF6: PRESTAMOS | BG6: ABONO | BH6: NUEVO | BI6: FECHA DE | BJ6: INTERSES | BK6: INTERESES | BM6: FECHA | BN6: PRESTAMOS | BO6: ABONO | BP6: NUEVO | BQ6: FECHA DE | BR6: INTERSES | BS6: INTERESES | BU6: FECHA | BV6: PRESTAMOS | BW6: ABONO | BX6: NUEVO | BY6: FECHA DE | BZ6: INTERSES | CA6: INTERESES | CC6: FECHA | CD6: PRESTAMOS | CE6: ABONO | CF6: NUEVO | CG6: FECHA DE | CH6: INTERSES | CI6: INTERESES | CK6: FECHA | CL6: PRESTAMOS | CM6: ABONO | CN6: NUEVO | CO6: FECHA DE | CP6: INTERSES | CQ6: INTERESES | CS6: FECHA | CT6: PRESTAMOS | CU6: ABONO | CV6: NUEVO | CW6: FECHA DE | CX6: INTERSES | CY6: INTERESES | DA6: FECHA | DB6: PRESTAMOS | DC6: ABONO | DD6: NUEVO | DE6: FECHA DE | DF6: INTERSES | DG6: INTERESES | DI6: FECHA | DJ6: PRESTAMOS | DK6: ABONO | DL6: NUEVO | DM6: FECHA DE | DN6: INTERSES | DO6: INTERESES | DQ6: FECHA | DR6: PRESTAMOS | DS6: ABONO | DT6: NUEVO | DU6: FECHA DE | DV6: INTERSES | DW6: INTERESES | DY6: FECHA | DZ6: PRESTAMOS | EA6: ABONO | EB6: NUEVO | EC6: FECHA DE | ED6: INTERSES | EE6: INTERESES | EG6: FECHA | EH6: PRESTAMOS | EI6: ABONO | EJ6: NUEVO | EK6: FECHA DE | EL6: INTERSES | EM6: INTERESES | EO6: FECHA | EP6: PRESTAMOS | EQ6: ABONO | ER6: NUEVO | ES6: FECHA DE | ET6: INTERSES | EU6: INTERESES | EW6: FECHA | EX6: PRESTAMOS | EY6: ABONO | EZ6: NUEVO | FA6: FECHA DE | FB6: INTERSES | FC6: INTERESES | FE6: FECHA | FF6: PRESTAMOS | FG6: ABONO | FH6: NUEVO | FI6: FECHA DE | FJ6: INTERSES | FK6: INTERESES | FM6: FECHA | FN6: PRESTAMOS | FO6: ABONO | FP6: NUEVO | FQ6: FECHA DE | FR6: INTERSES | FS6: INTERESES | FU6: FECHA | FV6: PRESTAMOS | FW6: ABONO | FX6: NUEVO | FY6: FECHA DE | FZ6: INTERSES | GA6: INTERESES | GC6: FECHA | GD6: PRESTAMOS | GE6: ABONO | GF6: NUEVO | GG6: FECHA DE | GH6: INTERSES | GI6: INTERESES | GK6: FECHA | GL6: PRESTAMOS | GM6: ABONO | GN6: NUEVO | GO6: FECHA DE | GP6: INTERSES | GQ6: INTERESES | GS6: FECHA | GT6: PRESTAMOS | GU6: ABONO | GV6: NUEVO | GW6: FECHA DE | GX6: INTERSES | GY6: INTERESES | HA6: FECHA | HB6: PRESTAMOS | HC6: ABONO | HD6: NUEVO | HE6: FECHA DE | HF6: INTERSES | HG6: INTERESES | HI6: FECHA | HJ6: PRESTAMOS | HK6: ABONO | HL6: NUEVO | HM6: FECHA DE | HN6: INTERSES | HO6: INTERESES | HQ6: FECHA | HR6: PRESTAMOS | HS6: ABONO | HT6: NUEVO | HU6: FECHA DE | HV6: INTERSES | HW6: INTERESES | HY6: FECHA | HZ6: PRESTAMOS | IA6: ABONO | IB6: NUEVO | IC6: FECHA DE | ID6: INTERSES | IE6: INTERESES | IG6: FECHA | IH6: PRESTAMOS | II6: ABONO | IJ6: NUEVO | IK6: FECHA DE | IL6: INTERSES | IM6: INTERESES | IO6: FECHA | IP6: PRESTAMOS | IQ6: ABONO | IR6: NUEVO | IS6: FECHA DE | IT6: INTERSES | IU6: INTERESES | IW6: FECHA | IX6: PRESTAMOS | IY6: ABONO | IZ6: NUEVO | JA6: FECHA DE | JB6: INTERSES | JC6: INTERESES | JE6: FECHA | JF6: PRESTAMOS | JG6: ABONO | JH6: NUEVO | JI6: FECHA DE | JJ6: INTERSES | JK6: INTERESES | JM6: FECHA | JN6: PRESTAMOS | JO6: ABONO | JP6: NUEVO | JQ6: FECHA DE | JR6: INTERSES | JS6: INTERESES | JU6: FECHA | JV6: PRESTAMOS | JW6: ABONO | JX6: NUEVO | JY6: FECHA DE | JZ6: INTERSES | KA6: INTERESES | KC6: FECHA | KD6: PRESTAMOS | KE6: ABONO | KF6: NUEVO | KG6: FECHA DE | KH6: INTERSES | KI6: INTERESES | KK6: FECHA | KL6: PRESTAMOS | KM6: ABONO | KN6: NUEVO | KO6: FECHA DE | KP6: INTERSES | KQ6: INTERESES | KS6: FECHA | KT6: PRESTAMOS | KU6: ABONO | KV6: NUEVO | KW6: FECHA DE | KX6: INTERSES | KY6: INTERESES | LA6: FECHA | LB6: PRESTAMOS | LC6: ABONO | LD6: NUEVO | LE6: FECHA DE | LF6: INTERSES | LG6: INTERESES | LI6: FECHA | LJ6: PRESTAMOS | LK6: ABONO | LL6: NUEVO | LM6: FECHA DE | LN6: INTERSES | LO6: INTERESES | LQ6: FECHA | LR6: PRESTAMOS | LS6: ABONO | LT6: NUEVO | LU6: FECHA DE | LV6: INTERSES | LW6: INTERESES | LY6: FECHA | LZ6: PRESTAMOS | MA6: ABONO | MB6: NUEVO | MC6: FECHA DE | MD6: INTERSES | ME6: INTERESES | MG6: FECHA | MH6: PRESTAMOS | MI6: ABONO | MJ6: NUEVO | MK6: FECHA DE | ML6: INTERSES | MM6: INTERESES | MO6: FECHA | MP6: PRESTAMOS | MQ6: ABONO | MR6: NUEVO | MS6: FECHA DE | MT6: INTERSES | MU6: INTERESES | MW6: FECHA | MX6: PRESTAMOS | MY6: ABONO | MZ6: NUEVO | NA6: FECHA DE | NB6: INTERSES | NC6: INTERESES | NE6: FECHA | NF6: PRESTAMOS | NG6: ABONO | NH6: NUEVO | NI6: FECHA DE | NJ6: INTERSES | NK6: INTERESES | NM6: FECHA | NN6: PRESTAMOS | NO6: ABONO | NP6: NUEVO | NQ6: FECHA DE | NR6: INTERSES | NS6: INTERESES | NU6: FECHA | NV6: PRESTAMOS | NW6: ABONO | NX6: NUEVO | NY6: FECHA DE | NZ6: INTERSES | OA6: INTERESES | OC6: FECHA | OD6: PRESTAMOS | OE6: ABONO | OF6: NUEVO | OG6: FECHA DE | OH6: INTERSES | OI6: INTERESES | OK6: FECHA | OL6: PRESTAMOS | OM6: ABONO | ON6: NUEVO | OO6: FECHA DE | OP6: INTERSES | OQ6: INTERESES | OS6: FECHA | OT6: PRESTAMOS | OU6: ABONO | OV6: NUEVO | OW6: FECHA DE | OX6: INTERSES | OY6: INTERESES | PA6: FECHA | PB6: PRESTAMOS | PC6: ABONO | PD6: NUEVO | PE6: FECHA DE | PF6: INTERSES | PG6: INTERESES | PI6: FECHA | PJ6: PRESTAMOS | PK6: ABONO | PL6: NUEVO | PM6: FECHA DE | PN6: INTERSES | PO6: INTERESES | PQ6: FECHA | PR6: PRESTAMOS | PS6: ABONO | PT6: NUEVO | PU6: FECHA DE | PV6: INTERSES | PW6: INTERESES | PY6: FECHA | PZ6: PRESTAMOS | QA6: ABONO | QB6: NUEVO | QC6: FECHA DE | QD6: INTERSES | QE6: INTERESES | QG6: FECHA | QH6: PRESTAMOS | QI6: ABONO | QJ6: NUEVO | QK6: FECHA DE | QL6: INTERSES | QM6: INTERESES | QO6: FECHA | QP6: PRESTAMOS | QQ6: ABONO | QR6: NUEVO | QS6: FECHA DE | QT6: INTERSES | QU6: INTERESES | QW6: FECHA | QX6: PRESTAMOS | QY6: ABONO | QZ6: NUEVO | RA6: FECHA DE | RB6: INTERSES | RC6: INTERESES | RE6: FECHA | RF6: PRESTAMOS | RG6: ABONO | RH6: NUEVO | RI6: FECHA DE | RJ6: INTERSES | RK6: INTERESES | RM6: FECHA | RN6: PRESTAMOS | RO6: ABONO | RP6: NUEVO | RQ6: FECHA DE | RR6: INTERSES | RS6: INTERESES | RU6: FECHA | RV6: PRESTAMOS | RW6: ABONO | RX6: NUEVO | RY6: FECHA DE | RZ6: INTERSES | SA6: INTERESES | SC6: FECHA | SD6: PRESTAMOS | SE6: ABONO | SF6: NUEVO | SG6: FECHA DE | SH6: INTERSES | SI6: INTERESES | SK6: FECHA | SL6: PRESTAMOS | SM6: ABONO | SN6: NUEVO | SO6: FECHA DE | SP6: INTERSES | SQ6: INTERESES | SS6: FECHA | ST6: PRESTAMOS | SU6: ABONO | SV6: NUEVO | SW6: FECHA DE | SX6: INTERSES | SY6: INTERESES | TA6: FECHA | TB6: PRESTAMOS | TC6: ABONO | TD6: NUEVO | TE6: FECHA DE | TF6: INTERSES | TG6: INTERESES | TI6: FECHA | TJ6: PRESTAMOS | TK6: ABONO | TL6: NUEVO | TM6: FECHA DE | TN6: INTERSES | TO6: INTERESES | TQ6: FECHA | TR6: PRESTAMOS | TS6: ABONO | TT6: NUEVO | TU6: FECHA DE | TV6: INTERSES | TW6: INTERESES | TY6: FECHA | TZ6: PRESTAMOS | UA6: ABONO | UB6: NUEVO | UC6: FECHA DE | UD6: INTERSES | UE6: INTERESES | UG6: FECHA | UH6: PRESTAMOS | UI6: ABONO | UJ6: NUEVO | UK6: FECHA DE | UL6: INTERSES | UM6: INTERESES | UO6: FECHA | UP6: PRESTAMOS | UQ6: ABONO | UR6: NUEVO | US6: FECHA DE | UT6: INTERSES | UU6: INTERESES | UW6: FECHA | UX6: PRESTAMOS | UY6: ABONO | UZ6: NUEVO | VA6: FECHA DE | VB6: INTERSES | VC6: INTERESES | VE6: FECHA | VF6: PRESTAMOS | VG6: ABONO | VH6: NUEVO | VI6: FECHA DE | VJ6: INTERSES | VK6: INTERESES | VM6: FECHA | VN6: PRESTAMOS | VO6: ABONO | VP6: NUEVO | VQ6: FECHA DE | VR6: INTERSES | VS6: INTERESES | VU6: FECHA | VV6: PRESTAMOS | VW6: ABONO | VX6: NUEVO | VY6: FECHA DE | VZ6: INTERSES | WA6: INTERESES | WC6: FECHA | WD6: PRESTAMOS | WE6: ABONO | WF6: NUEVO | WG6: FECHA DE | WH6: INTERSES | WI6: INTERESES | WK6: FECHA | WL6: PRESTAMOS | WM6: ABONO | WN6: NUEVO | WO6: FECHA DE | WP6: INTERSES | WQ6: INTERESES | WS6: FECHA | WT6: PRESTAMOS | WU6: ABONO | WV6: NUEVO | WW6: FECHA DE | WX6: INTERSES | WY6: INTERESES | XA6: FECHA | XB6: PRESTAMOS | XC6: ABONO | XD6: NUEVO | XE6: FECHA DE | XF6: INTERSES | XG6: INTERESES | XI6: FECHA | XJ6: PRESTAMOS | XK6: ABONO | XL6: NUEVO | XM6: FECHA DE | XN6: INTERSES | XO6: INTERESES | XQ6: FECHA | XR6: PRESTAMOS | XS6: ABONO | XT6: NUEVO | XU6: FECHA DE | XV6: INTERSES | XW6: INTERESES | XY6: FECHA | XZ6: PRESTAMOS | YA6: ABONO | YB6: NUEVO | YC6: FECHA DE | YD6: INTERSES | YE6: INTERESES | YG6: FECHA | YH6: PRESTAMOS | YI6: ABONO | YJ6: NUEVO | YK6: FECHA DE | YL6: INTERSES | YM6: INTERESES | YO6: FECHA | YP6: PRESTAMOS | YQ6: ABONO | YR6: NUEVO | YS6: FECHA DE | YT6: INTERSES | YU6: INTERESES | YW6: FECHA | YX6: PRESTAMOS | YY6: ABONO | YZ6: NUEVO | ZA6: FECHA DE | ZB6: INTERSES | ZC6: INTERESES | ZE6: FECHA | ZF6: PRESTAMOS | ZG6: ABONO | ZH6: NUEVO | ZI6: FECHA DE | ZJ6: INTERSES | ZK6: INTERESES | ZM6: FECHA | ZN6: PRESTAMOS | ZO6: ABONO | ZP6: NUEVO | ZQ6: FECHA DE | ZR6: INTERSES | ZS6: INTERESES | ZU6: FECHA | ZV6: PRESTAMOS | ZW6: ABONO | ZX6: NUEVO | ZY6: FECHA DE | ZZ6: INTERSES | AAA6: INTERESES | AAC6: FECHA | AAD6: PRESTAMOS | AAE6: ABONO | AAF6: NUEVO | AAG6: FECHA DE | AAH6: INTERSES | AAI6: INTERESES | AAK6: FECHA | AAL6: PRESTAMOS | AAM6: ABONO | AAN6: NUEVO | AAO6: FECHA DE | AAP6: INTERSES | AAQ6: INTERESES | AAS6: FECHA | AAT6: PRESTAMOS | AAU6: ABONO | AAV6: NUEVO | AAW6: FECHA DE | AAX6: INTERSES | AAY6: INTERESES | ABA6: FECHA | ABB6: PRESTAMOS | ABC6: ABONO | ABD6: NUEVO | ABE6: FECHA DE | ABF6: INTERSES | ABG6: INTERESES | ABI6: FECHA | ABJ6: PRESTAMOS | ABK6: ABONO | ABL6: NUEVO | ABM6: FECHA DE | ABN6: INTERSES | ABO6: INTERESES | ABQ6: FECHA | ABR6: PRESTAMOS | ABS6: ABONO | ABT6: NUEVO | ABU6: FECHA DE | ABV6: INTERSES | ABW6: INTERESES | ABY6: FECHA | ABZ6: PRESTAMOS | ACA6: ABONO | ACB6: NUEVO | ACC6: FECHA DE | ACD6: INTERSES | ACE6: INTERESES
B7: CONCEDIDO | D7: SALDO | E7: INTERES | F7: PAGADOS | G7: PENDIENTES | J7: CONCEDIDO | L7: SALDO | M7: INTERES | N7: PAGADOS | O7: PENDIENTES | R7: CONCEDIDO | T7: SALDO | U7: INTERES | V7: PAGADOS | W7: PENDIENTES | Z7: CONCEDIDO | AB7: SALDO | AC7: INTERES | AE7: PENDIENTES | AH7: CONCEDIDO | AJ7: SALDO | AK7: INTERES | AL7: PAGADOS | AM7: PENDIENTES | AP7: CONCEDIDO | AR7: SALDO | AS7: INTERES | AT7: PAGADOS | AU7: PENDIENTES | AX7: CONCEDIDO | AZ7: SALDO | BA7: INTERES | BB7: PAGADOS | BC7: PENDIENTES | BF7: CONCEDIDO | BH7: SALDO | BI7: INTERES | BJ7: PAGADOS | BK7: PENDIENTES | BN7: CONCEDIDO | BP7: SALDO | BQ7: INTERES | BR7: PAGADOS | BS7: PENDIENTES | BV7: CONCEDIDO | BX7: SALDO | BY7: INTERES | BZ7: PAGADOS | CA7: PENDIENTES | CD7: CONCEDIDO | CF7: SALDO | CG7: INTERES | CH7: PAGADOS | CI7: PENDIENTES | CL7: CONCEDIDO | CN7: SALDO | CO7: INTERES | CP7: PAGADOS | CQ7: PENDIENTES | CT7: CONCEDIDO | CV7: SALDO | CW7: INTERES | CX7: PAGADOS | CY7: PENDIENTES | DB7: CONCEDIDO | DD7: SALDO | DE7: INTERES | DF7: PAGADOS | DG7: PENDIENTES | DJ7: CONCEDIDO | DL7: SALDO | DM7: INTERES | DN7: PAGADOS | DO7: PENDIENTES | DR7: CONCEDIDO | DT7: SALDO | DU7: INTERES | DV7: PAGADOS | DW7: PENDIENTES | DZ7: CONCEDIDO | EB7: SALDO | EC7: INTERES | ED7: PAGADOS | EE7: PENDIENTES | EH7: CONCEDIDO | EJ7: SALDO | EK7: INTERES | EL7: PAGADOS | EM7: PENDIENTES | EP7: CONCEDIDO | ER7: SALDO | ES7: INTERES | ET7: PAGADOS | EU7: PENDIENTES | EX7: CONCEDIDO | EZ7: SALDO | FA7: INTERES | FB7: PAGADOS | FC7: PENDIENTES | FF7: CONCEDIDO | FH7: SALDO | FI7: INTERES | FJ7: PAGADOS | FK7: PENDIENTES | FN7: CONCEDIDO | FP7: SALDO | FQ7: INTERES | FR7: PAGADOS | FS7: PENDIENTES | FV7: CONCEDIDO | FX7: SALDO | FY7: INTERES | FZ7: PAGADOS | GA7: PENDIENTES | GD7: CONCEDIDO | GF7: SALDO | GG7: INTERES | GH7: PAGADOS | GI7: PENDIENTES | GL7: CONCEDIDO | GN7: SALDO | GO7: INTERES | GP7: PAGADOS | GQ7: PENDIENTES | GT7: CONCEDIDO | GV7: SALDO | GW7: INTERES | GX7: PAGADOS | HB7: CONCEDIDO | HD7: SALDO | HE7: INTERES | HF7: PAGADOS | HG7: PENDIENTES | HJ7: CONCEDIDO | HL7: SALDO | HM7: INTERES | HN7: PAGADOS | HO7: PENDIENTES | HR7: CONCEDIDO | HT7: SALDO | HU7: INTERES | HV7: PAGADOS | HW7: PENDIENTES | HZ7: CONCEDIDO | IB7: SALDO | IC7: INTERES | ID7: PAGADOS | IE7: PENDIENTES | IH7: CONCEDIDO | IJ7: SALDO | IK7: INTERES | IP7: CONCEDIDO | IR7: SALDO | IS7: INTERES | IT7: PAGADOS | IU7: PENDIENTES | IX7: CONCEDIDO | IZ7: SALDO | JA7: INTERES | JB7: PAGADOS | JC7: PENDIENTES | JF7: CONCEDIDO | JH7: SALDO | JI7: INTERES | JJ7: PAGADOS | JK7: PENDIENTES | JN7: CONCEDIDO | JP7: SALDO | JQ7: INTERES | JR7: PAGADOS | JS7: PENDIENTES | JV7: CONCEDIDO | JX7: SALDO | JY7: INTERES | JZ7: PAGADOS | KA7: PENDIENTES | KD7: CONCEDIDO | KF7: SALDO | KG7: INTERES | KH7: PAGADOS | KI7: PENDIENTES | KL7: CONCEDIDO | KN7: SALDO | KO7: INTERES | KP7: PAGADOS | KQ7: PENDIENTES | KT7: CONCEDIDO | KV7: SALDO | KW7: INTERES | KX7: PAGADOS | KY7: PENDIENTES | LB7: CONCEDIDO | LD7: SALDO | LE7: INTERES | LF7: PAGADOS | LG7: PENDIENTES | LL7: SALDO | LM7: INTERES | LN7: PAGADOS | LO7: PENDIENTES | LR7: CONCEDIDO | LT7: SALDO | LU7: INTERES | LV7: PAGADOS | LW7: PENDIENTES | LZ7: CONCEDIDO | MB7: SALDO | MC7: INTERES | MD7: PAGADOS | ME7: PENDIENTES | MH7: CONCEDIDO | MJ7: SALDO | MK7: INTERES | ML7: PAGADOS | MM7: PENDIENTES | MP7: CONCEDIDO | MR7: SALDO | MS7: INTERES | MT7: PAGADOS | MU7: PENDIENTES | MX7: CONCEDIDO | MZ7: SALDO | NA7: INTERES | NB7: PAGADOS | NC7: PENDIENTES | NF7: CONCEDIDO | NH7: SALDO | NI7: INTERES | NJ7: PAGADOS | NK7: PENDIENTES | NN7: CONCEDIDO | NP7: SALDO | NQ7: INTERES | NR7: PAGADOS | NS7: PENDIENTES | NV7: CONCEDIDO | NX7: SALDO | NY7: INTERES | NZ7: PAGADOS | OA7: PENDIENTES | OD7: CONCEDIDO | OF7: SALDO | OG7: INTERES | OH7: PAGADOS | OI7: PENDIENTES | OL7: CONCEDIDO | ON7: SALDO | OO7: INTERES | OP7: PAGADOS | OQ7: PENDIENTES | OT7: CONCEDIDO | OV7: SALDO | OW7: INTERES | OX7: PAGADOS | OY7: PENDIENTES | PB7: CONCEDIDO | PD7: SALDO | PE7: INTERES | PF7: PAGADOS | PG7: PENDIENTES | PJ7: CONCEDIDO | PL7: SALDO | PM7: INTERES | PN7: PAGADOS | PO7: PENDIENTES | PR7: CONCEDIDO | PT7: SALDO | PU7: INTERES | PV7: PAGADOS | PW7: PENDIENTES | PZ7: CONCEDIDO | QB7: SALDO | QC7: INTERES | QD7: PAGADOS | QE7: PENDIENTES | QH7: CONCEDIDO | QJ7: SALDO | QK7: INTERES | QL7: PAGADOS | QM7: PENDIENTES | QP7: CONCEDIDO | QR7: SALDO | QS7: INTERES | QT7: PAGADOS | QU7: PENDIENTES | QX7: CONCEDIDO | QZ7: SALDO | RA7: INTERES | RB7: PAGADOS | RC7: PENDIENTES | RF7: CONCEDIDO | RH7: SALDO | RI7: INTERES | RJ7: PAGADOS | RK7: PENDIENTES | RN7: CONCEDIDO | RP7: SALDO | RQ7: INTERES | RR7: PAGADOS | RS7: PENDIENTES | RV7: CONCEDIDO | RX7: SALDO | RY7: INTERES | RZ7: PAGADOS | SA7: PENDIENTES | SD7: CONCEDIDO | SF7: SALDO | SG7: INTERES | SH7: PAGADOS | SI7: PENDIENTES | SL7: CONCEDIDO | SN7: SALDO | SO7: INTERES | SP7: PAGADOS | SQ7: PENDIENTES | ST7: CONCEDIDO | SV7: SALDO | SW7: INTERES | SX7: PAGADOS | SY7: PENDIENTES | TB7: CONCEDIDO | TD7: SALDO | TE7: INTERES | TF7: PAGADOS | TG7: PENDIENTES | TJ7: CONCEDIDO | TL7: SALDO | TM7: INTERES | TN7: PAGADOS | TO7: PENDIENTES | TR7: CONCEDIDO | TT7: SALDO | TU7: INTERES | TV7: PAGADOS | TW7: PENDIENTES | TZ7: CONCEDIDO | UB7: SALDO | UC7: INTERES | UD7: PAGADOS | UE7: PENDIENTES | UH7: CONCEDIDO | UJ7: SALDO | UK7: INTERES | UL7: PAGADOS | UM7: PENDIENTES | UP7: CONCEDIDO | UR7: SALDO | US7: INTERES | UT7: PAGADOS | UU7: PENDIENTES | UX7: CONCEDIDO | UZ7: SALDO | VA7: INTERES | VB7: PAGADOS | VC7: PENDIENTES | VF7: CONCEDIDO | VH7: SALDO | VI7: INTERES | VJ7: PAGADOS | VK7: PENDIENTES | VN7: CONCEDIDO | VP7: SALDO | VQ7: INTERES | VR7: PAGADOS | VS7: PENDIENTES | VV7: CONCEDIDO | VX7: SALDO | VY7: INTERES | VZ7: PAGADOS | WA7: PENDIENTES | WD7: CONCEDIDO | WF7: SALDO | WG7: INTERES | WH7: PAGADOS | WI7: PENDIENTES | WL7: CONCEDIDO | WN7: ? | WO7: INTERES | WP7: PAGADOS | WQ7: PENDIENTES | WT7: CONCEDIDO | WV7: SALDO | WW7: INTERES | WX7: PAGADOS | WY7: PENDIENTES | XB7: CONCEDIDO | XD7: SALDO | XE7: INTERES | XF7: PAGADOS | XG7: PENDIENTES | XJ7: CONCEDIDO | XL7: SALDO | XM7: INTERES | XN7: PAGADOS | XO7: PENDIENTES | XR7: CONCEDIDO | XT7: SALDO | XU7: INTERES | XV7: PAGADOS | XW7: PENDIENTES | XZ7: CONCEDIDO | YB7: SALDO | YC7: INTERES | YD7: PAGADOS | YE7: PENDIENTES | YH7: CONCEDIDO | YJ7: SALDO | YK7: INTERES | YL7: PAGADOS | YM7: PENDIENTES | YP7: CONCEDIDO | YR7: SALDO | YS7: INTERES | YT7: PAGADOS | YU7: PENDIENTES | YX7: CONCEDIDO | YZ7: SALDO | ZA7: INTERES | ZB7: PAGADOS | ZC7: PENDIENTES | ZF7: CONCEDIDO | ZH7: SALDO | ZI7: INTERES | ZJ7: PAGADOS | ZK7: PENDIENTES | ZN7: CONCEDIDO | ZP7: SALDO | ZQ7: INTERES | ZR7: PAGADOS | ZS7: PENDIENTES | ZV7: CONCEDIDO | ZX7: SALDO | ZY7: INTERES | ZZ7: PAGADOS | AAA7: PENDIENTES | AAD7: CONCEDIDO | AAF7: SALDO | AAG7: INTERES | AAH7: PAGADOS | AAI7: PENDIENTES | AAL7: CONCEDIDO | AAN7: SALDO | AAO7: INTERES | AAP7: PAGADOS | AAQ7: PENDIENTES | AAT7: CONCEDIDO | AAV7: SALDO | AAW7: INTERES | AAX7: PAGADOS | AAY7: PENDIENTES | ABB7: CONCEDIDO | ABD7: SALDO | ABE7: INTERES | ABF7: PAGADOS | ABG7: PENDIENTES | ABJ7: CONCEDIDO | ABL7: SALDO | ABM7: INTERES | ABN7: PAGADOS | ABO7: PENDIENTES | ABR7: CONCEDIDO | ABT7: SALDO | ABU7: INTERES | ABV7: PAGADOS | ABW7: PENDIENTES | ABZ7: CONCEDIDO | ACB7: SALDO | ACC7: INTERES | ACD7: PAGADOS | ACE7: PENDIENTES
A8: 46023 | B8: 2000 | D8: =B8 -> 2000 | E8: 46021 | I8: 46023 | J8: 800 | L8: =J8 -> 800 | M8: 46021 | Q8: 46023 | R8: 4200 | T8: =R8 -> 4200 | U8: 46021 | Y8: 46023 | Z8: 1000 | AB8: =Z8 -> 1000 | AC8: 46021 | AG8: 46023 | AH8: 1000 | AJ8: =AH8 -> 1000 | AK8: 46021 | AO8: 46023 | AP8: 1000 | AR8: =AP8 -> 1000 | AS8: 46021 | AW8: 46023 | AX8: 1200 | AZ8: =AX8 -> 1200 | BA8: 46021 | BE8: 46023 | BF8: 5000 | BH8: =BF8 -> 5000 | BI8: 46021 | BM8: 46023 | BN8: 1000 | BP8: =BN8 -> 1000 | BQ8: 46021 | BU8: 46023 | BV8: 1500 | BX8: =BV8 -> 1500 | BY8: 46021 | CF8: =CD8 -> 0 | CG8: 46037 | CN8: =CL8 -> 0 | CO8: 46037 | CV8: =CT8 -> 0 | CW8: 46037 | DD8: =DB8 -> 0 | DE8: 46037 | DL8: =DJ8 -> 0 | DM8: 46021 | DT8: =DR8 -> 0 | DU8: 46021 | EB8: =DZ8 -> 0 | EC8: 46021 | EJ8: =EH8 -> 0 | EK8: 46021 | ER8: =EP8 -> 0 | ES8: 46021 | ET8: 0 | EZ8: =EX8 -> 0 | FA8: 46021 | FB8: 0 | FH8: =FF8 -> 0 | FI8: 46021 | FJ8: 0 | FK8: 0 | FP8: =FN8 -> 0 | FQ8: 46021 | FR8: 0 | FX8: =FV8 -> 0 | FY8: 46021 | FZ8: 0 | GA8: 0 | GF8: =GD8 -> 0 | GG8: 46021 | GN8: =GL8 -> 0 | GO8: 46037 | GV8: =GT8 -> 0 | GW8: 46037 | HD8: =HB8 -> 0 | HE8: 46037 | HL8: =HJ8 -> 0 | HM8: 46037 | HT8: =HR8 -> 0 | HU8: 46037 | IB8: =HZ8 -> 0 | IC8: 46037 | IJ8: =IH8 -> 0 | IK8: 46037 | IR8: =IP8 -> 0 | IS8: 46037 | IZ8: =IX8 -> 0 | JA8: 46037 | JH8: =JF8 -> 0 | JI8: 46037 | JP8: =JN8 -> 0 | JQ8: 46037 | JX8: =JV8 -> 0 | JY8: 46037 | KF8: =KD8 -> 0 | KG8: 46037 | KN8: =KL8 -> 0 | KO8: 46037 | KV8: =KT8 -> 0 | KW8: 46037 | LD8: =LB8 -> 0 | LE8: 46037 | LL8: =LJ8 -> 0 | LM8: 46037 | LT8: =LR8 -> 0 | LU8: 46037 | MB8: =LZ8 -> 0 | MC8: 46037 | MJ8: =MH8 -> 0 | MK8: 46037 | MR8: =MP8 -> 0 | MS8: 46037 | MZ8: =MX8 -> 0 | NA8: 46037 | NH8: =NF8 -> 0 | NI8: 46037 | NP8: =NN8 -> 0 | NQ8: 46037 | NX8: =NV8 -> 0 | NY8: 46037 | OF8: =OD8 -> 0 | OG8: 46037 | ON8: =OL8 -> 0 | OO8: 46037 | OV8: =OT8 -> 0 | OW8: 46037 | PD8: =PB8 -> 0 | PE8: 46037 | PL8: =PJ8 -> 0 | PM8: 46037 | PT8: =PR8 -> 0 | PU8: 46037 | QB8: =PZ8 -> 0 | QC8: 46037 | QJ8: =QH8 -> 0 | QK8: 46037 | QR8: =QP8 -> 0 | QS8: 46037 | QZ8: =QX8 -> 0 | RA8: 46037 | RH8: =RF8 -> 0 | RI8: 46037 | RP8: =RN8 -> 0 | RQ8: 46037 | RX8: =RV8 -> 0 | RY8: 46037 | SF8: =SD8 -> 0 | SG8: 46037 | SN8: =SL8 -> 0 | SO8: 46037 | SV8: =ST8 -> 0 | SW8: 46037 | TD8: =TB8 -> 0 | TE8: 46037 | TL8: =TJ8 -> 0 | TM8: 46037 | TT8: =TR8 -> 0 | TU8: 46037 | UB8: =TZ8 -> 0 | UC8: 46037 | UJ8: =UH8 -> 0 | UK8: 46037 | UR8: =UP8 -> 0 | US8: 46037 | UZ8: =UX8 -> 0 | VA8: 46037 | VH8: =VF8 -> 0 | VI8: 46037 | VP8: =VN8 -> 0 | VQ8: 46037 | VX8: =VV8 -> 0 | VY8: 46037 | WF8: =WD8 -> 0 | WG8: 46037 | WN8: =WL8 -> 0 | WO8: 46037 | WV8: =WT8 -> 0 | WW8: 46037 | XD8: =XB8 -> 0 | XE8: 46037 | XL8: =XJ8 -> 0 | XM8: 46037 | XT8: =XR8 -> 0 | XU8: 46037 | YB8: =XZ8 -> 0 | YC8: 46037 | YJ8: =YH8 -> 0 | YK8: 46037 | YR8: =YP8 -> 0 | YS8: 46037 | YZ8: =YX8 -> 0 | ZA8: 46037 | ZH8: =ZF8 -> 0 | ZI8: 46037 | ZP8: =ZN8 -> 0 | ZQ8: 46037 | ZX8: =ZV8 -> 0 | ZY8: 46037 | AAF8: =AAD8 -> 0 | AAG8: 46037 | AAN8: =AAL8 -> 0 | AAO8: 46037 | AAV8: =AAT8 -> 0 | AAW8: 46037 | ABD8: =ABB8 -> 0 | ABE8: 46037 | ABL8: =ABJ8 -> 0 | ABM8: 46037 | ABT8: =ABR8 -> 0 | ABU8: 46037 | ACB8: =ABZ8 -> 0 | ACC8: 46037
A9: 46037 | C9: 300 | D9: =SUM(D8,B9,-C9) -> 1700 | E9: 46037 | F9: 100 | I9: 46037 | J9: 200 | L9: =SUM(L8,J9,-K9) -> 1000 | M9: 46037 | N9: 24 | Q9: 46037 | S9: 200 | T9: =SUM(T8,R9,-S9) -> 4000 | U9: 46037 | V9: 84 | Y9: 46037 | AB9: =SUM(AB8,Z9,-AA9) -> 1000 | AC9: 46037 | AE9: 40 | AG9: 46037 | AH9: 1000 | AJ9: =SUM(AJ8,AH9,-AI9) -> 2000 | AK9: 46037 | AL9: 40 | AO9: 46037 | AP9: 0 | AQ9: 0 | AR9: =SUM(AR8,AP9,-AQ9) -> 1000 | AS9: 46037 | AU9: 35 | AW9: 46037 | AY9: 50 | AZ9: =SUM(AZ8,AX9,-AY9) -> 1150 | BA9: 46037 | BB9: 42 | BE9: 46037 | BF9: 2000 | BH9: =SUM(BH8,BF9,-BG9) -> 7000 | BI9: 46037 | BJ9: 225 | BM9: 46037 | BN9: 0 | BO9: 0 | BP9: =SUM(BP8,BN9,-BO9) -> 1000 | BQ9: 46037 | BS9: 45 | BU9: 46037 | BW9: 1500 | BX9: =SUM(BX8,BV9,-BW9) -> 0 | BY9: 46037 | BZ9: 75 | CF9: =SUM(CF8,CD9,-CE9) -> 0 | CG9: 46052 | CN9: =SUM(CN8,CL9,-CM9) -> 0 | CO9: 46052 | CV9: =SUM(CV8,CT9,-CU9) -> 0 | CW9: 46052 | DD9: =SUM(DD8,DB9,-DC9) -> 0 | DE9: 46052 | DL9: =SUM(DL8,DJ9,-DK9) -> 0 | DM9: 46037 | DT9: =SUM(DT8,DR9,-DS9) -> 0 | DU9: 46037 | EB9: =SUM(EB8,DZ9,-EA9) -> 0 | EC9: 46037 | EJ9: =SUM(EJ8,EH9,-EI9) -> 0 | EK9: 46037 | ER9: =SUM(ER8,EP9,-EQ9) -> 0 | ES9: 46037 | EZ9: =SUM(EZ8,EX9,-EY9) -> 0 | FA9: 46037 | FH9: =SUM(FH8,FF9,-FG9) -> 0 | FI9: 46037 | FP9: =SUM(FP8,FN9,-FO9) -> 0 | FQ9: 46037 | FX9: =SUM(FX8,FV9,-FW9) -> 0 | FY9: 46037 | GF9: =SUM(GF8,GD9,-GE9) -> 0 | GG9: 46037 | GH9: 0 | GN9: =SUM(GN8,GL9,-GM9) -> 0 | GO9: 46052 | GV9: =SUM(GV8,GT9,-GU9) -> 0 | GW9: 46052 | HD9: =SUM(HD8,HB9,-HC9) -> 0 | HE9: 46052 | HL9: =SUM(HL8,HJ9,-HK9) -> 0 | HM9: 46052 | HT9: =SUM(HT8,HR9,-HS9) -> 0 | HU9: 46052 | IB9: =SUM(IB8,HZ9,-IA9) -> 0 | IC9: 46052 | IJ9: =SUM(IJ8,IH9,-II9) -> 0 | IK9: 46052 | IR9: =SUM(IR8,IP9,-IQ9) -> 0 | IS9: 46052 | IZ9: =SUM(IZ8,IX9,-IY9) -> 0 | JA9: 46052 | JH9: =SUM(JH8,JF9,-JG9) -> 0 | JI9: 46052 | JP9: =SUM(JP8,JN9,-JO9) -> 0 | JQ9: 46052 | JX9: =SUM(JX8,JV9,-JW9) -> 0 | JY9: 46052 | KF9: =SUM(KF8,KD9,-KE9) -> 0 | KG9: 46052 | KN9: =SUM(KN8,KL9,-KM9) -> 0 | KO9: 46052 | KV9: =SUM(KV8,KT9,-KU9) -> 0 | KW9: 46052 | LD9: =SUM(LD8,LB9,-LC9) -> 0 | LE9: 46052 | LL9: =SUM(LL8,LJ9,-LK9) -> 0 | LM9: 46052 | LT9: =SUM(LT8,LR9,-LS9) -> 0 | LU9: 46052 | MB9: =SUM(MB8,LZ9,-MA9) -> 0 | MC9: 46052 | MJ9: =SUM(MJ8,MH9,-MI9) -> 0 | MK9: 46052 | MR9: =SUM(MR8,MP9,-MQ9) -> 0 | MS9: 46052 | MZ9: =SUM(MZ8,MX9,-MY9) -> 0 | NA9: 46052 | NH9: =SUM(NH8,NF9,-NG9) -> 0 | NI9: 46052 | NP9: =SUM(NP8,NN9,-NO9) -> 0 | NQ9: 46052 | NX9: =SUM(NX8,NV9,-NW9) -> 0 | NY9: 46052 | OF9: =SUM(OF8,OD9,-OE9) -> 0 | OG9: 46052 | ON9: =SUM(ON8,OL9,-OM9) -> 0 | OO9: 46052 | OV9: =SUM(OV8,OT9,-OU9) -> 0 | OW9: 46052 | PD9: =SUM(PD8,PB9,-PC9) -> 0 | PE9: 46052 | PL9: =SUM(PL8,PJ9,-PK9) -> 0 | PM9: 46052 | PT9: =SUM(PT8,PR9,-PS9) -> 0 | PU9: 46052 | QB9: =SUM(QB8,PZ9,-QA9) -> 0 | QC9: 46052 | QJ9: =SUM(QJ8,QH9,-QI9) -> 0 | QK9: 46052 | QR9: =SUM(QR8,QP9,-QQ9) -> 0 | QS9: 46052 | QZ9: =SUM(QZ8,QX9,-QY9) -> 0 | RA9: 46052 | RH9: =SUM(RH8,RF9,-RG9) -> 0 | RI9: 46052 | RP9: =SUM(RP8,RN9,-RO9) -> 0 | RQ9: 46052 | RX9: =SUM(RX8,RV9,-RW9) -> 0 | RY9: 46052 | SF9: =SUM(SF8,SD9,-SE9) -> 0 | SG9: 46052 | SN9: =SUM(SN8,SL9,-SM9) -> 0 | SO9: 46052 | SV9: =SUM(SV8,ST9,-SU9) -> 0 | SW9: 46052 | TD9: =SUM(TD8,TB9,-TC9) -> 0 | TE9: 46052 | TL9: =SUM(TL8,TJ9,-TK9) -> 0 | TM9: 46052 | TT9: =SUM(TT8,TR9,-TS9) -> 0 | TU9: 46052 | UB9: =SUM(UB8,TZ9,-UA9) -> 0 | UC9: 46052 | UJ9: =SUM(UJ8,UH9,-UI9) -> 0 | UK9: 46052 | UR9: =SUM(UR8,UP9,-UQ9) -> 0 | US9: 46052 | UZ9: =SUM(UZ8,UX9,-UY9) -> 0 | VA9: 46052 | VH9: =SUM(VH8,VF9,-VG9) -> 0 | VI9: 46052 | VP9: =SUM(VP8,VN9,-VO9) -> 0 | VQ9: 46052 | VX9: =SUM(VX8,VV9,-VW9) -> 0 | VY9: 46052 | WF9: =SUM(WF8,WD9,-WE9) -> 0 | WG9: 46052 | WN9: =SUM(WN8,WL9,-WM9) -> 0 | WO9: 46052 | WV9: =SUM(WV8,WT9,-WU9) -> 0 | WW9: 46052 | XD9: =SUM(XD8,XB9,-XC9) -> 0 | XE9: 46052 | XL9: =SUM(XL8,XJ9,-XK9) -> 0 | XM9: 46052 | XT9: =SUM(XT8,XR9,-XS9) -> 0 | XU9: 46052 | YB9: =SUM(YB8,XZ9,-YA9) -> 0 | YC9: 46052 | YJ9: =SUM(YJ8,YH9,-YI9) -> 0 | YK9: 46052 | YR9: =SUM(YR8,YP9,-YQ9) -> 0 | YS9: 46052 | YZ9: =SUM(YZ8,YX9,-YY9) -> 0 | ZA9: 46052 | ZH9: =SUM(ZH8,ZF9,-ZG9) -> 0 | ZI9: 46052 | ZP9: =SUM(ZP8,ZN9,-ZO9) -> 0 | ZQ9: 46052 | ZX9: =SUM(ZX8,ZV9,-ZW9) -> 0 | ZY9: 46052 | AAF9: =SUM(AAF8,AAD9,-AAE9) -> 0 | AAG9: 46052 | AAN9: =SUM(AAN8,AAL9,-AAM9) -> 0 | AAO9: 46052 | AAV9: =SUM(AAV8,AAT9,-AAU9) -> 0 | AAW9: 46052 | ABD9: =SUM(ABD8,ABB9,-ABC9) -> 0 | ABE9: 46052 | ABL9: =SUM(ABL8,ABJ9,-ABK9) -> 0 | ABM9: 46052 | ABT9: =SUM(ABT8,ABR9,-ABS9) -> 0 | ABU9: 46052 | ACB9: =SUM(ACB8,ABZ9,-ACA9) -> 0 | ACC9: 46052
D10: =SUM(D9,B10,-C10) -> 1700 | E10: 46052 | L10: =SUM(L9,J10,-K10) -> 1000 | M10: 46052 | T10: =SUM(T9,R10,-S10) -> 4000 | U10: 46052 | AB10: =SUM(AB9,Z10,-AA10) -> 1000 | AC10: 46052 | AJ10: =SUM(AJ9,AH10,-AI10) -> 2000 | AK10: 46052 | AR10: =SUM(AR9,AP10,-AQ10) -> 1000 | AS10: 46052 | AZ10: =SUM(AZ9,AX10,-AY10) -> 1150 | BA10: 46052 | BH10: =SUM(BH9,BF10,-BG10) -> 7000 | BI10: 46052 | BP10: =SUM(BP9,BN10,-BO10) -> 1000 | BQ10: 46052 | BX10: =SUM(BX9,BV10,-BW10) -> 0 | BY10: 46052 | CF10: =SUM(CF9,CD10,-CE10) -> 0 | CG10: 46068 | CN10: =SUM(CN9,CL10,-CM10) -> 0 | CO10: 46068 | CV10: =SUM(CV9,CT10,-CU10) -> 0 | CW10: 46068 | DD10: =SUM(DD9,DB10,-DC10) -> 0 | DE10: 46068 | DL10: =SUM(DL9,DJ10,-DK10) -> 0 | DM10: 46052 | DT10: =SUM(DT9,DR10,-DS10) -> 0 | DU10: 46052 | EB10: =SUM(EB9,DZ10,-EA10) -> 0 | EC10: 46052 | EJ10: =SUM(EJ9,EH10,-EI10) -> 0 | EK10: 46052 | ER10: =SUM(ER9,EP10,-EQ10) -> 0 | ES10: 46052 | EZ10: =SUM(EZ9,EX10,-EY10) -> 0 | FA10: 46052 | FH10: =SUM(FH9,FF10,-FG10) -> 0 | FI10: 46052 | FP10: =SUM(FP9,FN10,-FO10) -> 0 | FQ10: 46052 | FX10: =SUM(FX9,FV10,-FW10) -> 0 | FY10: 46052 | GF10: =SUM(GF9,GD10,-GE10) -> 0 | GG10: 46052 | GN10: =SUM(GN9,GL10,-GM10) -> 0 | GO10: 46068 | GV10: =SUM(GV9,GT10,-GU10) -> 0 | GW10: 46068 | HD10: =SUM(HD9,HB10,-HC10) -> 0 | HE10: 46068 | HL10: =SUM(HL9,HJ10,-HK10) -> 0 | HM10: 46068 | HT10: =SUM(HT9,HR10,-HS10) -> 0 | HU10: 46068 | IB10: =SUM(IB9,HZ10,-IA10) -> 0 | IC10: 46068 | IJ10: =SUM(IJ9,IH10,-II10) -> 0 | IK10: 46068 | IR10: =SUM(IR9,IP10,-IQ10) -> 0 | IS10: 46068 | IZ10: =SUM(IZ9,IX10,-IY10) -> 0 | JA10: 46068 | JH10: =SUM(JH9,JF10,-JG10) -> 0 | JI10: 46068 | JP10: =SUM(JP9,JN10,-JO10) -> 0 | JQ10: 46068 | JX10: =SUM(JX9,JV10,-JW10) -> 0 | JY10: 46068 | KF10: =SUM(KF9,KD10,-KE10) -> 0 | KG10: 46068 | KN10: =SUM(KN9,KL10,-KM10) -> 0 | KO10: 46068 | KV10: =SUM(KV9,KT10,-KU10) -> 0 | KW10: 46068 | LD10: =SUM(LD9,LB10,-LC10) -> 0 | LE10: 46068 | LL10: =SUM(LL9,LJ10,-LK10) -> 0 | LM10: 46068 | LT10: =SUM(LT9,LR10,-LS10) -> 0 | LU10: 46068 | MB10: =SUM(MB9,LZ10,-MA10) -> 0 | MC10: 46068 | MJ10: =SUM(MJ9,MH10,-MI10) -> 0 | MK10: 46068 | MR10: =SUM(MR9,MP10,-MQ10) -> 0 | MS10: 46068 | MZ10: =SUM(MZ9,MX10,-MY10) -> 0 | NA10: 46068 | NH10: =SUM(NH9,NF10,-NG10) -> 0 | NI10: 46068 | NP10: =SUM(NP9,NN10,-NO10) -> 0 | NQ10: 46068 | NX10: =SUM(NX9,NV10,-NW10) -> 0 | NY10: 46068 | OF10: =SUM(OF9,OD10,-OE10) -> 0 | OG10: 46068 | ON10: =SUM(ON9,OL10,-OM10) -> 0 | OO10: 46068 | OV10: =SUM(OV9,OT10,-OU10) -> 0 | OW10: 46068 | PD10: =SUM(PD9,PB10,-PC10) -> 0 | PE10: 46068 | PL10: =SUM(PL9,PJ10,-PK10) -> 0 | PM10: 46068 | PT10: =SUM(PT9,PR10,-PS10) -> 0 | PU10: 46068 | QB10: =SUM(QB9,PZ10,-QA10) -> 0 | QC10: 46068 | QJ10: =SUM(QJ9,QH10,-QI10) -> 0 | QK10: 46068 | QR10: =SUM(QR9,QP10,-QQ10) -> 0 | QS10: 46068 | QZ10: =SUM(QZ9,QX10,-QY10) -> 0 | RA10: 46068 | RH10: =SUM(RH9,RF10,-RG10) -> 0 | RI10: 46068 | RP10: =SUM(RP9,RN10,-RO10) -> 0 | RQ10: 46068 | RX10: =SUM(RX9,RV10,-RW10) -> 0 | RY10: 46068 | SF10: =SUM(SF9,SD10,-SE10) -> 0 | SG10: 46068 | SN10: =SUM(SN9,SL10,-SM10) -> 0 | SO10: 46068 | SV10: =SUM(SV9,ST10,-SU10) -> 0 | SW10: 46068 | TD10: =SUM(TD9,TB10,-TC10) -> 0 | TE10: 46068 | TL10: =SUM(TL9,TJ10,-TK10) -> 0 | TM10: 46068 | TT10: =SUM(TT9,TR10,-TS10) -> 0 | TU10: 46068 | UB10: =SUM(UB9,TZ10,-UA10) -> 0 | UC10: 46068 | UJ10: =SUM(UJ9,UH10,-UI10) -> 0 | UK10: 46068 | UR10: =SUM(UR9,UP10,-UQ10) -> 0 | US10: 46068 | UZ10: =SUM(UZ9,UX10,-UY10) -> 0 | VA10: 46068 | VH10: =SUM(VH9,VF10,-VG10) -> 0 | VI10: 46068 | VP10: =SUM(VP9,VN10,-VO10) -> 0 | VQ10: 46068 | VX10: =SUM(VX9,VV10,-VW10) -> 0 | VY10: 46068 | WF10: =SUM(WF9,WD10,-WE10) -> 0 | WG10: 46068 | WN10: =SUM(WN9,WL10,-WM10) -> 0 | WO10: 46068 | WV10: =SUM(WV9,WT10,-WU10) -> 0 | WW10: 46068 | XD10: =SUM(XD9,XB10,-XC10) -> 0 | XE10: 46068 | XL10: =SUM(XL9,XJ10,-XK10) -> 0 | XM10: 46068 | XT10: =SUM(XT9,XR10,-XS10) -> 0 | XU10: 46068 | YB10: =SUM(YB9,XZ10,-YA10) -> 0 | YC10: 46068 | YJ10: =SUM(YJ9,YH10,-YI10) -> 0 | YK10: 46068 | YR10: =SUM(YR9,YP10,-YQ10) -> 0 | YS10: 46068 | YZ10: =SUM(YZ9,YX10,-YY10) -> 0 | ZA10: 46068 | ZH10: =SUM(ZH9,ZF10,-ZG10) -> 0 | ZI10: 46068 | ZP10: =SUM(ZP9,ZN10,-ZO10) -> 0 | ZQ10: 46068 | ZX10: =SUM(ZX9,ZV10,-ZW10) -> 0 | ZY10: 46068 | AAF10: =SUM(AAF9,AAD10,-AAE10) -> 0 | AAG10: 46068 | AAN10: =SUM(AAN9,AAL10,-AAM10) -> 0 | AAO10: 46068 | AAV10: =SUM(AAV9,AAT10,-AAU10) -> 0 | AAW10: 46068 | ABD10: =SUM(ABD9,ABB10,-ABC10) -> 0 | ABE10: 46068 | ABL10: =SUM(ABL9,ABJ10,-ABK10) -> 0 | ABM10: 46068 | ABT10: =SUM(ABT9,ABR10,-ABS10) -> 0 | ABU10: 46068 | ACB10: =SUM(ACB9,ABZ10,-ACA10) -> 0 | ACC10: 46068
D11: =SUM(D10,B11,-C11) -> 1700 | E11: 46068 | L11: =SUM(L10,J11,-K11) -> 1000 | M11: 46068 | T11: =SUM(T10,R11,-S11) -> 4000 | U11: 46068 | AB11: =SUM(AB10,Z11,-AA11) -> 1000 | AC11: 46068 | AJ11: =SUM(AJ10,AH11,-AI11) -> 2000 | AK11: 46068 | AR11: =SUM(AR10,AP11,-AQ11) -> 1000 | AS11: 46068 | AZ11: =SUM(AZ10,AX11,-AY11) -> 1150 | BA11: 46068 | BH11: =SUM(BH10,BF11,-BG11) -> 7000 | BI11: 46068 | BP11: =SUM(BP10,BN11,-BO11) -> 1000 | BQ11: 46068 | BX11: =SUM(BX10,BV11,-BW11) -> 0 | BY11: 46068 | CF11: =SUM(CF10,CD11,-CE11) -> 0 | CG11: 46081 | CN11: =SUM(CN10,CL11,-CM11) -> 0 | CO11: 46081 | CV11: =SUM(CV10,CT11,-CU11) -> 0 | CW11: 46081 | DD11: =SUM(DD10,DB11,-DC11) -> 0 | DE11: 46081 | DL11: =SUM(DL10,DJ11,-DK11) -> 0 | DM11: 46068 | DT11: =SUM(DT10,DR11,-DS11) -> 0 | DU11: 46068 | EB11: =SUM(EB10,DZ11,-EA11) -> 0 | EC11: 46068 | EJ11: =SUM(EJ10,EH11,-EI11) -> 0 | EK11: 46068 | ER11: =SUM(ER10,EP11,-EQ11) -> 0 | ES11: 46068 | EZ11: =SUM(EZ10,EX11,-EY11) -> 0 | FA11: 46068 | FH11: =SUM(FH10,FF11,-FG11) -> 0 | FI11: 46068 | FP11: =SUM(FP10,FN11,-FO11) -> 0 | FQ11: 46068 | FX11: =SUM(FX10,FV11,-FW11) -> 0 | FY11: 46068 | GF11: =SUM(GF10,GD11,-GE11) -> 0 | GG11: 46068 | GN11: =SUM(GN10,GL11,-GM11) -> 0 | GO11: 46081 | GV11: =SUM(GV10,GT11,-GU11) -> 0 | GW11: 46081 | HD11: =SUM(HD10,HB11,-HC11) -> 0 | HE11: 46081 | HL11: =SUM(HL10,HJ11,-HK11) -> 0 | HM11: 46081 | HT11: =SUM(HT10,HR11,-HS11) -> 0 | HU11: 46081 | IB11: =SUM(IB10,HZ11,-IA11) -> 0 | IC11: 46081 | IJ11: =SUM(IJ10,IH11,-II11) -> 0 | IK11: 46081 | IR11: =SUM(IR10,IP11,-IQ11) -> 0 | IS11: 46081 | IZ11: =SUM(IZ10,IX11,-IY11) -> 0 | JA11: 46081 | JH11: =SUM(JH10,JF11,-JG11) -> 0 | JI11: 46081 | JP11: =SUM(JP10,JN11,-JO11) -> 0 | JQ11: 46081 | JX11: =SUM(JX10,JV11,-JW11) -> 0 | JY11: 46081 | KF11: =SUM(KF10,KD11,-KE11) -> 0 | KG11: 46081 | KN11: =SUM(KN10,KL11,-KM11) -> 0 | KO11: 46081 | KV11: =SUM(KV10,KT11,-KU11) -> 0 | KW11: 46081 | LD11: =SUM(LD10,LB11,-LC11) -> 0 | LE11: 46081 | LL11: =SUM(LL10,LJ11,-LK11) -> 0 | LM11: 46081 | LT11: =SUM(LT10,LR11,-LS11) -> 0 | LU11: 46081 | MB11: =SUM(MB10,LZ11,-MA11) -> 0 | MC11: 46081 | MJ11: =SUM(MJ10,MH11,-MI11) -> 0 | MK11: 46081 | MR11: =SUM(MR10,MP11,-MQ11) -> 0 | MS11: 46081 | MZ11: =SUM(MZ10,MX11,-MY11) -> 0 | NA11: 46081 | NH11: =SUM(NH10,NF11,-NG11) -> 0 | NI11: 46081 | NP11: =SUM(NP10,NN11,-NO11) -> 0 | NQ11: 46081 | NX11: =SUM(NX10,NV11,-NW11) -> 0 | NY11: 46081 | OF11: =SUM(OF10,OD11,-OE11) -> 0 | OG11: 46081 | ON11: =SUM(ON10,OL11,-OM11) -> 0 | OO11: 46081 | OV11: =SUM(OV10,OT11,-OU11) -> 0 | OW11: 46081 | PD11: =SUM(PD10,PB11,-PC11) -> 0 | PE11: 46081 | PL11: =SUM(PL10,PJ11,-PK11) -> 0 | PM11: 46081 | PT11: =SUM(PT10,PR11,-PS11) -> 0 | PU11: 46081 | QB11: =SUM(QB10,PZ11,-QA11) -> 0 | QC11: 46081 | QJ11: =SUM(QJ10,QH11,-QI11) -> 0 | QK11: 46081 | QR11: =SUM(QR10,QP11,-QQ11) -> 0 | QS11: 46081 | QZ11: =SUM(QZ10,QX11,-QY11) -> 0 | RA11: 46081 | RH11: =SUM(RH10,RF11,-RG11) -> 0 | RI11: 46081 | RP11: =SUM(RP10,RN11,-RO11) -> 0 | RQ11: 46081 | RX11: =SUM(RX10,RV11,-RW11) -> 0 | RY11: 46081 | SF11: =SUM(SF10,SD11,-SE11) -> 0 | SG11: 46081 | SN11: =SUM(SN10,SL11,-SM11) -> 0 | SO11: 46081 | SV11: =SUM(SV10,ST11,-SU11) -> 0 | SW11: 46081 | TD11: =SUM(TD10,TB11,-TC11) -> 0 | TE11: 46081 | TL11: =SUM(TL10,TJ11,-TK11) -> 0 | TM11: 46081 | TT11: =SUM(TT10,TR11,-TS11) -> 0 | TU11: 46081 | UB11: =SUM(UB10,TZ11,-UA11) -> 0 | UC11: 46081 | UJ11: =SUM(UJ10,UH11,-UI11) -> 0 | UK11: 46081 | UR11: =SUM(UR10,UP11,-UQ11) -> 0 | US11: 46081 | UZ11: =SUM(UZ10,UX11,-UY11) -> 0 | VA11: 46081 | VH11: =SUM(VH10,VF11,-VG11) -> 0 | VI11: 46081 | VP11: =SUM(VP10,VN11,-VO11) -> 0 | VQ11: 46081 | VX11: =SUM(VX10,VV11,-VW11) -> 0 | VY11: 46081 | WF11: =SUM(WF10,WD11,-WE11) -> 0 | WG11: 46081 | WN11: =SUM(WN10,WL11,-WM11) -> 0 | WO11: 46081 | WV11: =SUM(WV10,WT11,-WU11) -> 0 | WW11: 46081 | XD11: =SUM(XD10,XB11,-XC11) -> 0 | XE11: 46081 | XL11: =SUM(XL10,XJ11,-XK11) -> 0 | XM11: 46081 | XT11: =SUM(XT10,XR11,-XS11) -> 0 | XU11: 46081 | YB11: =SUM(YB10,XZ11,-YA11) -> 0 | YC11: 46081 | YJ11: =SUM(YJ10,YH11,-YI11) -> 0 | YK11: 46081 | YR11: =SUM(YR10,YP11,-YQ11) -> 0 | YS11: 46081 | YZ11: =SUM(YZ10,YX11,-YY11) -> 0 | ZA11: 46081 | ZH11: =SUM(ZH10,ZF11,-ZG11) -> 0 | ZI11: 46081 | ZP11: =SUM(ZP10,ZN11,-ZO11) -> 0 | ZQ11: 46081 | ZX11: =SUM(ZX10,ZV11,-ZW11) -> 0 | ZY11: 46081 | AAF11: =SUM(AAF10,AAD11,-AAE11) -> 0 | AAG11: 46081 | AAN11: =SUM(AAN10,AAL11,-AAM11) -> 0 | AAO11: 46081 | AAV11: =SUM(AAV10,AAT11,-AAU11) -> 0 | AAW11: 46081 | ABD11: =SUM(ABD10,ABB11,-ABC11) -> 0 | ABE11: 46081 | ABL11: =SUM(ABL10,ABJ11,-ABK11) -> 0 | ABM11: 46081 | ABT11: =SUM(ABT10,ABR11,-ABS11) -> 0 | ABU11: 46081 | ACB11: =SUM(ACB10,ABZ11,-ACA11) -> 0 | ACC11: 46081
D12: =SUM(D11,B12,-C12) -> 1700 | E12: 46081 | L12: =SUM(L11,J12,-K12) -> 1000 | M12: 46081 | T12: =SUM(T11,R12,-S12) -> 4000 | U12: 46081 | AB12: =SUM(AB11,Z12,-AA12) -> 1000 | AC12: 46081 | AJ12: =SUM(AJ11,AH12,-AI12) -> 2000 | AK12: 46081 | AR12: =SUM(AR11,AP12,-AQ12) -> 1000 | AS12: 46081 | AZ12: =SUM(AZ11,AX12,-AY12) -> 1150 | BA12: 46081 | BH12: =SUM(BH11,BF12,-BG12) -> 7000 | BI12: 46081 | BP12: =SUM(BP11,BN12,-BO12) -> 1000 | BQ12: 46081 | BX12: =SUM(BX11,BV12,-BW12) -> 0 | BY12: 46081 | CF12: =SUM(CF11,CD12,-CE12) -> 0 | CG12: 46096 | CN12: =SUM(CN11,CL12,-CM12) -> 0 | CO12: 46096 | CV12: =SUM(CV11,CT12,-CU12) -> 0 | CW12: 46096 | DD12: =SUM(DD11,DB12,-DC12) -> 0 | DE12: 46096 | DL12: =SUM(DL11,DJ12,-DK12) -> 0 | DM12: 46081 | DT12: =SUM(DT11,DR12,-DS12) -> 0 | DU12: 46081 | EB12: =SUM(EB11,DZ12,-EA12) -> 0 | EC12: 46081 | EJ12: =SUM(EJ11,EH12,-EI12) -> 0 | EK12: 46081 | ER12: =SUM(ER11,EP12,-EQ12) -> 0 | ES12: 46081 | EZ12: =SUM(EZ11,EX12,-EY12) -> 0 | FA12: 46081 | FH12: =SUM(FH11,FF12,-FG12) -> 0 | FI12: 46081 | FP12: =SUM(FP11,FN12,-FO12) -> 0 | FQ12: 46081 | FX12: =SUM(FX11,FV12,-FW12) -> 0 | FY12: 46081 | GF12: =SUM(GF11,GD12,-GE12) -> 0 | GG12: 46081 | GN12: =SUM(GN11,GL12,-GM12) -> 0 | GO12: 46096 | GV12: =SUM(GV11,GT12,-GU12) -> 0 | GW12: 46096 | HD12: =SUM(HD11,HB12,-HC12) -> 0 | HE12: 46096 | HL12: =SUM(HL11,HJ12,-HK12) -> 0 | HM12: 46096 | HT12: =SUM(HT11,HR12,-HS12) -> 0 | HU12: 46096 | IB12: =SUM(IB11,HZ12,-IA12) -> 0 | IC12: 46096 | IJ12: =SUM(IJ11,IH12,-II12) -> 0 | IK12: 46096 | IR12: =SUM(IR11,IP12,-IQ12) -> 0 | IS12: 46096 | IZ12: =SUM(IZ11,IX12,-IY12) -> 0 | JA12: 46096 | JH12: =SUM(JH11,JF12,-JG12) -> 0 | JI12: 46096 | JP12: =SUM(JP11,JN12,-JO12) -> 0 | JQ12: 46096 | JX12: =SUM(JX11,JV12,-JW12) -> 0 | JY12: 46096 | KF12: =SUM(KF11,KD12,-KE12) -> 0 | KG12: 46096 | KN12: =SUM(KN11,KL12,-KM12) -> 0 | KO12: 46096 | KV12: =SUM(KV11,KT12,-KU12) -> 0 | KW12: 46096 | LD12: =SUM(LD11,LB12,-LC12) -> 0 | LE12: 46096 | LL12: =SUM(LL11,LJ12,-LK12) -> 0 | LM12: 46096 | LT12: =SUM(LT11,LR12,-LS12) -> 0 | LU12: 46096 | MB12: =SUM(MB11,LZ12,-MA12) -> 0 | MC12: 46096 | MJ12: =SUM(MJ11,MH12,-MI12) -> 0 | MK12: 46096 | MR12: =SUM(MR11,MP12,-MQ12) -> 0 | MS12: 46096 | MZ12: =SUM(MZ11,MX12,-MY12) -> 0 | NA12: 46096 | NH12: =SUM(NH11,NF12,-NG12) -> 0 | NI12: 46096 | NP12: =SUM(NP11,NN12,-NO12) -> 0 | NQ12: 46096 | NX12: =SUM(NX11,NV12,-NW12) -> 0 | NY12: 46096 | OF12: =SUM(OF11,OD12,-OE12) -> 0 | OG12: 46096 | ON12: =SUM(ON11,OL12,-OM12) -> 0 | OO12: 46096 | OV12: =SUM(OV11,OT12,-OU12) -> 0 | OW12: 46096 | PD12: =SUM(PD11,PB12,-PC12) -> 0 | PE12: 46096 | PL12: =SUM(PL11,PJ12,-PK12) -> 0 | PM12: 46096 | PT12: =SUM(PT11,PR12,-PS12) -> 0 | PU12: 46096 | QB12: =SUM(QB11,PZ12,-QA12) -> 0 | QC12: 46096 | QJ12: =SUM(QJ11,QH12,-QI12) -> 0 | QK12: 46096 | QR12: =SUM(QR11,QP12,-QQ12) -> 0 | QS12: 46096 | QZ12: =SUM(QZ11,QX12,-QY12) -> 0 | RA12: 46096 | RH12: =SUM(RH11,RF12,-RG12) -> 0 | RI12: 46096 | RP12: =SUM(RP11,RN12,-RO12) -> 0 | RQ12: 46096 | RX12: =SUM(RX11,RV12,-RW12) -> 0 | RY12: 46096 | SF12: =SUM(SF11,SD12,-SE12) -> 0 | SG12: 46096 | SN12: =SUM(SN11,SL12,-SM12) -> 0 | SO12: 46096 | SV12: =SUM(SV11,ST12,-SU12) -> 0 | SW12: 46096 | TD12: =SUM(TD11,TB12,-TC12) -> 0 | TE12: 46096 | TL12: =SUM(TL11,TJ12,-TK12) -> 0 | TM12: 46096 | TT12: =SUM(TT11,TR12,-TS12) -> 0 | TU12: 46096 | UB12: =SUM(UB11,TZ12,-UA12) -> 0 | UC12: 46096 | UJ12: =SUM(UJ11,UH12,-UI12) -> 0 | UK12: 46096 | UR12: =SUM(UR11,UP12,-UQ12) -> 0 | US12: 46096 | UZ12: =SUM(UZ11,UX12,-UY12) -> 0 | VA12: 46096 | VH12: =SUM(VH11,VF12,-VG12) -> 0 | VI12: 46096 | VP12: =SUM(VP11,VN12,-VO12) -> 0 | VQ12: 46096 | VX12: =SUM(VX11,VV12,-VW12) -> 0 | VY12: 46096 | WF12: =SUM(WF11,WD12,-WE12) -> 0 | WG12: 46096 | WN12: =SUM(WN11,WL12,-WM12) -> 0 | WO12: 46096 | WV12: =SUM(WV11,WT12,-WU12) -> 0 | WW12: 46096 | XD12: =SUM(XD11,XB12,-XC12) -> 0 | XE12: 46096 | XL12: =SUM(XL11,XJ12,-XK12) -> 0 | XM12: 46096 | XT12: =SUM(XT11,XR12,-XS12) -> 0 | XU12: 46096 | YB12: =SUM(YB11,XZ12,-YA12) -> 0 | YC12: 46096 | YJ12: =SUM(YJ11,YH12,-YI12) -> 0 | YK12: 46096 | YR12: =SUM(YR11,YP12,-YQ12) -> 0 | YS12: 46096 | YZ12: =SUM(YZ11,YX12,-YY12) -> 0 | ZA12: 46096 | ZH12: =SUM(ZH11,ZF12,-ZG12) -> 0 | ZI12: 46096 | ZP12: =SUM(ZP11,ZN12,-ZO12) -> 0 | ZQ12: 46096 | ZX12: =SUM(ZX11,ZV12,-ZW12) -> 0 | ZY12: 46096 | AAF12: =SUM(AAF11,AAD12,-AAE12) -> 0 | AAG12: 46096 | AAN12: =SUM(AAN11,AAL12,-AAM12) -> 0 | AAO12: 46096 | AAV12: =SUM(AAV11,AAT12,-AAU12) -> 0 | AAW12: 46096 | ABD12: =SUM(ABD11,ABB12,-ABC12) -> 0 | ABE12: 46096 | ABL12: =SUM(ABL11,ABJ12,-ABK12) -> 0 | ABM12: 46096 | ABT12: =SUM(ABT11,ABR12,-ABS12) -> 0 | ABU12: 46096 | ACB12: =SUM(ACB11,ABZ12,-ACA12) -> 0 | ACC12: 46096
D13: =SUM(D12,B13,-C13) -> 1700 | E13: 46096 | L13: =SUM(L12,J13,-K13) -> 1000 | M13: 46096 | T13: =SUM(T12,R13,-S13) -> 4000 | U13: 46096 | AB13: =SUM(AB12,Z13,-AA13) -> 1000 | AC13: 46096 | AJ13: =SUM(AJ12,AH13,-AI13) -> 2000 | AK13: 46096 | AR13: =SUM(AR12,AP13,-AQ13) -> 1000 | AS13: 46096 | AZ13: =SUM(AZ12,AX13,-AY13) -> 1150 | BA13: 46096 | BH13: =SUM(BH12,BF13,-BG13) -> 7000 | BI13: 46096 | BP13: =SUM(BP12,BN13,-BO13) -> 1000 | BQ13: 46096 | BX13: =SUM(BX12,BV13,-BW13) -> 0 | BY13: 46096 | CF13: =SUM(CF12,CD13,-CE13) -> 0 | CG13: 46111 | CN13: =SUM(CN12,CL13,-CM13) -> 0 | CO13: 46111 | CV13: =SUM(CV12,CT13,-CU13) -> 0 | CW13: 46111 | DD13: =SUM(DD12,DB13,-DC13) -> 0 | DE13: 46111 | DL13: =SUM(DL12,DJ13,-DK13) -> 0 | DM13: 46096 | DT13: =SUM(DT12,DR13,-DS13) -> 0 | DU13: 46096 | EB13: =SUM(EB12,DZ13,-EA13) -> 0 | EC13: 46096 | EJ13: =SUM(EJ12,EH13,-EI13) -> 0 | EK13: 46096 | ER13: =SUM(ER12,EP13,-EQ13) -> 0 | ES13: 46096 | EZ13: =SUM(EZ12,EX13,-EY13) -> 0 | FA13: 46096 | FH13: =SUM(FH12,FF13,-FG13) -> 0 | FI13: 46096 | FP13: =SUM(FP12,FN13,-FO13) -> 0 | FQ13: 46096 | FX13: =SUM(FX12,FV13,-FW13) -> 0 | FY13: 46096 | GF13: =SUM(GF12,GD13,-GE13) -> 0 | GG13: 46096 | GN13: =SUM(GN12,GL13,-GM13) -> 0 | GO13: 46111 | GV13: =SUM(GV12,GT13,-GU13) -> 0 | GW13: 46111 | HD13: =SUM(HD12,HB13,-HC13) -> 0 | HE13: 46111 | HL13: =SUM(HL12,HJ13,-HK13) -> 0 | HM13: 46111 | HT13: =SUM(HT12,HR13,-HS13) -> 0 | HU13: 46111 | IB13: =SUM(IB12,HZ13,-IA13) -> 0 | IC13: 46111 | IJ13: =SUM(IJ12,IH13,-II13) -> 0 | IK13: 46111 | IR13: =SUM(IR12,IP13,-IQ13) -> 0 | IS13: 46111 | IZ13: =SUM(IZ12,IX13,-IY13) -> 0 | JA13: 46111 | JH13: =SUM(JH12,JF13,-JG13) -> 0 | JI13: 46111 | JP13: =SUM(JP12,JN13,-JO13) -> 0 | JQ13: 46111 | JX13: =SUM(JX12,JV13,-JW13) -> 0 | JY13: 46111 | KF13: =SUM(KF12,KD13,-KE13) -> 0 | KG13: 46111 | KN13: =SUM(KN12,KL13,-KM13) -> 0 | KO13: 46111 | KV13: =SUM(KV12,KT13,-KU13) -> 0 | KW13: 46111 | LD13: =SUM(LD12,LB13,-LC13) -> 0 | LE13: 46111 | LL13: =SUM(LL12,LJ13,-LK13) -> 0 | LM13: 46111 | LT13: =SUM(LT12,LR13,-LS13) -> 0 | LU13: 46111 | MB13: =SUM(MB12,LZ13,-MA13) -> 0 | MC13: 46111 | MJ13: =SUM(MJ12,MH13,-MI13) -> 0 | MK13: 46111 | MR13: =SUM(MR12,MP13,-MQ13) -> 0 | MS13: 46111 | MZ13: =SUM(MZ12,MX13,-MY13) -> 0 | NA13: 46111 | NH13: =SUM(NH12,NF13,-NG13) -> 0 | NI13: 46111 | NP13: =SUM(NP12,NN13,-NO13) -> 0 | NQ13: 46111 | NX13: =SUM(NX12,NV13,-NW13) -> 0 | NY13: 46111 | OF13: =SUM(OF12,OD13,-OE13) -> 0 | OG13: 46111 | ON13: =SUM(ON12,OL13,-OM13) -> 0 | OO13: 46111 | OV13: =SUM(OV12,OT13,-OU13) -> 0 | OW13: 46111 | PD13: =SUM(PD12,PB13,-PC13) -> 0 | PE13: 46111 | PL13: =SUM(PL12,PJ13,-PK13) -> 0 | PM13: 46111 | PT13: =SUM(PT12,PR13,-PS13) -> 0 | PU13: 46111 | QB13: =SUM(QB12,PZ13,-QA13) -> 0 | QC13: 46111 | QJ13: =SUM(QJ12,QH13,-QI13) -> 0 | QK13: 46111 | QR13: =SUM(QR12,QP13,-QQ13) -> 0 | QS13: 46111 | QZ13: =SUM(QZ12,QX13,-QY13) -> 0 | RA13: 46111 | RH13: =SUM(RH12,RF13,-RG13) -> 0 | RI13: 46111 | RP13: =SUM(RP12,RN13,-RO13) -> 0 | RQ13: 46111 | RX13: =SUM(RX12,RV13,-RW13) -> 0 | RY13: 46111 | SF13: =SUM(SF12,SD13,-SE13) -> 0 | SG13: 46111 | SN13: =SUM(SN12,SL13,-SM13) -> 0 | SO13: 46111 | SV13: =SUM(SV12,ST13,-SU13) -> 0 | SW13: 46111 | TD13: =SUM(TD12,TB13,-TC13) -> 0 | TE13: 46111 | TL13: =SUM(TL12,TJ13,-TK13) -> 0 | TM13: 46111 | TT13: =SUM(TT12,TR13,-TS13) -> 0 | TU13: 46111 | UB13: =SUM(UB12,TZ13,-UA13) -> 0 | UC13: 46111 | UJ13: =SUM(UJ12,UH13,-UI13) -> 0 | UK13: 46111 | UR13: =SUM(UR12,UP13,-UQ13) -> 0 | US13: 46111 | UZ13: =SUM(UZ12,UX13,-UY13) -> 0 | VA13: 46111 | VH13: =SUM(VH12,VF13,-VG13) -> 0 | VI13: 46111 | VP13: =SUM(VP12,VN13,-VO13) -> 0 | VQ13: 46111 | VX13: =SUM(VX12,VV13,-VW13) -> 0 | VY13: 46111 | WF13: =SUM(WF12,WD13,-WE13) -> 0 | WG13: 46111 | WN13: =SUM(WN12,WL13,-WM13) -> 0 | WO13: 46111 | WV13: =SUM(WV12,WT13,-WU13) -> 0 | WW13: 46111 | XD13: =SUM(XD12,XB13,-XC13) -> 0 | XE13: 46111 | XL13: =SUM(XL12,XJ13,-XK13) -> 0 | XM13: 46111 | XT13: =SUM(XT12,XR13,-XS13) -> 0 | XU13: 46111 | YB13: =SUM(YB12,XZ13,-YA13) -> 0 | YC13: 46111 | YJ13: =SUM(YJ12,YH13,-YI13) -> 0 | YK13: 46111 | YR13: =SUM(YR12,YP13,-YQ13) -> 0 | YS13: 46111 | YZ13: =SUM(YZ12,YX13,-YY13) -> 0 | ZA13: 46111 | ZH13: =SUM(ZH12,ZF13,-ZG13) -> 0 | ZI13: 46111 | ZP13: =SUM(ZP12,ZN13,-ZO13) -> 0 | ZQ13: 46111 | ZX13: =SUM(ZX12,ZV13,-ZW13) -> 0 | ZY13: 46111 | AAF13: =SUM(AAF12,AAD13,-AAE13) -> 0 | AAG13: 46111 | AAN13: =SUM(AAN12,AAL13,-AAM13) -> 0 | AAO13: 46111 | AAV13: =SUM(AAV12,AAT13,-AAU13) -> 0 | AAW13: 46111 | ABD13: =SUM(ABD12,ABB13,-ABC13) -> 0 | ABE13: 46111 | ABL13: =SUM(ABL12,ABJ13,-ABK13) -> 0 | ABM13: 46111 | ABT13: =SUM(ABT12,ABR13,-ABS13) -> 0 | ABU13: 46111 | ACB13: =SUM(ACB12,ABZ13,-ACA13) -> 0 | ACC13: 46111
D14: =SUM(D13,B14,-C14) -> 1700 | E14: 46111 | L14: =SUM(L13,J14,-K14) -> 1000 | M14: 46111 | T14: =SUM(T13,R14,-S14) -> 4000 | U14: 46111 | AB14: =SUM(AB13,Z14,-AA14) -> 1000 | AC14: 46111 | AJ14: =SUM(AJ13,AH14,-AI14) -> 2000 | AK14: 46111 | AR14: =SUM(AR13,AP14,-AQ14) -> 1000 | AS14: 46111 | AZ14: =SUM(AZ13,AX14,-AY14) -> 1150 | BA14: 46111 | BH14: =SUM(BH13,BF14,-BG14) -> 7000 | BI14: 46111 | BP14: =SUM(BP13,BN14,-BO14) -> 1000 | BQ14: 46111 | BX14: =SUM(BX13,BV14,-BW14) -> 0 | BY14: 46111 | CF14: =SUM(CF13,CD14,-CE14) -> 0 | CG14: 46127 | CN14: =SUM(CN13,CL14,-CM14) -> 0 | CO14: 46127 | CV14: =SUM(CV13,CT14,-CU14) -> 0 | CW14: 46127 | DD14: =SUM(DD13,DB14,-DC14) -> 0 | DE14: 46127 | DL14: =SUM(DL13,DJ14,-DK14) -> 0 | DM14: 46111 | DT14: =SUM(DT13,DR14,-DS14) -> 0 | DU14: 46111 | EB14: =SUM(EB13,DZ14,-EA14) -> 0 | EC14: 46111 | EJ14: =SUM(EJ13,EH14,-EI14) -> 0 | EK14: 46111 | ER14: =SUM(ER13,EP14,-EQ14) -> 0 | ES14: 46111 | EZ14: =SUM(EZ13,EX14,-EY14) -> 0 | FA14: 46111 | FH14: =SUM(FH13,FF14,-FG14) -> 0 | FI14: 46111 | FP14: =SUM(FP13,FN14,-FO14) -> 0 | FQ14: 46111 | FX14: =SUM(FX13,FV14,-FW14) -> 0 | FY14: 46111 | GF14: =SUM(GF13,GD14,-GE14) -> 0 | GG14: 46111 | GN14: =SUM(GN13,GL14,-GM14) -> 0 | GO14: 46127 | GV14: =SUM(GV13,GT14,-GU14) -> 0 | GW14: 46127 | HD14: =SUM(HD13,HB14,-HC14) -> 0 | HE14: 46127 | HL14: =SUM(HL13,HJ14,-HK14) -> 0 | HM14: 46127 | HT14: =SUM(HT13,HR14,-HS14) -> 0 | HU14: 46127 | IB14: =SUM(IB13,HZ14,-IA14) -> 0 | IC14: 46127 | IJ14: =SUM(IJ13,IH14,-II14) -> 0 | IK14: 46127 | IR14: =SUM(IR13,IP14,-IQ14) -> 0 | IS14: 46127 | IZ14: =SUM(IZ13,IX14,-IY14) -> 0 | JA14: 46127 | JH14: =SUM(JH13,JF14,-JG14) -> 0 | JI14: 46127 | JP14: =SUM(JP13,JN14,-JO14) -> 0 | JQ14: 46127 | JX14: =SUM(JX13,JV14,-JW14) -> 0 | JY14: 46127 | KF14: =SUM(KF13,KD14,-KE14) -> 0 | KG14: 46127 | KN14: =SUM(KN13,KL14,-KM14) -> 0 | KO14: 46127 | KV14: =SUM(KV13,KT14,-KU14) -> 0 | KW14: 46127 | LD14: =SUM(LD13,LB14,-LC14) -> 0 | LE14: 46127 | LL14: =SUM(LL13,LJ14,-LK14) -> 0 | LM14: 46127 | LT14: =SUM(LT13,LR14,-LS14) -> 0 | LU14: 46127 | MB14: =SUM(MB13,LZ14,-MA14) -> 0 | MC14: 46127 | MJ14: =SUM(MJ13,MH14,-MI14) -> 0 | MK14: 46127 | MR14: =SUM(MR13,MP14,-MQ14) -> 0 | MS14: 46127 | MZ14: =SUM(MZ13,MX14,-MY14) -> 0 | NA14: 46127 | NH14: =SUM(NH13,NF14,-NG14) -> 0 | NI14: 46127 | NP14: =SUM(NP13,NN14,-NO14) -> 0 | NQ14: 46127 | NX14: =SUM(NX13,NV14,-NW14) -> 0 | NY14: 46127 | OF14: =SUM(OF13,OD14,-OE14) -> 0 | OG14: 46127 | ON14: =SUM(ON13,OL14,-OM14) -> 0 | OO14: 46127 | OV14: =SUM(OV13,OT14,-OU14) -> 0 | OW14: 46127 | PD14: =SUM(PD13,PB14,-PC14) -> 0 | PE14: 46127 | PL14: =SUM(PL13,PJ14,-PK14) -> 0 | PM14: 46127 | PT14: =SUM(PT13,PR14,-PS14) -> 0 | PU14: 46127 | QB14: =SUM(QB13,PZ14,-QA14) -> 0 | QC14: 46127 | QJ14: =SUM(QJ13,QH14,-QI14) -> 0 | QK14: 46127 | QR14: =SUM(QR13,QP14,-QQ14) -> 0 | QS14: 46127 | QZ14: =SUM(QZ13,QX14,-QY14) -> 0 | RA14: 46127 | RH14: =SUM(RH13,RF14,-RG14) -> 0 | RI14: 46127 | RP14: =SUM(RP13,RN14,-RO14) -> 0 | RQ14: 46127 | RX14: =SUM(RX13,RV14,-RW14) -> 0 | RY14: 46127 | SF14: =SUM(SF13,SD14,-SE14) -> 0 | SG14: 46127 | SN14: =SUM(SN13,SL14,-SM14) -> 0 | SO14: 46127 | SV14: =SUM(SV13,ST14,-SU14) -> 0 | SW14: 46127 | TD14: =SUM(TD13,TB14,-TC14) -> 0 | TE14: 46127 | TL14: =SUM(TL13,TJ14,-TK14) -> 0 | TM14: 46127 | TT14: =SUM(TT13,TR14,-TS14) -> 0 | TU14: 46127 | UB14: =SUM(UB13,TZ14,-UA14) -> 0 | UC14: 46127 | UJ14: =SUM(UJ13,UH14,-UI14) -> 0 | UK14: 46127 | UR14: =SUM(UR13,UP14,-UQ14) -> 0 | US14: 46127 | UZ14: =SUM(UZ13,UX14,-UY14) -> 0 | VA14: 46127 | VH14: =SUM(VH13,VF14,-VG14) -> 0 | VI14: 46127 | VP14: =SUM(VP13,VN14,-VO14) -> 0 | VQ14: 46127 | VX14: =SUM(VX13,VV14,-VW14) -> 0 | VY14: 46127 | WF14: =SUM(WF13,WD14,-WE14) -> 0 | WG14: 46127 | WN14: =SUM(WN13,WL14,-WM14) -> 0 | WO14: 46127 | WV14: =SUM(WV13,WT14,-WU14) -> 0 | WW14: 46127 | XD14: =SUM(XD13,XB14,-XC14) -> 0 | XE14: 46127 | XL14: =SUM(XL13,XJ14,-XK14) -> 0 | XM14: 46127 | XT14: =SUM(XT13,XR14,-XS14) -> 0 | XU14: 46127 | YB14: =SUM(YB13,XZ14,-YA14) -> 0 | YC14: 46127 | YJ14: =SUM(YJ13,YH14,-YI14) -> 0 | YK14: 46127 | YR14: =SUM(YR13,YP14,-YQ14) -> 0 | YS14: 46127 | YZ14: =SUM(YZ13,YX14,-YY14) -> 0 | ZA14: 46127 | ZH14: =SUM(ZH13,ZF14,-ZG14) -> 0 | ZI14: 46127 | ZP14: =SUM(ZP13,ZN14,-ZO14) -> 0 | ZQ14: 46127 | ZX14: =SUM(ZX13,ZV14,-ZW14) -> 0 | ZY14: 46127 | AAF14: =SUM(AAF13,AAD14,-AAE14) -> 0 | AAG14: 46127 | AAN14: =SUM(AAN13,AAL14,-AAM14) -> 0 | AAO14: 46127 | AAV14: =SUM(AAV13,AAT14,-AAU14) -> 0 | AAW14: 46127 | ABD14: =SUM(ABD13,ABB14,-ABC14) -> 0 | ABE14: 46127 | ABL14: =SUM(ABL13,ABJ14,-ABK14) -> 0 | ABM14: 46127 | ABT14: =SUM(ABT13,ABR14,-ABS14) -> 0 | ABU14: 46127 | ACB14: =SUM(ACB13,ABZ14,-ACA14) -> 0 | ACC14: 46127
D15: =SUM(D14,B15,-C15) -> 1700 | E15: 46127 | L15: =SUM(L14,J15,-K15) -> 1000 | M15: 46127 | T15: =SUM(T14,R15,-S15) -> 4000 | U15: 46127 | AB15: =SUM(AB14,Z15,-AA15) -> 1000 | AC15: 46127 | AJ15: =SUM(AJ14,AH15,-AI15) -> 2000 | AK15: 46127 | AR15: =SUM(AR14,AP15,-AQ15) -> 1000 | AS15: 46127 | AZ15: =SUM(AZ14,AX15,-AY15) -> 1150 | BA15: 46127 | BH15: =SUM(BH14,BF15,-BG15) -> 7000 | BI15: 46127 | BP15: =SUM(BP14,BN15,-BO15) -> 1000 | BQ15: 46127 | BX15: =SUM(BX14,BV15,-BW15) -> 0 | BY15: 46127 | CF15: =SUM(CF14,CD15,-CE15) -> 0 | CG15: 46142 | CN15: =SUM(CN14,CL15,-CM15) -> 0 | CO15: 46142 | CV15: =SUM(CV14,CT15,-CU15) -> 0 | CW15: 46142 | DD15: =SUM(DD14,DB15,-DC15) -> 0 | DE15: 46142 | DL15: =SUM(DL14,DJ15,-DK15) -> 0 | DM15: 46127 | DT15: =SUM(DT14,DR15,-DS15) -> 0 | DU15: 46127 | EB15: =SUM(EB14,DZ15,-EA15) -> 0 | EC15: 46127 | EJ15: =SUM(EJ14,EH15,-EI15) -> 0 | EK15: 46127 | ER15: =SUM(ER14,EP15,-EQ15) -> 0 | ES15: 46127 | EZ15: =SUM(EZ14,EX15,-EY15) -> 0 | FA15: 46127 | FH15: =SUM(FH14,FF15,-FG15) -> 0 | FI15: 46127 | FP15: =SUM(FP14,FN15,-FO15) -> 0 | FQ15: 46127 | FX15: =SUM(FX14,FV15,-FW15) -> 0 | FY15: 46127 | GF15: =SUM(GF14,GD15,-GE15) -> 0 | GG15: 46127 | GN15: =SUM(GN14,GL15,-GM15) -> 0 | GO15: 46142 | GV15: =SUM(GV14,GT15,-GU15) -> 0 | GW15: 46142 | HD15: =SUM(HD14,HB15,-HC15) -> 0 | HE15: 46142 | HL15: =SUM(HL14,HJ15,-HK15) -> 0 | HM15: 46142 | HT15: =SUM(HT14,HR15,-HS15) -> 0 | HU15: 46142 | IB15: =SUM(IB14,HZ15,-IA15) -> 0 | IC15: 46142 | IJ15: =SUM(IJ14,IH15,-II15) -> 0 | IK15: 46142 | IR15: =SUM(IR14,IP15,-IQ15) -> 0 | IS15: 46142 | IZ15: =SUM(IZ14,IX15,-IY15) -> 0 | JA15: 46142 | JH15: =SUM(JH14,JF15,-JG15) -> 0 | JI15: 46142 | JP15: =SUM(JP14,JN15,-JO15) -> 0 | JQ15: 46142 | JX15: =SUM(JX14,JV15,-JW15) -> 0 | JY15: 46142 | KF15: =SUM(KF14,KD15,-KE15) -> 0 | KG15: 46142 | KN15: =SUM(KN14,KL15,-KM15) -> 0 | KO15: 46142 | KV15: =SUM(KV14,KT15,-KU15) -> 0 | KW15: 46142 | LD15: =SUM(LD14,LB15,-LC15) -> 0 | LE15: 46142 | LL15: =SUM(LL14,LJ15,-LK15) -> 0 | LM15: 46142 | LT15: =SUM(LT14,LR15,-LS15) -> 0 | LU15: 46142 | MB15: =SUM(MB14,LZ15,-MA15) -> 0 | MC15: 46142 | MJ15: =SUM(MJ14,MH15,-MI15) -> 0 | MK15: 46142 | MR15: =SUM(MR14,MP15,-MQ15) -> 0 | MS15: 46142 | MZ15: =SUM(MZ14,MX15,-MY15) -> 0 | NA15: 46142 | NH15: =SUM(NH14,NF15,-NG15) -> 0 | NI15: 46142 | NP15: =SUM(NP14,NN15,-NO15) -> 0 | NQ15: 46142 | NX15: =SUM(NX14,NV15,-NW15) -> 0 | NY15: 46142 | OF15: =SUM(OF14,OD15,-OE15) -> 0 | OG15: 46142 | ON15: =SUM(ON14,OL15,-OM15) -> 0 | OO15: 46142 | OV15: =SUM(OV14,OT15,-OU15) -> 0 | OW15: 46142 | PD15: =SUM(PD14,PB15,-PC15) -> 0 | PE15: 46142 | PL15: =SUM(PL14,PJ15,-PK15) -> 0 | PM15: 46142 | PT15: =SUM(PT14,PR15,-PS15) -> 0 | PU15: 46142 | QB15: =SUM(QB14,PZ15,-QA15) -> 0 | QC15: 46142 | QJ15: =SUM(QJ14,QH15,-QI15) -> 0 | QK15: 46142 | QR15: =SUM(QR14,QP15,-QQ15) -> 0 | QS15: 46142 | QZ15: =SUM(QZ14,QX15,-QY15) -> 0 | RA15: 46142 | RH15: =SUM(RH14,RF15,-RG15) -> 0 | RI15: 46142 | RP15: =SUM(RP14,RN15,-RO15) -> 0 | RQ15: 46142 | RX15: =SUM(RX14,RV15,-RW15) -> 0 | RY15: 46142 | SF15: =SUM(SF14,SD15,-SE15) -> 0 | SG15: 46142 | SN15: =SUM(SN14,SL15,-SM15) -> 0 | SO15: 46142 | SV15: =SUM(SV14,ST15,-SU15) -> 0 | SW15: 46142 | TD15: =SUM(TD14,TB15,-TC15) -> 0 | TE15: 46142 | TL15: =SUM(TL14,TJ15,-TK15) -> 0 | TM15: 46142 | TT15: =SUM(TT14,TR15,-TS15) -> 0 | TU15: 46142 | UB15: =SUM(UB14,TZ15,-UA15) -> 0 | UC15: 46142 | UJ15: =SUM(UJ14,UH15,-UI15) -> 0 | UK15: 46142 | UR15: =SUM(UR14,UP15,-UQ15) -> 0 | US15: 46142 | UZ15: =SUM(UZ14,UX15,-UY15) -> 0 | VA15: 46142 | VH15: =SUM(VH14,VF15,-VG15) -> 0 | VI15: 46142 | VP15: =SUM(VP14,VN15,-VO15) -> 0 | VQ15: 46142 | VX15: =SUM(VX14,VV15,-VW15) -> 0 | VY15: 46142 | WF15: =SUM(WF14,WD15,-WE15) -> 0 | WG15: 46142 | WN15: =SUM(WN14,WL15,-WM15) -> 0 | WO15: 46142 | WV15: =SUM(WV14,WT15,-WU15) -> 0 | WW15: 46142 | XD15: =SUM(XD14,XB15,-XC15) -> 0 | XE15: 46142 | XL15: =SUM(XL14,XJ15,-XK15) -> 0 | XM15: 46142 | XT15: =SUM(XT14,XR15,-XS15) -> 0 | XU15: 46142 | YB15: =SUM(YB14,XZ15,-YA15) -> 0 | YC15: 46142 | YJ15: =SUM(YJ14,YH15,-YI15) -> 0 | YK15: 46142 | YR15: =SUM(YR14,YP15,-YQ15) -> 0 | YS15: 46142 | YZ15: =SUM(YZ14,YX15,-YY15) -> 0 | ZA15: 46142 | ZH15: =SUM(ZH14,ZF15,-ZG15) -> 0 | ZI15: 46142 | ZP15: =SUM(ZP14,ZN15,-ZO15) -> 0 | ZQ15: 46142 | ZX15: =SUM(ZX14,ZV15,-ZW15) -> 0 | ZY15: 46142 | AAF15: =SUM(AAF14,AAD15,-AAE15) -> 0 | AAG15: 46142 | AAN15: =SUM(AAN14,AAL15,-AAM15) -> 0 | AAO15: 46142 | AAV15: =SUM(AAV14,AAT15,-AAU15) -> 0 | AAW15: 46142 | ABD15: =SUM(ABD14,ABB15,-ABC15) -> 0 | ABE15: 46142 | ABL15: =SUM(ABL14,ABJ15,-ABK15) -> 0 | ABM15: 46142 | ABT15: =SUM(ABT14,ABR15,-ABS15) -> 0 | ABU15: 46142 | ACB15: =SUM(ACB14,ABZ15,-ACA15) -> 0 | ACC15: 46142
D16: =SUM(D15,B16,-C16) -> 1700 | E16: 46142 | L16: =SUM(L15,J16,-K16) -> 1000 | M16: 46142 | T16: =SUM(T15,R16,-S16) -> 4000 | U16: 46142 | AB16: =SUM(AB15,Z16,-AA16) -> 1000 | AC16: 46142 | AJ16: =SUM(AJ15,AH16,-AI16) -> 2000 | AK16: 46142 | AR16: =SUM(AR15,AP16,-AQ16) -> 1000 | AS16: 46142 | AZ16: =SUM(AZ15,AX16,-AY16) -> 1150 | BA16: 46142 | BH16: =SUM(BH15,BF16,-BG16) -> 7000 | BI16: 46142 | BP16: =SUM(BP15,BN16,-BO16) -> 1000 | BQ16: 46142 | BX16: =SUM(BX15,BV16,-BW16) -> 0 | BY16: 46142 | CF16: =SUM(CF15,CD16,-CE16) -> 0 | CG16: 46157 | CN16: =SUM(CN15,CL16,-CM16) -> 0 | CO16: 46157 | CV16: =SUM(CV15,CT16,-CU16) -> 0 | CW16: 46157 | DD16: =SUM(DD15,DB16,-DC16) -> 0 | DE16: 46157 | DG16: 0 | DL16: =SUM(DL15,DJ16,-DK16) -> 0 | DM16: 46142 | DT16: =SUM(DT15,DR16,-DS16) -> 0 | DU16: 46142 | EB16: =SUM(EB15,DZ16,-EA16) -> 0 | EC16: 46142 | EJ16: =SUM(EJ15,EH16,-EI16) -> 0 | EK16: 46142 | ER16: =SUM(ER15,EP16,-EQ16) -> 0 | ES16: 46142 | EZ16: =SUM(EZ15,EX16,-EY16) -> 0 | FA16: 46142 | FH16: =SUM(FH15,FF16,-FG16) -> 0 | FI16: 46142 | FP16: =SUM(FP15,FN16,-FO16) -> 0 | FQ16: 46142 | FX16: =SUM(FX15,FV16,-FW16) -> 0 | FY16: 46142 | GF16: =SUM(GF15,GD16,-GE16) -> 0 | GG16: 46142 | GN16: =SUM(GN15,GL16,-GM16) -> 0 | GO16: 46157 | GV16: =SUM(GV15,GT16,-GU16) -> 0 | GW16: 46157 | HD16: =SUM(HD15,HB16,-HC16) -> 0 | HE16: 46157 | HL16: =SUM(HL15,HJ16,-HK16) -> 0 | HM16: 46157 | HT16: =SUM(HT15,HR16,-HS16) -> 0 | HU16: 46157 | IB16: =SUM(IB15,HZ16,-IA16) -> 0 | IC16: 46157 | IJ16: =SUM(IJ15,IH16,-II16) -> 0 | IK16: 46157 | IR16: =SUM(IR15,IP16,-IQ16) -> 0 | IS16: 46157 | IZ16: =SUM(IZ15,IX16,-IY16) -> 0 | JA16: 46157 | JH16: =SUM(JH15,JF16,-JG16) -> 0 | JI16: 46157 | JP16: =SUM(JP15,JN16,-JO16) -> 0 | JQ16: 46157 | JX16: =SUM(JX15,JV16,-JW16) -> 0 | JY16: 46157 | KF16: =SUM(KF15,KD16,-KE16) -> 0 | KG16: 46157 | KN16: =SUM(KN15,KL16,-KM16) -> 0 | KO16: 46157 | KV16: =SUM(KV15,KT16,-KU16) -> 0 | KW16: 46157 | LD16: =SUM(LD15,LB16,-LC16) -> 0 | LE16: 46157 | LL16: =SUM(LL15,LJ16,-LK16) -> 0 | LM16: 46157 | LT16: =SUM(LT15,LR16,-LS16) -> 0 | LU16: 46157 | MB16: =SUM(MB15,LZ16,-MA16) -> 0 | MC16: 46157 | MJ16: =SUM(MJ15,MH16,-MI16) -> 0 | MK16: 46157 | MR16: =SUM(MR15,MP16,-MQ16) -> 0 | MS16: 46157 | MZ16: =SUM(MZ15,MX16,-MY16) -> 0 | NA16: 46157 | NH16: =SUM(NH15,NF16,-NG16) -> 0 | NI16: 46157 | NP16: =SUM(NP15,NN16,-NO16) -> 0 | NQ16: 46157 | NX16: =SUM(NX15,NV16,-NW16) -> 0 | NY16: 46157 | OF16: =SUM(OF15,OD16,-OE16) -> 0 | OG16: 46157 | ON16: =SUM(ON15,OL16,-OM16) -> 0 | OO16: 46157 | OV16: =SUM(OV15,OT16,-OU16) -> 0 | OW16: 46157 | PD16: =SUM(PD15,PB16,-PC16) -> 0 | PE16: 46157 | PL16: =SUM(PL15,PJ16,-PK16) -> 0 | PM16: 46157 | PT16: =SUM(PT15,PR16,-PS16) -> 0 | PU16: 46157 | QB16: =SUM(QB15,PZ16,-QA16) -> 0 | QC16: 46157 | QJ16: =SUM(QJ15,QH16,-QI16) -> 0 | QK16: 46157 | QR16: =SUM(QR15,QP16,-QQ16) -> 0 | QS16: 46157 | QZ16: =SUM(QZ15,QX16,-QY16) -> 0 | RA16: 46157 | RH16: =SUM(RH15,RF16,-RG16) -> 0 | RI16: 46157 | RP16: =SUM(RP15,RN16,-RO16) -> 0 | RQ16: 46157 | RX16: =SUM(RX15,RV16,-RW16) -> 0 | RY16: 46157 | SF16: =SUM(SF15,SD16,-SE16) -> 0 | SG16: 46157 | SN16: =SUM(SN15,SL16,-SM16) -> 0 | SO16: 46157 | SV16: =SUM(SV15,ST16,-SU16) -> 0 | SW16: 46157 | TD16: =SUM(TD15,TB16,-TC16) -> 0 | TE16: 46157 | TL16: =SUM(TL15,TJ16,-TK16) -> 0 | TM16: 46157 | TT16: =SUM(TT15,TR16,-TS16) -> 0 | TU16: 46157 | UB16: =SUM(UB15,TZ16,-UA16) -> 0 | UC16: 46157 | UJ16: =SUM(UJ15,UH16,-UI16) -> 0 | UK16: 46157 | UR16: =SUM(UR15,UP16,-UQ16) -> 0 | US16: 46157 | UZ16: =SUM(UZ15,UX16,-UY16) -> 0 | VA16: 46157 | VH16: =SUM(VH15,VF16,-VG16) -> 0 | VI16: 46157 | VP16: =SUM(VP15,VN16,-VO16) -> 0 | VQ16: 46157 | VX16: =SUM(VX15,VV16,-VW16) -> 0 | VY16: 46157 | WF16: =SUM(WF15,WD16,-WE16) -> 0 | WG16: 46157 | WN16: =SUM(WN15,WL16,-WM16) -> 0 | WO16: 46157 | WV16: =SUM(WV15,WT16,-WU16) -> 0 | WW16: 46157 | XD16: =SUM(XD15,XB16,-XC16) -> 0 | XE16: 46157 | XL16: =SUM(XL15,XJ16,-XK16) -> 0 | XM16: 46157 | XT16: =SUM(XT15,XR16,-XS16) -> 0 | XU16: 46157 | YB16: =SUM(YB15,XZ16,-YA16) -> 0 | YC16: 46157 | YJ16: =SUM(YJ15,YH16,-YI16) -> 0 | YK16: 46157 | YR16: =SUM(YR15,YP16,-YQ16) -> 0 | YS16: 46157 | YZ16: =SUM(YZ15,YX16,-YY16) -> 0 | ZA16: 46157 | ZH16: =SUM(ZH15,ZF16,-ZG16) -> 0 | ZI16: 46157 | ZP16: =SUM(ZP15,ZN16,-ZO16) -> 0 | ZQ16: 46157 | ZX16: =SUM(ZX15,ZV16,-ZW16) -> 0 | ZY16: 46157 | AAF16: =SUM(AAF15,AAD16,-AAE16) -> 0 | AAG16: 46157 | AAN16: =SUM(AAN15,AAL16,-AAM16) -> 0 | AAO16: 46157 | AAV16: =SUM(AAV15,AAT16,-AAU16) -> 0 | AAW16: 46157 | ABD16: =SUM(ABD15,ABB16,-ABC16) -> 0 | ABE16: 46157 | ABL16: =SUM(ABL15,ABJ16,-ABK16) -> 0 | ABM16: 46157 | ABT16: =SUM(ABT15,ABR16,-ABS16) -> 0 | ABU16: 46157 | ACB16: =SUM(ACB15,ABZ16,-ACA16) -> 0 | ACC16: 46157
D17: =SUM(D16,B17,-C17) -> 1700 | E17: 46157 | L17: =SUM(L16,J17,-K17) -> 1000 | M17: 46157 | T17: =SUM(T16,R17,-S17) -> 4000 | U17: 46157 | AB17: =SUM(AB16,Z17,-AA17) -> 1000 | AC17: 46157 | AJ17: =SUM(AJ16,AH17,-AI17) -> 2000 | AK17: 46157 | AR17: =SUM(AR16,AP17,-AQ17) -> 1000 | AS17: 46157 | AZ17: =SUM(AZ16,AX17,-AY17) -> 1150 | BA17: 46157 | BH17: =SUM(BH16,BF17,-BG17) -> 7000 | BI17: 46157 | BP17: =SUM(BP16,BN17,-BO17) -> 1000 | BQ17: 46157 | BX17: =SUM(BX16,BV17,-BW17) -> 0 | BY17: 46157 | CF17: =SUM(CF16,CD17,-CE17) -> 0 | CG17: 46172 | CN17: =SUM(CN16,CL17,-CM17) -> 0 | CO17: 46172 | CV17: =SUM(CV16,CT17,-CU17) -> 0 | CW17: 46172 | DD17: =SUM(DD16,DB17,-DC17) -> 0 | DE17: 46172 | DL17: =SUM(DL16,DJ17,-DK17) -> 0 | DM17: 46157 | DT17: =SUM(DT16,DR17,-DS17) -> 0 | DU17: 46157 | EB17: =SUM(EB16,DZ17,-EA17) -> 0 | EC17: 46157 | EJ17: =SUM(EJ16,EH17,-EI17) -> 0 | EK17: 46157 | ER17: =SUM(ER16,EP17,-EQ17) -> 0 | ES17: 46157 | EZ17: =SUM(EZ16,EX17,-EY17) -> 0 | FA17: 46157 | FH17: =SUM(FH16,FF17,-FG17) -> 0 | FI17: 46157 | FP17: =SUM(FP16,FN17,-FO17) -> 0 | FQ17: 46157 | FX17: =SUM(FX16,FV17,-FW17) -> 0 | FY17: 46157 | GF17: =SUM(GF16,GD17,-GE17) -> 0 | GG17: 46157 | GN17: =SUM(GN16,GL17,-GM17) -> 0 | GO17: 46172 | GV17: =SUM(GV16,GT17,-GU17) -> 0 | GW17: 46172 | HD17: =SUM(HD16,HB17,-HC17) -> 0 | HE17: 46172 | HL17: =SUM(HL16,HJ17,-HK17) -> 0 | HM17: 46172 | HT17: =SUM(HT16,HR17,-HS17) -> 0 | HU17: 46172 | IB17: =SUM(IB16,HZ17,-IA17) -> 0 | IC17: 46172 | IJ17: =SUM(IJ16,IH17,-II17) -> 0 | IK17: 46172 | IR17: =SUM(IR16,IP17,-IQ17) -> 0 | IS17: 46172 | IZ17: =SUM(IZ16,IX17,-IY17) -> 0 | JA17: 46172 | JH17: =SUM(JH16,JF17,-JG17) -> 0 | JI17: 46172 | JP17: =SUM(JP16,JN17,-JO17) -> 0 | JQ17: 46172 | JX17: =SUM(JX16,JV17,-JW17) -> 0 | JY17: 46172 | KF17: =SUM(KF16,KD17,-KE17) -> 0 | KG17: 46172 | KN17: =SUM(KN16,KL17,-KM17) -> 0 | KO17: 46172 | KV17: =SUM(KV16,KT17,-KU17) -> 0 | KW17: 46172 | LD17: =SUM(LD16,LB17,-LC17) -> 0 | LE17: 46172 | LL17: =SUM(LL16,LJ17,-LK17) -> 0 | LM17: 46172 | LT17: =SUM(LT16,LR17,-LS17) -> 0 | LU17: 46172 | MB17: =SUM(MB16,LZ17,-MA17) -> 0 | MC17: 46172 | MJ17: =SUM(MJ16,MH17,-MI17) -> 0 | MK17: 46172 | MR17: =SUM(MR16,MP17,-MQ17) -> 0 | MS17: 46172 | MZ17: =SUM(MZ16,MX17,-MY17) -> 0 | NA17: 46172 | NH17: =SUM(NH16,NF17,-NG17) -> 0 | NI17: 46172 | NP17: =SUM(NP16,NN17,-NO17) -> 0 | NQ17: 46172 | NX17: =SUM(NX16,NV17,-NW17) -> 0 | NY17: 46172 | OF17: =SUM(OF16,OD17,-OE17) -> 0 | OG17: 46172 | ON17: =SUM(ON16,OL17,-OM17) -> 0 | OO17: 46172 | OV17: =SUM(OV16,OT17,-OU17) -> 0 | OW17: 46172 | PD17: =SUM(PD16,PB17,-PC17) -> 0 | PE17: 46172 | PL17: =SUM(PL16,PJ17,-PK17) -> 0 | PM17: 46172 | PT17: =SUM(PT16,PR17,-PS17) -> 0 | PU17: 46172 | QB17: =SUM(QB16,PZ17,-QA17) -> 0 | QC17: 46172 | QJ17: =SUM(QJ16,QH17,-QI17) -> 0 | QK17: 46172 | QR17: =SUM(QR16,QP17,-QQ17) -> 0 | QS17: 46172 | QZ17: =SUM(QZ16,QX17,-QY17) -> 0 | RA17: 46172 | RH17: =SUM(RH16,RF17,-RG17) -> 0 | RI17: 46172 | RP17: =SUM(RP16,RN17,-RO17) -> 0 | RQ17: 46172 | RX17: =SUM(RX16,RV17,-RW17) -> 0 | RY17: 46172 | SF17: =SUM(SF16,SD17,-SE17) -> 0 | SG17: 46172 | SN17: =SUM(SN16,SL17,-SM17) -> 0 | SO17: 46172 | SV17: =SUM(SV16,ST17,-SU17) -> 0 | SW17: 46172 | TD17: =SUM(TD16,TB17,-TC17) -> 0 | TE17: 46172 | TL17: =SUM(TL16,TJ17,-TK17) -> 0 | TM17: 46172 | TT17: =SUM(TT16,TR17,-TS17) -> 0 | TU17: 46172 | UB17: =SUM(UB16,TZ17,-UA17) -> 0 | UC17: 46172 | UJ17: =SUM(UJ16,UH17,-UI17) -> 0 | UK17: 46172 | UR17: =SUM(UR16,UP17,-UQ17) -> 0 | US17: 46172 | UZ17: =SUM(UZ16,UX17,-UY17) -> 0 | VA17: 46172 | VH17: =SUM(VH16,VF17,-VG17) -> 0 | VI17: 46172 | VP17: =SUM(VP16,VN17,-VO17) -> 0 | VQ17: 46172 | VX17: =SUM(VX16,VV17,-VW17) -> 0 | VY17: 46172 | WF17: =SUM(WF16,WD17,-WE17) -> 0 | WG17: 46172 | WN17: =SUM(WN16,WL17,-WM17) -> 0 | WO17: 46172 | WV17: =SUM(WV16,WT17,-WU17) -> 0 | WW17: 46172 | XD17: =SUM(XD16,XB17,-XC17) -> 0 | XE17: 46172 | XL17: =SUM(XL16,XJ17,-XK17) -> 0 | XM17: 46172 | XT17: =SUM(XT16,XR17,-XS17) -> 0 | XU17: 46172 | YB17: =SUM(YB16,XZ17,-YA17) -> 0 | YC17: 46172 | YJ17: =SUM(YJ16,YH17,-YI17) -> 0 | YK17: 46172 | YR17: =SUM(YR16,YP17,-YQ17) -> 0 | YS17: 46172 | YZ17: =SUM(YZ16,YX17,-YY17) -> 0 | ZA17: 46172 | ZH17: =SUM(ZH16,ZF17,-ZG17) -> 0 | ZI17: 46172 | ZP17: =SUM(ZP16,ZN17,-ZO17) -> 0 | ZQ17: 46172 | ZX17: =SUM(ZX16,ZV17,-ZW17) -> 0 | ZY17: 46172 | AAF17: =SUM(AAF16,AAD17,-AAE17) -> 0 | AAG17: 46172 | AAN17: =SUM(AAN16,AAL17,-AAM17) -> 0 | AAO17: 46172 | AAV17: =SUM(AAV16,AAT17,-AAU17) -> 0 | AAW17: 46172 | ABD17: =SUM(ABD16,ABB17,-ABC17) -> 0 | ABE17: 46172 | ABL17: =SUM(ABL16,ABJ17,-ABK17) -> 0 | ABM17: 46172 | ABT17: =SUM(ABT16,ABR17,-ABS17) -> 0 | ABU17: 46172 | ACB17: =SUM(ACB16,ABZ17,-ACA17) -> 0 | ACC17: 46172
D18: =SUM(D17,B18,-C18) -> 1700 | E18: 46172 | L18: =SUM(L17,J18,-K18) -> 1000 | M18: 46172 | T18: =SUM(T17,R18,-S18) -> 4000 | U18: 46172 | AB18: =SUM(AB17,Z18,-AA18) -> 1000 | AC18: 46172 | AJ18: =SUM(AJ17,AH18,-AI18) -> 2000 | AK18: 46172 | AR18: =SUM(AR17,AP18,-AQ18) -> 1000 | AS18: 46172 | AZ18: =SUM(AZ17,AX18,-AY18) -> 1150 | BA18: 46172 | BH18: =SUM(BH17,BF18,-BG18) -> 7000 | BI18: 46172 | BP18: =SUM(BP17,BN18,-BO18) -> 1000 | BQ18: 46172 | BX18: =SUM(BX17,BV18,-BW18) -> 0 | BY18: 46172 | CF18: =SUM(CF17,CD18,-CE18) -> 0 | CG18: 46188 | CN18: =SUM(CN17,CL18,-CM18) -> 0 | CO18: 46188 | CV18: =SUM(CV17,CT18,-CU18) -> 0 | CW18: 46188 | DD18: =SUM(DD17,DB18,-DC18) -> 0 | DE18: 46188 | DL18: =SUM(DL17,DJ18,-DK18) -> 0 | DM18: 46172 | DT18: =SUM(DT17,DR18,-DS18) -> 0 | DU18: 46172 | EB18: =SUM(EB17,DZ18,-EA18) -> 0 | EC18: 46172 | EJ18: =SUM(EJ17,EH18,-EI18) -> 0 | EK18: 46172 | ER18: =SUM(ER17,EP18,-EQ18) -> 0 | ES18: 46172 | EZ18: =SUM(EZ17,EX18,-EY18) -> 0 | FA18: 46172 | FH18: =SUM(FH17,FF18,-FG18) -> 0 | FI18: 46172 | FP18: =SUM(FP17,FN18,-FO18) -> 0 | FQ18: 46172 | FX18: =SUM(FX17,FV18,-FW18) -> 0 | FY18: 46172 | GF18: =SUM(GF17,GD18,-GE18) -> 0 | GG18: 46172 | GN18: =SUM(GN17,GL18,-GM18) -> 0 | GO18: 46188 | GV18: =SUM(GV17,GT18,-GU18) -> 0 | GW18: 46188 | HD18: =SUM(HD17,HB18,-HC18) -> 0 | HE18: 46188 | HL18: =SUM(HL17,HJ18,-HK18) -> 0 | HM18: 46188 | HT18: =SUM(HT17,HR18,-HS18) -> 0 | HU18: 46188 | IB18: =SUM(IB17,HZ18,-IA18) -> 0 | IC18: 46188 | IJ18: =SUM(IJ17,IH18,-II18) -> 0 | IK18: 46188 | IR18: =SUM(IR17,IP18,-IQ18) -> 0 | IS18: 46188 | IZ18: =SUM(IZ17,IX18,-IY18) -> 0 | JA18: 46188 | JH18: =SUM(JH17,JF18,-JG18) -> 0 | JI18: 46188 | JP18: =SUM(JP17,JN18,-JO18) -> 0 | JQ18: 46188 | JX18: =SUM(JX17,JV18,-JW18) -> 0 | JY18: 46188 | KF18: =SUM(KF17,KD18,-KE18) -> 0 | KG18: 46188 | KN18: =SUM(KN17,KL18,-KM18) -> 0 | KO18: 46188 | KV18: =SUM(KV17,KT18,-KU18) -> 0 | KW18: 46188 | LD18: =SUM(LD17,LB18,-LC18) -> 0 | LE18: 46188 | LL18: =SUM(LL17,LJ18,-LK18) -> 0 | LM18: 46188 | LT18: =SUM(LT17,LR18,-LS18) -> 0 | LU18: 46188 | MB18: =SUM(MB17,LZ18,-MA18) -> 0 | MC18: 46188 | MJ18: =SUM(MJ17,MH18,-MI18) -> 0 | MK18: 46188 | MR18: =SUM(MR17,MP18,-MQ18) -> 0 | MS18: 46188 | MZ18: =SUM(MZ17,MX18,-MY18) -> 0 | NA18: 46188 | NH18: =SUM(NH17,NF18,-NG18) -> 0 | NI18: 46188 | NP18: =SUM(NP17,NN18,-NO18) -> 0 | NQ18: 46188 | NX18: =SUM(NX17,NV18,-NW18) -> 0 | NY18: 46188 | OF18: =SUM(OF17,OD18,-OE18) -> 0 | OG18: 46188 | ON18: =SUM(ON17,OL18,-OM18) -> 0 | OO18: 46188 | OV18: =SUM(OV17,OT18,-OU18) -> 0 | OW18: 46188 | PD18: =SUM(PD17,PB18,-PC18) -> 0 | PE18: 46188 | PL18: =SUM(PL17,PJ18,-PK18) -> 0 | PM18: 46188 | PT18: =SUM(PT17,PR18,-PS18) -> 0 | PU18: 46188 | QB18: =SUM(QB17,PZ18,-QA18) -> 0 | QC18: 46188 | QJ18: =SUM(QJ17,QH18,-QI18) -> 0 | QK18: 46188 | QR18: =SUM(QR17,QP18,-QQ18) -> 0 | QS18: 46188 | QZ18: =SUM(QZ17,QX18,-QY18) -> 0 | RA18: 46188 | RH18: =SUM(RH17,RF18,-RG18) -> 0 | RI18: 46188 | RP18: =SUM(RP17,RN18,-RO18) -> 0 | RQ18: 46188 | RX18: =SUM(RX17,RV18,-RW18) -> 0 | RY18: 46188 | SF18: =SUM(SF17,SD18,-SE18) -> 0 | SG18: 46188 | SN18: =SUM(SN17,SL18,-SM18) -> 0 | SO18: 46188 | SV18: =SUM(SV17,ST18,-SU18) -> 0 | SW18: 46188 | TD18: =SUM(TD17,TB18,-TC18) -> 0 | TE18: 46188 | TL18: =SUM(TL17,TJ18,-TK18) -> 0 | TM18: 46188 | TT18: =SUM(TT17,TR18,-TS18) -> 0 | TU18: 46188 | UB18: =SUM(UB17,TZ18,-UA18) -> 0 | UC18: 46188 | UJ18: =SUM(UJ17,UH18,-UI18) -> 0 | UK18: 46188 | UR18: =SUM(UR17,UP18,-UQ18) -> 0 | US18: 46188 | UZ18: =SUM(UZ17,UX18,-UY18) -> 0 | VA18: 46188 | VH18: =SUM(VH17,VF18,-VG18) -> 0 | VI18: 46188 | VP18: =SUM(VP17,VN18,-VO18) -> 0 | VQ18: 46188 | VX18: =SUM(VX17,VV18,-VW18) -> 0 | VY18: 46188 | WF18: =SUM(WF17,WD18,-WE18) -> 0 | WG18: 46188 | WN18: =SUM(WN17,WL18,-WM18) -> 0 | WO18: 46188 | WV18: =SUM(WV17,WT18,-WU18) -> 0 | WW18: 46188 | XD18: =SUM(XD17,XB18,-XC18) -> 0 | XE18: 46188 | XL18: =SUM(XL17,XJ18,-XK18) -> 0 | XM18: 46188 | XT18: =SUM(XT17,XR18,-XS18) -> 0 | XU18: 46188 | YB18: =SUM(YB17,XZ18,-YA18) -> 0 | YC18: 46188 | YJ18: =SUM(YJ17,YH18,-YI18) -> 0 | YK18: 46188 | YR18: =SUM(YR17,YP18,-YQ18) -> 0 | YS18: 46188 | YZ18: =SUM(YZ17,YX18,-YY18) -> 0 | ZA18: 46188 | ZH18: =SUM(ZH17,ZF18,-ZG18) -> 0 | ZI18: 46188 | ZP18: =SUM(ZP17,ZN18,-ZO18) -> 0 | ZQ18: 46188 | ZX18: =SUM(ZX17,ZV18,-ZW18) -> 0 | ZY18: 46188 | AAF18: =SUM(AAF17,AAD18,-AAE18) -> 0 | AAG18: 46188 | AAN18: =SUM(AAN17,AAL18,-AAM18) -> 0 | AAO18: 46188 | AAV18: =SUM(AAV17,AAT18,-AAU18) -> 0 | AAW18: 46188 | ABD18: =SUM(ABD17,ABB18,-ABC18) -> 0 | ABE18: 46188 | ABL18: =SUM(ABL17,ABJ18,-ABK18) -> 0 | ABM18: 46188 | ABT18: =SUM(ABT17,ABR18,-ABS18) -> 0 | ABU18: 46188 | ACB18: =SUM(ACB17,ABZ18,-ACA18) -> 0 | ACC18: 46188
D19: =SUM(D18,B19,-C19) -> 1700 | E19: 46188 | L19: =SUM(L18,J19,-K19) -> 1000 | M19: 46188 | T19: =SUM(T18,R19,-S19) -> 4000 | U19: 46188 | AB19: =SUM(AB18,Z19,-AA19) -> 1000 | AC19: 46188 | AJ19: =SUM(AJ18,AH19,-AI19) -> 2000 | AK19: 46188 | AR19: =SUM(AR18,AP19,-AQ19) -> 1000 | AS19: 46188 | AZ19: =SUM(AZ18,AX19,-AY19) -> 1150 | BA19: 46188 | BH19: =SUM(BH18,BF19,-BG19) -> 7000 | BI19: 46188 | BP19: =SUM(BP18,BN19,-BO19) -> 1000 | BQ19: 46188 | BX19: =SUM(BX18,BV19,-BW19) -> 0 | BY19: 46188 | CF19: =SUM(CF18,CD19,-CE19) -> 0 | CG19: 46203 | CN19: =SUM(CN18,CL19,-CM19) -> 0 | CO19: 46203 | CV19: =SUM(CV18,CT19,-CU19) -> 0 | CW19: 46203 | DD19: =SUM(DD18,DB19,-DC19) -> 0 | DE19: 46203 | DL19: =SUM(DL18,DJ19,-DK19) -> 0 | DM19: 46188 | DT19: =SUM(DT18,DR19,-DS19) -> 0 | DU19: 46188 | EB19: =SUM(EB18,DZ19,-EA19) -> 0 | EC19: 46188 | EJ19: =SUM(EJ18,EH19,-EI19) -> 0 | EK19: 46188 | ER19: =SUM(ER18,EP19,-EQ19) -> 0 | ES19: 46188 | EZ19: =SUM(EZ18,EX19,-EY19) -> 0 | FA19: 46188 | FH19: =SUM(FH18,FF19,-FG19) -> 0 | FI19: 46188 | FP19: =SUM(FP18,FN19,-FO19) -> 0 | FQ19: 46188 | FX19: =SUM(FX18,FV19,-FW19) -> 0 | FY19: 46188 | GF19: =SUM(GF18,GD19,-GE19) -> 0 | GG19: 46188 | GN19: =SUM(GN18,GL19,-GM19) -> 0 | GO19: 46203 | GV19: =SUM(GV18,GT19,-GU19) -> 0 | GW19: 46203 | HD19: =SUM(HD18,HB19,-HC19) -> 0 | HE19: 46203 | HL19: =SUM(HL18,HJ19,-HK19) -> 0 | HM19: 46203 | HT19: =SUM(HT18,HR19,-HS19) -> 0 | HU19: 46203 | IB19: =SUM(IB18,HZ19,-IA19) -> 0 | IC19: 46203 | IJ19: =SUM(IJ18,IH19,-II19) -> 0 | IK19: 46203 | IR19: =SUM(IR18,IP19,-IQ19) -> 0 | IS19: 46203 | IZ19: =SUM(IZ18,IX19,-IY19) -> 0 | JA19: 46203 | JH19: =SUM(JH18,JF19,-JG19) -> 0 | JI19: 46203 | JP19: =SUM(JP18,JN19,-JO19) -> 0 | JQ19: 46203 | JX19: =SUM(JX18,JV19,-JW19) -> 0 | JY19: 46203 | KF19: =SUM(KF18,KD19,-KE19) -> 0 | KG19: 46203 | KN19: =SUM(KN18,KL19,-KM19) -> 0 | KO19: 46203 | KV19: =SUM(KV18,KT19,-KU19) -> 0 | KW19: 46203 | LD19: =SUM(LD18,LB19,-LC19) -> 0 | LE19: 46203 | LL19: =SUM(LL18,LJ19,-LK19) -> 0 | LM19: 46203 | LT19: =SUM(LT18,LR19,-LS19) -> 0 | LU19: 46203 | MB19: =SUM(MB18,LZ19,-MA19) -> 0 | MC19: 46203 | MJ19: =SUM(MJ18,MH19,-MI19) -> 0 | MK19: 46203 | MR19: =SUM(MR18,MP19,-MQ19) -> 0 | MS19: 46203 | MZ19: =SUM(MZ18,MX19,-MY19) -> 0 | NA19: 46203 | NH19: =SUM(NH18,NF19,-NG19) -> 0 | NI19: 46203 | NP19: =SUM(NP18,NN19,-NO19) -> 0 | NQ19: 46203 | NX19: =SUM(NX18,NV19,-NW19) -> 0 | NY19: 46203 | OF19: =SUM(OF18,OD19,-OE19) -> 0 | OG19: 46203 | ON19: =SUM(ON18,OL19,-OM19) -> 0 | OO19: 46203 | OV19: =SUM(OV18,OT19,-OU19) -> 0 | OW19: 46203 | PD19: =SUM(PD18,PB19,-PC19) -> 0 | PE19: 46203 | PL19: =SUM(PL18,PJ19,-PK19) -> 0 | PM19: 46203 | PT19: =SUM(PT18,PR19,-PS19) -> 0 | PU19: 46203 | QB19: =SUM(QB18,PZ19,-QA19) -> 0 | QC19: 46203 | QJ19: =SUM(QJ18,QH19,-QI19) -> 0 | QK19: 46203 | QR19: =SUM(QR18,QP19,-QQ19) -> 0 | QS19: 46203 | QZ19: =SUM(QZ18,QX19,-QY19) -> 0 | RA19: 46203 | RH19: =SUM(RH18,RF19,-RG19) -> 0 | RI19: 46203 | RP19: =SUM(RP18,RN19,-RO19) -> 0 | RQ19: 46203 | RX19: =SUM(RX18,RV19,-RW19) -> 0 | RY19: 46203 | SF19: =SUM(SF18,SD19,-SE19) -> 0 | SG19: 46203 | SN19: =SUM(SN18,SL19,-SM19) -> 0 | SO19: 46203 | SV19: =SUM(SV18,ST19,-SU19) -> 0 | SW19: 46203 | TD19: =SUM(TD18,TB19,-TC19) -> 0 | TE19: 46203 | TL19: =SUM(TL18,TJ19,-TK19) -> 0 | TM19: 46203 | TT19: =SUM(TT18,TR19,-TS19) -> 0 | TU19: 46203 | UB19: =SUM(UB18,TZ19,-UA19) -> 0 | UC19: 46203 | UJ19: =SUM(UJ18,UH19,-UI19) -> 0 | UK19: 46203 | UR19: =SUM(UR18,UP19,-UQ19) -> 0 | US19: 46203 | UZ19: =SUM(UZ18,UX19,-UY19) -> 0 | VA19: 46203 | VH19: =SUM(VH18,VF19,-VG19) -> 0 | VI19: 46203 | VP19: =SUM(VP18,VN19,-VO19) -> 0 | VQ19: 46203 | VX19: =SUM(VX18,VV19,-VW19) -> 0 | VY19: 46203 | WF19: =SUM(WF18,WD19,-WE19) -> 0 | WG19: 46203 | WN19: =SUM(WN18,WL19,-WM19) -> 0 | WO19: 46203 | WV19: =SUM(WV18,WT19,-WU19) -> 0 | WW19: 46203 | XD19: =SUM(XD18,XB19,-XC19) -> 0 | XE19: 46203 | XL19: =SUM(XL18,XJ19,-XK19) -> 0 | XM19: 46203 | XT19: =SUM(XT18,XR19,-XS19) -> 0 | XU19: 46203 | YB19: =SUM(YB18,XZ19,-YA19) -> 0 | YC19: 46203 | YJ19: =SUM(YJ18,YH19,-YI19) -> 0 | YK19: 46203 | YR19: =SUM(YR18,YP19,-YQ19) -> 0 | YS19: 46203 | YZ19: =SUM(YZ18,YX19,-YY19) -> 0 | ZA19: 46203 | ZH19: =SUM(ZH18,ZF19,-ZG19) -> 0 | ZI19: 46203 | ZP19: =SUM(ZP18,ZN19,-ZO19) -> 0 | ZQ19: 46203 | ZX19: =SUM(ZX18,ZV19,-ZW19) -> 0 | ZY19: 46203 | AAF19: =SUM(AAF18,AAD19,-AAE19) -> 0 | AAG19: 46203 | AAN19: =SUM(AAN18,AAL19,-AAM19) -> 0 | AAO19: 46203 | AAV19: =SUM(AAV18,AAT19,-AAU19) -> 0 | AAW19: 46203 | ABD19: =SUM(ABD18,ABB19,-ABC19) -> 0 | ABE19: 46203 | ABL19: =SUM(ABL18,ABJ19,-ABK19) -> 0 | ABM19: 46203 | ABT19: =SUM(ABT18,ABR19,-ABS19) -> 0 | ABU19: 46203 | ACB19: =SUM(ACB18,ABZ19,-ACA19) -> 0 | ACC19: 46203
D20: =SUM(D19,B20,-C20) -> 1700 | E20: 46203 | L20: =SUM(L19,J20,-K20) -> 1000 | M20: 46203 | T20: =SUM(T19,R20,-S20) -> 4000 | U20: 46203 | AB20: =SUM(AB19,Z20,-AA20) -> 1000 | AC20: 46203 | AJ20: =SUM(AJ19,AH20,-AI20) -> 2000 | AK20: 46203 | AR20: =SUM(AR19,AP20,-AQ20) -> 1000 | AS20: 46203 | AZ20: =SUM(AZ19,AX20,-AY20) -> 1150 | BA20: 46203 | BH20: =SUM(BH19,BF20,-BG20) -> 7000 | BI20: 46203 | BP20: =SUM(BP19,BN20,-BO20) -> 1000 | BQ20: 46203 | BX20: =SUM(BX19,BV20,-BW20) -> 0 | BY20: 46203 | CF20: =SUM(CF19,CD20,-CE20) -> 0 | CG20: 46218 | CN20: =SUM(CN19,CL20,-CM20) -> 0 | CO20: 46218 | CV20: =SUM(CV19,CT20,-CU20) -> 0 | CW20: 46218 | DD20: =SUM(DD19,DB20,-DC20) -> 0 | DE20: 46218 | DL20: =SUM(DL19,DJ20,-DK20) -> 0 | DM20: 46203 | DT20: =SUM(DT19,DR20,-DS20) -> 0 | DU20: 46203 | EB20: =SUM(EB19,DZ20,-EA20) -> 0 | EC20: 46203 | EJ20: =SUM(EJ19,EH20,-EI20) -> 0 | EK20: 46203 | ER20: =SUM(ER19,EP20,-EQ20) -> 0 | ES20: 46203 | EZ20: =SUM(EZ19,EX20,-EY20) -> 0 | FA20: 46203 | FH20: =SUM(FH19,FF20,-FG20) -> 0 | FI20: 46203 | FP20: =SUM(FP19,FN20,-FO20) -> 0 | FQ20: 46203 | FX20: =SUM(FX19,FV20,-FW20) -> 0 | FY20: 46203 | GF20: =SUM(GF19,GD20,-GE20) -> 0 | GG20: 46203 | GN20: =SUM(GN19,GL20,-GM20) -> 0 | GO20: 46218 | GV20: =SUM(GV19,GT20,-GU20) -> 0 | GW20: 46218 | HD20: =SUM(HD19,HB20,-HC20) -> 0 | HE20: 46218 | HL20: =SUM(HL19,HJ20,-HK20) -> 0 | HM20: 46218 | HT20: =SUM(HT19,HR20,-HS20) -> 0 | HU20: 46218 | IB20: =SUM(IB19,HZ20,-IA20) -> 0 | IC20: 46218 | IJ20: =SUM(IJ19,IH20,-II20) -> 0 | IK20: 46218 | IR20: =SUM(IR19,IP20,-IQ20) -> 0 | IS20: 46218 | IZ20: =SUM(IZ19,IX20,-IY20) -> 0 | JA20: 46218 | JH20: =SUM(JH19,JF20,-JG20) -> 0 | JI20: 46218 | JP20: =SUM(JP19,JN20,-JO20) -> 0 | JQ20: 46218 | JX20: =SUM(JX19,JV20,-JW20) -> 0 | JY20: 46218 | KF20: =SUM(KF19,KD20,-KE20) -> 0 | KG20: 46218 | KN20: =SUM(KN19,KL20,-KM20) -> 0 | KO20: 46218 | KV20: =SUM(KV19,KT20,-KU20) -> 0 | KW20: 46218 | LD20: =SUM(LD19,LB20,-LC20) -> 0 | LE20: 46218 | LL20: =SUM(LL19,LJ20,-LK20) -> 0 | LM20: 46218 | LT20: =SUM(LT19,LR20,-LS20) -> 0 | LU20: 46218 | MB20: =SUM(MB19,LZ20,-MA20) -> 0 | MC20: 46218 | MJ20: =SUM(MJ19,MH20,-MI20) -> 0 | MK20: 46218 | MR20: =SUM(MR19,MP20,-MQ20) -> 0 | MS20: 46218 | MZ20: =SUM(MZ19,MX20,-MY20) -> 0 | NA20: 46218 | NH20: =SUM(NH19,NF20,-NG20) -> 0 | NI20: 46218 | NP20: =SUM(NP19,NN20,-NO20) -> 0 | NQ20: 46218 | NX20: =SUM(NX19,NV20,-NW20) -> 0 | NY20: 46218 | OF20: =SUM(OF19,OD20,-OE20) -> 0 | OG20: 46218 | ON20: =SUM(ON19,OL20,-OM20) -> 0 | OO20: 46218 | OV20: =SUM(OV19,OT20,-OU20) -> 0 | OW20: 46218 | PD20: =SUM(PD19,PB20,-PC20) -> 0 | PE20: 46218 | PL20: =SUM(PL19,PJ20,-PK20) -> 0 | PM20: 46218 | PT20: =SUM(PT19,PR20,-PS20) -> 0 | PU20: 46218 | QB20: =SUM(QB19,PZ20,-QA20) -> 0 | QC20: 46218 | QJ20: =SUM(QJ19,QH20,-QI20) -> 0 | QK20: 46218 | QR20: =SUM(QR19,QP20,-QQ20) -> 0 | QS20: 46218 | QZ20: =SUM(QZ19,QX20,-QY20) -> 0 | RA20: 46218 | RH20: =SUM(RH19,RF20,-RG20) -> 0 | RI20: 46218 | RP20: =SUM(RP19,RN20,-RO20) -> 0 | RQ20: 46218 | RX20: =SUM(RX19,RV20,-RW20) -> 0 | RY20: 46218 | SF20: =SUM(SF19,SD20,-SE20) -> 0 | SG20: 46218 | SN20: =SUM(SN19,SL20,-SM20) -> 0 | SO20: 46218 | SV20: =SUM(SV19,ST20,-SU20) -> 0 | SW20: 46218 | TD20: =SUM(TD19,TB20,-TC20) -> 0 | TE20: 46218 | TL20: =SUM(TL19,TJ20,-TK20) -> 0 | TM20: 46218 | TT20: =SUM(TT19,TR20,-TS20) -> 0 | TU20: 46218 | UB20: =SUM(UB19,TZ20,-UA20) -> 0 | UC20: 46218 | UJ20: =SUM(UJ19,UH20,-UI20) -> 0 | UK20: 46218 | UR20: =SUM(UR19,UP20,-UQ20) -> 0 | US20: 46218 | UZ20: =SUM(UZ19,UX20,-UY20) -> 0 | VA20: 46218 | VH20: =SUM(VH19,VF20,-VG20) -> 0 | VI20: 46218 | VP20: =SUM(VP19,VN20,-VO20) -> 0 | VQ20: 46218 | VX20: =SUM(VX19,VV20,-VW20) -> 0 | VY20: 46218 | WF20: =SUM(WF19,WD20,-WE20) -> 0 | WG20: 46218 | WN20: =SUM(WN19,WL20,-WM20) -> 0 | WO20: 46218 | WV20: =SUM(WV19,WT20,-WU20) -> 0 | WW20: 46218 | XD20: =SUM(XD19,XB20,-XC20) -> 0 | XE20: 46218 | XL20: =SUM(XL19,XJ20,-XK20) -> 0 | XM20: 46218 | XT20: =SUM(XT19,XR20,-XS20) -> 0 | XU20: 46218 | YB20: =SUM(YB19,XZ20,-YA20) -> 0 | YC20: 46218 | YJ20: =SUM(YJ19,YH20,-YI20) -> 0 | YK20: 46218 | YR20: =SUM(YR19,YP20,-YQ20) -> 0 | YS20: 46218 | YZ20: =SUM(YZ19,YX20,-YY20) -> 0 | ZA20: 46218 | ZH20: =SUM(ZH19,ZF20,-ZG20) -> 0 | ZI20: 46218 | ZP20: =SUM(ZP19,ZN20,-ZO20) -> 0 | ZQ20: 46218 | ZX20: =SUM(ZX19,ZV20,-ZW20) -> 0 | ZY20: 46218 | AAF20: =SUM(AAF19,AAD20,-AAE20) -> 0 | AAG20: 46218 | AAN20: =SUM(AAN19,AAL20,-AAM20) -> 0 | AAO20: 46218 | AAV20: =SUM(AAV19,AAT20,-AAU20) -> 0 | AAW20: 46218 | ABD20: =SUM(ABD19,ABB20,-ABC20) -> 0 | ABE20: 46218 | ABL20: =SUM(ABL19,ABJ20,-ABK20) -> 0 | ABM20: 46218 | ABT20: =SUM(ABT19,ABR20,-ABS20) -> 0 | ABU20: 46218 | ACB20: =SUM(ACB19,ABZ20,-ACA20) -> 0 | ACC20: 46218
D21: =SUM(D20,B21,-C21) -> 1700 | E21: 46218 | L21: =SUM(L20,J21,-K21) -> 1000 | M21: 46218 | T21: =SUM(T20,R21,-S21) -> 4000 | U21: 46218 | AB21: =SUM(AB20,Z21,-AA21) -> 1000 | AC21: 46218 | AJ21: =SUM(AJ20,AH21,-AI21) -> 2000 | AK21: 46218 | AR21: =SUM(AR20,AP21,-AQ21) -> 1000 | AS21: 46218 | AZ21: =SUM(AZ20,AX21,-AY21) -> 1150 | BA21: 46218 | BH21: =SUM(BH20,BF21,-BG21) -> 7000 | BI21: 46218 | BP21: =SUM(BP20,BN21,-BO21) -> 1000 | BQ21: 46218 | BX21: =SUM(BX20,BV21,-BW21) -> 0 | BY21: 46218 | CF21: =SUM(CF20,CD21,-CE21) -> 0 | CG21: 46233 | CN21: =SUM(CN20,CL21,-CM21) -> 0 | CO21: 46233 | CV21: =SUM(CV20,CT21,-CU21) -> 0 | CW21: 46233 | DD21: =SUM(DD20,DB21,-DC21) -> 0 | DE21: 46233 | DL21: =SUM(DL20,DJ21,-DK21) -> 0 | DM21: 46218 | DT21: =SUM(DT20,DR21,-DS21) -> 0 | DU21: 46218 | EB21: =SUM(EB20,DZ21,-EA21) -> 0 | EC21: 46218 | EJ21: =SUM(EJ20,EH21,-EI21) -> 0 | EK21: 46218 | ER21: =SUM(ER20,EP21,-EQ21) -> 0 | ES21: 46218 | EZ21: =SUM(EZ20,EX21,-EY21) -> 0 | FA21: 46218 | FH21: =SUM(FH20,FF21,-FG21) -> 0 | FI21: 46218 | FP21: =SUM(FP20,FN21,-FO21) -> 0 | FQ21: 46218 | FX21: =SUM(FX20,FV21,-FW21) -> 0 | FY21: 46218 | GF21: =SUM(GF20,GD21,-GE21) -> 0 | GG21: 46218 | GN21: =SUM(GN20,GL21,-GM21) -> 0 | GO21: 46233 | GV21: =SUM(GV20,GT21,-GU21) -> 0 | GW21: 46233 | HD21: =SUM(HD20,HB21,-HC21) -> 0 | HE21: 46233 | HL21: =SUM(HL20,HJ21,-HK21) -> 0 | HM21: 46233 | HT21: =SUM(HT20,HR21,-HS21) -> 0 | HU21: 46233 | IB21: =SUM(IB20,HZ21,-IA21) -> 0 | IC21: 46233 | IJ21: =SUM(IJ20,IH21,-II21) -> 0 | IK21: 46233 | IR21: =SUM(IR20,IP21,-IQ21) -> 0 | IS21: 46233 | IZ21: =SUM(IZ20,IX21,-IY21) -> 0 | JA21: 46233 | JH21: =SUM(JH20,JF21,-JG21) -> 0 | JI21: 46233 | JP21: =SUM(JP20,JN21,-JO21) -> 0 | JQ21: 46233 | JX21: =SUM(JX20,JV21,-JW21) -> 0 | JY21: 46233 | KF21: =SUM(KF20,KD21,-KE21) -> 0 | KG21: 46233 | KN21: =SUM(KN20,KL21,-KM21) -> 0 | KO21: 46233 | KV21: =SUM(KV20,KT21,-KU21) -> 0 | KW21: 46233 | LD21: =SUM(LD20,LB21,-LC21) -> 0 | LE21: 46233 | LL21: =SUM(LL20,LJ21,-LK21) -> 0 | LM21: 46233 | LT21: =SUM(LT20,LR21,-LS21) -> 0 | LU21: 46233 | MB21: =SUM(MB20,LZ21,-MA21) -> 0 | MC21: 46233 | MJ21: =SUM(MJ20,MH21,-MI21) -> 0 | MK21: 46233 | MR21: =SUM(MR20,MP21,-MQ21) -> 0 | MS21: 46233 | MZ21: =SUM(MZ20,MX21,-MY21) -> 0 | NA21: 46233 | NH21: =SUM(NH20,NF21,-NG21) -> 0 | NI21: 46233 | NP21: =SUM(NP20,NN21,-NO21) -> 0 | NQ21: 46233 | NX21: =SUM(NX20,NV21,-NW21) -> 0 | NY21: 46233 | OF21: =SUM(OF20,OD21,-OE21) -> 0 | OG21: 46233 | ON21: =SUM(ON20,OL21,-OM21) -> 0 | OO21: 46233 | OV21: =SUM(OV20,OT21,-OU21) -> 0 | OW21: 46233 | PD21: =SUM(PD20,PB21,-PC21) -> 0 | PE21: 46233 | PL21: =SUM(PL20,PJ21,-PK21) -> 0 | PM21: 46233 | PT21: =SUM(PT20,PR21,-PS21) -> 0 | PU21: 46233 | QB21: =SUM(QB20,PZ21,-QA21) -> 0 | QC21: 46233 | QJ21: =SUM(QJ20,QH21,-QI21) -> 0 | QK21: 46233 | QR21: =SUM(QR20,QP21,-QQ21) -> 0 | QS21: 46233 | QZ21: =SUM(QZ20,QX21,-QY21) -> 0 | RA21: 46233 | RH21: =SUM(RH20,RF21,-RG21) -> 0 | RI21: 46233 | RP21: =SUM(RP20,RN21,-RO21) -> 0 | RQ21: 46233 | RX21: =SUM(RX20,RV21,-RW21) -> 0 | RY21: 46233 | SF21: =SUM(SF20,SD21,-SE21) -> 0 | SG21: 46233 | SN21: =SUM(SN20,SL21,-SM21) -> 0 | SO21: 46233 | SV21: =SUM(SV20,ST21,-SU21) -> 0 | SW21: 46233 | TD21: =SUM(TD20,TB21,-TC21) -> 0 | TE21: 46233 | TL21: =SUM(TL20,TJ21,-TK21) -> 0 | TM21: 46233 | TT21: =SUM(TT20,TR21,-TS21) -> 0 | TU21: 46233 | UB21: =SUM(UB20,TZ21,-UA21) -> 0 | UC21: 46233 | UJ21: =SUM(UJ20,UH21,-UI21) -> 0 | UK21: 46233 | UR21: =SUM(UR20,UP21,-UQ21) -> 0 | US21: 46233 | UZ21: =SUM(UZ20,UX21,-UY21) -> 0 | VA21: 46233 | VH21: =SUM(VH20,VF21,-VG21) -> 0 | VI21: 46233 | VP21: =SUM(VP20,VN21,-VO21) -> 0 | VQ21: 46233 | VX21: =SUM(VX20,VV21,-VW21) -> 0 | VY21: 46233 | WF21: =SUM(WF20,WD21,-WE21) -> 0 | WG21: 46233 | WN21: =SUM(WN20,WL21,-WM21) -> 0 | WO21: 46233 | WV21: =SUM(WV20,WT21,-WU21) -> 0 | WW21: 46233 | XD21: =SUM(XD20,XB21,-XC21) -> 0 | XE21: 46233 | XL21: =SUM(XL20,XJ21,-XK21) -> 0 | XM21: 46233 | XT21: =SUM(XT20,XR21,-XS21) -> 0 | XU21: 46233 | YB21: =SUM(YB20,XZ21,-YA21) -> 0 | YC21: 46233 | YJ21: =SUM(YJ20,YH21,-YI21) -> 0 | YK21: 46233 | YR21: =SUM(YR20,YP21,-YQ21) -> 0 | YS21: 46233 | YZ21: =SUM(YZ20,YX21,-YY21) -> 0 | ZA21: 46233 | ZH21: =SUM(ZH20,ZF21,-ZG21) -> 0 | ZI21: 46233 | ZP21: =SUM(ZP20,ZN21,-ZO21) -> 0 | ZQ21: 46233 | ZX21: =SUM(ZX20,ZV21,-ZW21) -> 0 | ZY21: 46233 | AAF21: =SUM(AAF20,AAD21,-AAE21) -> 0 | AAG21: 46233 | AAN21: =SUM(AAN20,AAL21,-AAM21) -> 0 | AAO21: 46233 | AAV21: =SUM(AAV20,AAT21,-AAU21) -> 0 | AAW21: 46233 | ABD21: =SUM(ABD20,ABB21,-ABC21) -> 0 | ABE21: 46233 | ABL21: =SUM(ABL20,ABJ21,-ABK21) -> 0 | ABM21: 46233 | ABT21: =SUM(ABT20,ABR21,-ABS21) -> 0 | ABU21: 46233 | ACB21: =SUM(ACB20,ABZ21,-ACA21) -> 0 | ACC21: 46233
D22: =SUM(D21,B22,-C22) -> 1700 | E22: 46233 | L22: =SUM(L21,J22,-K22) -> 1000 | M22: 46233 | T22: =SUM(T21,R22,-S22) -> 4000 | U22: 46233 | AB22: =SUM(AB21,Z22,-AA22) -> 1000 | AC22: 46233 | AJ22: =SUM(AJ21,AH22,-AI22) -> 2000 | AK22: 46233 | AR22: =SUM(AR21,AP22,-AQ22) -> 1000 | AS22: 46233 | AZ22: =SUM(AZ21,AX22,-AY22) -> 1150 | BA22: 46233 | BH22: =SUM(BH21,BF22,-BG22) -> 7000 | BI22: 46233 | BP22: =SUM(BP21,BN22,-BO22) -> 1000 | BQ22: 46233 | BX22: =SUM(BX21,BV22,-BW22) -> 0 | BY22: 46233 | CF22: =SUM(CF21,CD22,-CE22) -> 0 | CG22: 46249 | CN22: =SUM(CN21,CL22,-CM22) -> 0 | CO22: 46249 | CV22: =SUM(CV21,CT22,-CU22) -> 0 | CW22: 46249 | DD22: =SUM(DD21,DB22,-DC22) -> 0 | DE22: 46249 | DL22: =SUM(DL21,DJ22,-DK22) -> 0 | DM22: 46233 | DT22: =SUM(DT21,DR22,-DS22) -> 0 | DU22: 46233 | EB22: =SUM(EB21,DZ22,-EA22) -> 0 | EC22: 46233 | EJ22: =SUM(EJ21,EH22,-EI22) -> 0 | EK22: 46233 | ER22: =SUM(ER21,EP22,-EQ22) -> 0 | ES22: 46233 | EZ22: =SUM(EZ21,EX22,-EY22) -> 0 | FA22: 46233 | FH22: =SUM(FH21,FF22,-FG22) -> 0 | FI22: 46233 | FP22: =SUM(FP21,FN22,-FO22) -> 0 | FQ22: 46233 | FX22: =SUM(FX21,FV22,-FW22) -> 0 | FY22: 46233 | GF22: =SUM(GF21,GD22,-GE22) -> 0 | GG22: 46233 | GN22: =SUM(GN21,GL22,-GM22) -> 0 | GO22: 46249 | GV22: =SUM(GV21,GT22,-GU22) -> 0 | GW22: 46249 | HD22: =SUM(HD21,HB22,-HC22) -> 0 | HE22: 46249 | HL22: =SUM(HL21,HJ22,-HK22) -> 0 | HM22: 46249 | HT22: =SUM(HT21,HR22,-HS22) -> 0 | HU22: 46249 | IB22: =SUM(IB21,HZ22,-IA22) -> 0 | IC22: 46249 | IJ22: =SUM(IJ21,IH22,-II22) -> 0 | IK22: 46249 | IR22: =SUM(IR21,IP22,-IQ22) -> 0 | IS22: 46249 | IZ22: =SUM(IZ21,IX22,-IY22) -> 0 | JA22: 46249 | JH22: =SUM(JH21,JF22,-JG22) -> 0 | JI22: 46249 | JP22: =SUM(JP21,JN22,-JO22) -> 0 | JQ22: 46249 | JX22: =SUM(JX21,JV22,-JW22) -> 0 | JY22: 46249 | KF22: =SUM(KF21,KD22,-KE22) -> 0 | KG22: 46249 | KN22: =SUM(KN21,KL22,-KM22) -> 0 | KO22: 46249 | KQ22: 0 | KV22: =SUM(KV21,KT22,-KU22) -> 0 | KW22: 46249 | KY22: 0 | LD22: =SUM(LD21,LB22,-LC22) -> 0 | LE22: 46249 | LG22: 0 | LL22: =SUM(LL21,LJ22,-LK22) -> 0 | LM22: 46249 | LO22: 0 | LT22: =SUM(LT21,LR22,-LS22) -> 0 | LU22: 46249 | LW22: 0 | MB22: =SUM(MB21,LZ22,-MA22) -> 0 | MC22: 46249 | MJ22: =SUM(MJ21,MH22,-MI22) -> 0 | MK22: 46249 | MR22: =SUM(MR21,MP22,-MQ22) -> 0 | MS22: 46249 | MZ22: =SUM(MZ21,MX22,-MY22) -> 0 | NA22: 46249 | NH22: =SUM(NH21,NF22,-NG22) -> 0 | NI22: 46249 | NP22: =SUM(NP21,NN22,-NO22) -> 0 | NQ22: 46249 | NX22: =SUM(NX21,NV22,-NW22) -> 0 | NY22: 46249 | OF22: =SUM(OF21,OD22,-OE22) -> 0 | OG22: 46249 | ON22: =SUM(ON21,OL22,-OM22) -> 0 | OO22: 46249 | OV22: =SUM(OV21,OT22,-OU22) -> 0 | OW22: 46249 | PD22: =SUM(PD21,PB22,-PC22) -> 0 | PE22: 46249 | PL22: =SUM(PL21,PJ22,-PK22) -> 0 | PM22: 46249 | PT22: =SUM(PT21,PR22,-PS22) -> 0 | PU22: 46249 | QB22: =SUM(QB21,PZ22,-QA22) -> 0 | QC22: 46249 | QJ22: =SUM(QJ21,QH22,-QI22) -> 0 | QK22: 46249 | QR22: =SUM(QR21,QP22,-QQ22) -> 0 | QS22: 46249 | QZ22: =SUM(QZ21,QX22,-QY22) -> 0 | RA22: 46249 | RH22: =SUM(RH21,RF22,-RG22) -> 0 | RI22: 46249 | RP22: =SUM(RP21,RN22,-RO22) -> 0 | RQ22: 46249 | RX22: =SUM(RX21,RV22,-RW22) -> 0 | RY22: 46249 | SF22: =SUM(SF21,SD22,-SE22) -> 0 | SG22: 46249 | SN22: =SUM(SN21,SL22,-SM22) -> 0 | SO22: 46249 | SV22: =SUM(SV21,ST22,-SU22) -> 0 | SW22: 46249 | TD22: =SUM(TD21,TB22,-TC22) -> 0 | TE22: 46249 | TL22: =SUM(TL21,TJ22,-TK22) -> 0 | TM22: 46249 | TT22: =SUM(TT21,TR22,-TS22) -> 0 | TU22: 46249 | UB22: =SUM(UB21,TZ22,-UA22) -> 0 | UC22: 46249 | UJ22: =SUM(UJ21,UH22,-UI22) -> 0 | UK22: 46249 | UR22: =SUM(UR21,UP22,-UQ22) -> 0 | US22: 46249 | UZ22: =SUM(UZ21,UX22,-UY22) -> 0 | VA22: 46249 | VH22: =SUM(VH21,VF22,-VG22) -> 0 | VI22: 46249 | VP22: =SUM(VP21,VN22,-VO22) -> 0 | VQ22: 46249 | VX22: =SUM(VX21,VV22,-VW22) -> 0 | VY22: 46249 | WF22: =SUM(WF21,WD22,-WE22) -> 0 | WG22: 46249 | WN22: =SUM(WN21,WL22,-WM22) -> 0 | WO22: 46249 | WV22: =SUM(WV21,WT22,-WU22) -> 0 | WW22: 46249 | XD22: =SUM(XD21,XB22,-XC22) -> 0 | XE22: 46249 | XL22: =SUM(XL21,XJ22,-XK22) -> 0 | XM22: 46249 | XT22: =SUM(XT21,XR22,-XS22) -> 0 | XU22: 46249 | YB22: =SUM(YB21,XZ22,-YA22) -> 0 | YC22: 46249 | YJ22: =SUM(YJ21,YH22,-YI22) -> 0 | YK22: 46249 | YR22: =SUM(YR21,YP22,-YQ22) -> 0 | YS22: 46249 | YZ22: =SUM(YZ21,YX22,-YY22) -> 0 | ZA22: 46249 | ZH22: =SUM(ZH21,ZF22,-ZG22) -> 0 | ZI22: 46249 | ZP22: =SUM(ZP21,ZN22,-ZO22) -> 0 | ZQ22: 46249 | ZX22: =SUM(ZX21,ZV22,-ZW22) -> 0 | ZY22: 46249 | AAF22: =SUM(AAF21,AAD22,-AAE22) -> 0 | AAG22: 46249 | AAN22: =SUM(AAN21,AAL22,-AAM22) -> 0 | AAO22: 46249 | AAV22: =SUM(AAV21,AAT22,-AAU22) -> 0 | AAW22: 46249 | ABD22: =SUM(ABD21,ABB22,-ABC22) -> 0 | ABE22: 46249 | ABL22: =SUM(ABL21,ABJ22,-ABK22) -> 0 | ABM22: 46249 | ABT22: =SUM(ABT21,ABR22,-ABS22) -> 0 | ABU22: 46249 | ACB22: =SUM(ACB21,ABZ22,-ACA22) -> 0 | ACC22: 46249
D23: =SUM(D22,B23,-C23) -> 1700 | E23: 46249 | L23: =SUM(L22,J23,-K23) -> 1000 | M23: 46249 | T23: =SUM(T22,R23,-S23) -> 4000 | U23: 46249 | AB23: =SUM(AB22,Z23,-AA23) -> 1000 | AC23: 46249 | AJ23: =SUM(AJ22,AH23,-AI23) -> 2000 | AK23: 46249 | AR23: =SUM(AR22,AP23,-AQ23) -> 1000 | AS23: 46249 | AZ23: =SUM(AZ22,AX23,-AY23) -> 1150 | BA23: 46249 | BH23: =SUM(BH22,BF23,-BG23) -> 7000 | BI23: 46249 | BP23: =SUM(BP22,BN23,-BO23) -> 1000 | BQ23: 46249 | BX23: =SUM(BX22,BV23,-BW23) -> 0 | BY23: 46249 | CF23: =SUM(CF22,CD23,-CE23) -> 0 | CG23: 46264 | CN23: =SUM(CN22,CL23,-CM23) -> 0 | CO23: 46264 | CV23: =SUM(CV22,CT23,-CU23) -> 0 | CW23: 46264 | DD23: =SUM(DD22,DB23,-DC23) -> 0 | DE23: 46264 | DL23: =SUM(DL22,DJ23,-DK23) -> 0 | DM23: 46249 | DT23: =SUM(DT22,DR23,-DS23) -> 0 | DU23: 46249 | EB23: =SUM(EB22,DZ23,-EA23) -> 0 | EC23: 46249 | EJ23: =SUM(EJ22,EH23,-EI23) -> 0 | EK23: 46249 | ER23: =SUM(ER22,EP23,-EQ23) -> 0 | ES23: 46249 | EZ23: =SUM(EZ22,EX23,-EY23) -> 0 | FA23: 46249 | FH23: =SUM(FH22,FF23,-FG23) -> 0 | FI23: 46249 | FP23: =SUM(FP22,FN23,-FO23) -> 0 | FQ23: 46249 | FX23: =SUM(FX22,FV23,-FW23) -> 0 | FY23: 46249 | GF23: =SUM(GF22,GD23,-GE23) -> 0 | GG23: 46249 | GN23: =SUM(GN22,GL23,-GM23) -> 0 | GO23: 46264 | GV23: =SUM(GV22,GT23,-GU23) -> 0 | GW23: 46264 | HD23: =SUM(HD22,HB23,-HC23) -> 0 | HE23: 46264 | HL23: =SUM(HL22,HJ23,-HK23) -> 0 | HM23: 46264 | HT23: =SUM(HT22,HR23,-HS23) -> 0 | HU23: 46264 | IB23: =SUM(IB22,HZ23,-IA23) -> 0 | IC23: 46264 | IJ23: =SUM(IJ22,IH23,-II23) -> 0 | IK23: 46264 | IR23: =SUM(IR22,IP23,-IQ23) -> 0 | IS23: 46264 | IZ23: =SUM(IZ22,IX23,-IY23) -> 0 | JA23: 46264 | JH23: =SUM(JH22,JF23,-JG23) -> 0 | JI23: 46264 | JP23: =SUM(JP22,JN23,-JO23) -> 0 | JQ23: 46264 | JX23: =SUM(JX22,JV23,-JW23) -> 0 | JY23: 46264 | KF23: =SUM(KF22,KD23,-KE23) -> 0 | KG23: 46264 | KN23: =SUM(KN22,KL23,-KM23) -> 0 | KO23: 46264 | KV23: =SUM(KV22,KT23,-KU23) -> 0 | KW23: 46264 | LD23: =SUM(LD22,LB23,-LC23) -> 0 | LE23: 46264 | LL23: =SUM(LL22,LJ23,-LK23) -> 0 | LM23: 46264 | LT23: =SUM(LT22,LR23,-LS23) -> 0 | LU23: 46264 | MB23: =SUM(MB22,LZ23,-MA23) -> 0 | MC23: 46264 | MJ23: =SUM(MJ22,MH23,-MI23) -> 0 | MK23: 46264 | MR23: =SUM(MR22,MP23,-MQ23) -> 0 | MS23: 46264 | MZ23: =SUM(MZ22,MX23,-MY23) -> 0 | NA23: 46264 | NH23: =SUM(NH22,NF23,-NG23) -> 0 | NI23: 46264 | NP23: =SUM(NP22,NN23,-NO23) -> 0 | NQ23: 46264 | NX23: =SUM(NX22,NV23,-NW23) -> 0 | NY23: 46264 | OF23: =SUM(OF22,OD23,-OE23) -> 0 | OG23: 46264 | ON23: =SUM(ON22,OL23,-OM23) -> 0 | OO23: 46264 | OV23: =SUM(OV22,OT23,-OU23) -> 0 | OW23: 46264 | PD23: =SUM(PD22,PB23,-PC23) -> 0 | PE23: 46264 | PL23: =SUM(PL22,PJ23,-PK23) -> 0 | PM23: 46264 | PT23: =SUM(PT22,PR23,-PS23) -> 0 | PU23: 46264 | QB23: =SUM(QB22,PZ23,-QA23) -> 0 | QC23: 46264 | QJ23: =SUM(QJ22,QH23,-QI23) -> 0 | QK23: 46264 | QR23: =SUM(QR22,QP23,-QQ23) -> 0 | QS23: 46264 | QZ23: =SUM(QZ22,QX23,-QY23) -> 0 | RA23: 46264 | RH23: =SUM(RH22,RF23,-RG23) -> 0 | RI23: 46264 | RP23: =SUM(RP22,RN23,-RO23) -> 0 | RQ23: 46264 | RX23: =SUM(RX22,RV23,-RW23) -> 0 | RY23: 46264 | SF23: =SUM(SF22,SD23,-SE23) -> 0 | SG23: 46264 | SN23: =SUM(SN22,SL23,-SM23) -> 0 | SO23: 46264 | SV23: =SUM(SV22,ST23,-SU23) -> 0 | SW23: 46264 | TD23: =SUM(TD22,TB23,-TC23) -> 0 | TE23: 46264 | TL23: =SUM(TL22,TJ23,-TK23) -> 0 | TM23: 46264 | TT23: =SUM(TT22,TR23,-TS23) -> 0 | TU23: 46264 | UB23: =SUM(UB22,TZ23,-UA23) -> 0 | UC23: 46264 | UJ23: =SUM(UJ22,UH23,-UI23) -> 0 | UK23: 46264 | UR23: =SUM(UR22,UP23,-UQ23) -> 0 | US23: 46264 | UZ23: =SUM(UZ22,UX23,-UY23) -> 0 | VA23: 46264 | VH23: =SUM(VH22,VF23,-VG23) -> 0 | VI23: 46264 | VP23: =SUM(VP22,VN23,-VO23) -> 0 | VQ23: 46264 | VX23: =SUM(VX22,VV23,-VW23) -> 0 | VY23: 46264 | WF23: =SUM(WF22,WD23,-WE23) -> 0 | WG23: 46264 | WN23: =SUM(WN22,WL23,-WM23) -> 0 | WO23: 46264 | WV23: =SUM(WV22,WT23,-WU23) -> 0 | WW23: 46264 | XD23: =SUM(XD22,XB23,-XC23) -> 0 | XE23: 46264 | XL23: =SUM(XL22,XJ23,-XK23) -> 0 | XM23: 46264 | XT23: =SUM(XT22,XR23,-XS23) -> 0 | XU23: 46264 | YB23: =SUM(YB22,XZ23,-YA23) -> 0 | YC23: 46264 | YJ23: =SUM(YJ22,YH23,-YI23) -> 0 | YK23: 46264 | YR23: =SUM(YR22,YP23,-YQ23) -> 0 | YS23: 46264 | YZ23: =SUM(YZ22,YX23,-YY23) -> 0 | ZA23: 46264 | ZH23: =SUM(ZH22,ZF23,-ZG23) -> 0 | ZI23: 46264 | ZP23: =SUM(ZP22,ZN23,-ZO23) -> 0 | ZQ23: 46264 | ZX23: =SUM(ZX22,ZV23,-ZW23) -> 0 | ZY23: 46264 | AAF23: =SUM(AAF22,AAD23,-AAE23) -> 0 | AAG23: 46264 | AAN23: =SUM(AAN22,AAL23,-AAM23) -> 0 | AAO23: 46264 | AAV23: =SUM(AAV22,AAT23,-AAU23) -> 0 | AAW23: 46264 | ABD23: =SUM(ABD22,ABB23,-ABC23) -> 0 | ABE23: 46264 | ABL23: =SUM(ABL22,ABJ23,-ABK23) -> 0 | ABM23: 46264 | ABT23: =SUM(ABT22,ABR23,-ABS23) -> 0 | ABU23: 46264 | ACB23: =SUM(ACB22,ABZ23,-ACA23) -> 0 | ACC23: 46264
D24: =SUM(D23,B24,-C24) -> 1700 | E24: 46264 | L24: =SUM(L23,J24,-K24) -> 1000 | M24: 46264 | T24: =SUM(T23,R24,-S24) -> 4000 | U24: 46264 | AB24: =SUM(AB23,Z24,-AA24) -> 1000 | AC24: 46264 | AJ24: =SUM(AJ23,AH24,-AI24) -> 2000 | AK24: 46264 | AR24: =SUM(AR23,AP24,-AQ24) -> 1000 | AS24: 46264 | AZ24: =SUM(AZ23,AX24,-AY24) -> 1150 | BA24: 46264 | BH24: =SUM(BH23,BF24,-BG24) -> 7000 | BI24: 46264 | BP24: =SUM(BP23,BN24,-BO24) -> 1000 | BQ24: 46264 | BX24: =SUM(BX23,BV24,-BW24) -> 0 | BY24: 46264 | CF24: =SUM(CF23,CD24,-CE24) -> 0 | CG24: 46280 | CN24: =SUM(CN23,CL24,-CM24) -> 0 | CO24: 46280 | CV24: =SUM(CV23,CT24,-CU24) -> 0 | CW24: 46280 | DD24: =SUM(DD23,DB24,-DC24) -> 0 | DE24: 46280 | DL24: =SUM(DL23,DJ24,-DK24) -> 0 | DM24: 46264 | DT24: =SUM(DT23,DR24,-DS24) -> 0 | DU24: 46264 | EB24: =SUM(EB23,DZ24,-EA24) -> 0 | EC24: 46264 | EJ24: =SUM(EJ23,EH24,-EI24) -> 0 | EK24: 46264 | ER24: =SUM(ER23,EP24,-EQ24) -> 0 | ES24: 46264 | EZ24: =SUM(EZ23,EX24,-EY24) -> 0 | FA24: 46264 | FH24: =SUM(FH23,FF24,-FG24) -> 0 | FI24: 46264 | FP24: =SUM(FP23,FN24,-FO24) -> 0 | FQ24: 46264 | FX24: =SUM(FX23,FV24,-FW24) -> 0 | FY24: 46264 | GF24: =SUM(GF23,GD24,-GE24) -> 0 | GG24: 46264 | GN24: =SUM(GN23,GL24,-GM24) -> 0 | GO24: 46280 | GV24: =SUM(GV23,GT24,-GU24) -> 0 | GW24: 46280 | HD24: =SUM(HD23,HB24,-HC24) -> 0 | HE24: 46280 | HL24: =SUM(HL23,HJ24,-HK24) -> 0 | HM24: 46280 | HT24: =SUM(HT23,HR24,-HS24) -> 0 | HU24: 46280 | IB24: =SUM(IB23,HZ24,-IA24) -> 0 | IC24: 46280 | IJ24: =SUM(IJ23,IH24,-II24) -> 0 | IK24: 46280 | IR24: =SUM(IR23,IP24,-IQ24) -> 0 | IS24: 46280 | IZ24: =SUM(IZ23,IX24,-IY24) -> 0 | JA24: 46280 | JH24: =SUM(JH23,JF24,-JG24) -> 0 | JI24: 46280 | JP24: =SUM(JP23,JN24,-JO24) -> 0 | JQ24: 46280 | JX24: =SUM(JX23,JV24,-JW24) -> 0 | JY24: 46280 | KF24: =SUM(KF23,KD24,-KE24) -> 0 | KG24: 46280 | KN24: =SUM(KN23,KL24,-KM24) -> 0 | KO24: 46280 | KV24: =SUM(KV23,KT24,-KU24) -> 0 | KW24: 46280 | LD24: =SUM(LD23,LB24,-LC24) -> 0 | LE24: 46280 | LL24: =SUM(LL23,LJ24,-LK24) -> 0 | LM24: 46280 | LT24: =SUM(LT23,LR24,-LS24) -> 0 | LU24: 46280 | MB24: =SUM(MB23,LZ24,-MA24) -> 0 | MC24: 46280 | MJ24: =SUM(MJ23,MH24,-MI24) -> 0 | MK24: 46280 | MR24: =SUM(MR23,MP24,-MQ24) -> 0 | MS24: 46280 | MZ24: =SUM(MZ23,MX24,-MY24) -> 0 | NA24: 46280 | NH24: =SUM(NH23,NF24,-NG24) -> 0 | NI24: 46280 | NP24: =SUM(NP23,NN24,-NO24) -> 0 | NQ24: 46280 | NX24: =SUM(NX23,NV24,-NW24) -> 0 | NY24: 46280 | OF24: =SUM(OF23,OD24,-OE24) -> 0 | OG24: 46280 | ON24: =SUM(ON23,OL24,-OM24) -> 0 | OO24: 46280 | OV24: =SUM(OV23,OT24,-OU24) -> 0 | OW24: 46280 | PD24: =SUM(PD23,PB24,-PC24) -> 0 | PE24: 46280 | PL24: =SUM(PL23,PJ24,-PK24) -> 0 | PM24: 46280 | PT24: =SUM(PT23,PR24,-PS24) -> 0 | PU24: 46280 | QB24: =SUM(QB23,PZ24,-QA24) -> 0 | QC24: 46280 | QJ24: =SUM(QJ23,QH24,-QI24) -> 0 | QK24: 46280 | QR24: =SUM(QR23,QP24,-QQ24) -> 0 | QS24: 46280 | QZ24: =SUM(QZ23,QX24,-QY24) -> 0 | RA24: 46280 | RH24: =SUM(RH23,RF24,-RG24) -> 0 | RI24: 46280 | RP24: =SUM(RP23,RN24,-RO24) -> 0 | RQ24: 46280 | RX24: =SUM(RX23,RV24,-RW24) -> 0 | RY24: 46280 | SF24: =SUM(SF23,SD24,-SE24) -> 0 | SG24: 46280 | SN24: =SUM(SN23,SL24,-SM24) -> 0 | SO24: 46280 | SV24: =SUM(SV23,ST24,-SU24) -> 0 | SW24: 46280 | TD24: =SUM(TD23,TB24,-TC24) -> 0 | TE24: 46280 | TL24: =SUM(TL23,TJ24,-TK24) -> 0 | TM24: 46280 | TT24: =SUM(TT23,TR24,-TS24) -> 0 | TU24: 46280 | UB24: =SUM(UB23,TZ24,-UA24) -> 0 | UC24: 46280 | UJ24: =SUM(UJ23,UH24,-UI24) -> 0 | UK24: 46280 | UR24: =SUM(UR23,UP24,-UQ24) -> 0 | US24: 46280 | UZ24: =SUM(UZ23,UX24,-UY24) -> 0 | VA24: 46280 | VH24: =SUM(VH23,VF24,-VG24) -> 0 | VI24: 46280 | VP24: =SUM(VP23,VN24,-VO24) -> 0 | VQ24: 46280 | VX24: =SUM(VX23,VV24,-VW24) -> 0 | VY24: 46280 | WF24: =SUM(WF23,WD24,-WE24) -> 0 | WG24: 46280 | WN24: =SUM(WN23,WL24,-WM24) -> 0 | WO24: 46280 | WV24: =SUM(WV23,WT24,-WU24) -> 0 | WW24: 46280 | XD24: =SUM(XD23,XB24,-XC24) -> 0 | XE24: 46280 | XL24: =SUM(XL23,XJ24,-XK24) -> 0 | XM24: 46280 | XT24: =SUM(XT23,XR24,-XS24) -> 0 | XU24: 46280 | YB24: =SUM(YB23,XZ24,-YA24) -> 0 | YC24: 46280 | YJ24: =SUM(YJ23,YH24,-YI24) -> 0 | YK24: 46280 | YR24: =SUM(YR23,YP24,-YQ24) -> 0 | YS24: 46280 | YZ24: =SUM(YZ23,YX24,-YY24) -> 0 | ZA24: 46280 | ZH24: =SUM(ZH23,ZF24,-ZG24) -> 0 | ZI24: 46280 | ZP24: =SUM(ZP23,ZN24,-ZO24) -> 0 | ZQ24: 46280 | ZX24: =SUM(ZX23,ZV24,-ZW24) -> 0 | ZY24: 46280 | AAF24: =SUM(AAF23,AAD24,-AAE24) -> 0 | AAG24: 46280 | AAN24: =SUM(AAN23,AAL24,-AAM24) -> 0 | AAO24: 46280 | AAV24: =SUM(AAV23,AAT24,-AAU24) -> 0 | AAW24: 46280 | ABD24: =SUM(ABD23,ABB24,-ABC24) -> 0 | ABE24: 46280 | ABL24: =SUM(ABL23,ABJ24,-ABK24) -> 0 | ABM24: 46280 | ABT24: =SUM(ABT23,ABR24,-ABS24) -> 0 | ABU24: 46280 | ACB24: =SUM(ACB23,ABZ24,-ACA24) -> 0 | ACC24: 46280
D25: =SUM(D24,B25,-C25) -> 1700 | E25: 46280 | L25: =SUM(L24,J25,-K25) -> 1000 | M25: 46280 | T25: =SUM(T24,R25,-S25) -> 4000 | U25: 46280 | AB25: =SUM(AB24,Z25,-AA25) -> 1000 | AC25: 46280 | AJ25: =SUM(AJ24,AH25,-AI25) -> 2000 | AK25: 46280 | AR25: =SUM(AR24,AP25,-AQ25) -> 1000 | AS25: 46280 | AZ25: =SUM(AZ24,AX25,-AY25) -> 1150 | BA25: 46280 | BH25: =SUM(BH24,BF25,-BG25) -> 7000 | BI25: 46280 | BP25: =SUM(BP24,BN25,-BO25) -> 1000 | BQ25: 46280 | BX25: =SUM(BX24,BV25,-BW25) -> 0 | BY25: 46280 | CF25: =SUM(CF24,CD25,-CE25) -> 0 | CG25: 46295 | CN25: =SUM(CN24,CL25,-CM25) -> 0 | CO25: 46295 | CV25: =SUM(CV24,CT25,-CU25) -> 0 | CW25: 46295 | DD25: =SUM(DD24,DB25,-DC25) -> 0 | DE25: 46295 | DL25: =SUM(DL24,DJ25,-DK25) -> 0 | DM25: 46280 | DT25: =SUM(DT24,DR25,-DS25) -> 0 | DU25: 46280 | EB25: =SUM(EB24,DZ25,-EA25) -> 0 | EC25: 46280 | EJ25: =SUM(EJ24,EH25,-EI25) -> 0 | EK25: 46280 | ER25: =SUM(ER24,EP25,-EQ25) -> 0 | ES25: 46280 | EZ25: =SUM(EZ24,EX25,-EY25) -> 0 | FA25: 46280 | FH25: =SUM(FH24,FF25,-FG25) -> 0 | FI25: 46280 | FP25: =SUM(FP24,FN25,-FO25) -> 0 | FQ25: 46280 | FX25: =SUM(FX24,FV25,-FW25) -> 0 | FY25: 46280 | GF25: =SUM(GF24,GD25,-GE25) -> 0 | GG25: 46280 | GN25: =SUM(GN24,GL25,-GM25) -> 0 | GO25: 46295 | GV25: =SUM(GV24,GT25,-GU25) -> 0 | GW25: 46295 | HD25: =SUM(HD24,HB25,-HC25) -> 0 | HE25: 46295 | HL25: =SUM(HL24,HJ25,-HK25) -> 0 | HM25: 46295 | HT25: =SUM(HT24,HR25,-HS25) -> 0 | HU25: 46295 | IB25: =SUM(IB24,HZ25,-IA25) -> 0 | IC25: 46291 | IJ25: =SUM(IJ24,IH25,-II25) -> 0 | IK25: 46295 | IR25: =SUM(IR24,IP25,-IQ25) -> 0 | IS25: 46295 | IZ25: =SUM(IZ24,IX25,-IY25) -> 0 | JA25: 46295 | JH25: =SUM(JH24,JF25,-JG25) -> 0 | JI25: 46295 | JP25: =SUM(JP24,JN25,-JO25) -> 0 | JQ25: 46295 | JX25: =SUM(JX24,JV25,-JW25) -> 0 | JY25: 46295 | KF25: =SUM(KF24,KD25,-KE25) -> 0 | KG25: 46295 | KN25: =SUM(KN24,KL25,-KM25) -> 0 | KO25: 46295 | KV25: =SUM(KV24,KT25,-KU25) -> 0 | KW25: 46295 | LD25: =SUM(LD24,LB25,-LC25) -> 0 | LE25: 46295 | LL25: =SUM(LL24,LJ25,-LK25) -> 0 | LM25: 46295 | LT25: =SUM(LT24,LR25,-LS25) -> 0 | LU25: 46295 | MB25: =SUM(MB24,LZ25,-MA25) -> 0 | MC25: 46295 | MJ25: =SUM(MJ24,MH25,-MI25) -> 0 | MK25: 46295 | MR25: =SUM(MR24,MP25,-MQ25) -> 0 | MS25: 46295 | MZ25: =SUM(MZ24,MX25,-MY25) -> 0 | NA25: 46295 | NH25: =SUM(NH24,NF25,-NG25) -> 0 | NI25: 46295 | NP25: =SUM(NP24,NN25,-NO25) -> 0 | NQ25: 46295 | NX25: =SUM(NX24,NV25,-NW25) -> 0 | NY25: 46295 | OF25: =SUM(OF24,OD25,-OE25) -> 0 | OG25: 46295 | ON25: =SUM(ON24,OL25,-OM25) -> 0 | OO25: 46295 | OV25: =SUM(OV24,OT25,-OU25) -> 0 | OW25: 46295 | PD25: =SUM(PD24,PB25,-PC25) -> 0 | PE25: 46295 | PL25: =SUM(PL24,PJ25,-PK25) -> 0 | PM25: 46295 | PT25: =SUM(PT24,PR25,-PS25) -> 0 | PU25: 46295 | QB25: =SUM(QB24,PZ25,-QA25) -> 0 | QC25: 46295 | QJ25: =SUM(QJ24,QH25,-QI25) -> 0 | QK25: 46295 | QR25: =SUM(QR24,QP25,-QQ25) -> 0 | QS25: 46295 | QZ25: =SUM(QZ24,QX25,-QY25) -> 0 | RA25: 46295 | RH25: =SUM(RH24,RF25,-RG25) -> 0 | RI25: 46295 | RP25: =SUM(RP24,RN25,-RO25) -> 0 | RQ25: 46295 | RX25: =SUM(RX24,RV25,-RW25) -> 0 | RY25: 46295 | SF25: =SUM(SF24,SD25,-SE25) -> 0 | SG25: 46295 | SN25: =SUM(SN24,SL25,-SM25) -> 0 | SO25: 46295 | SV25: =SUM(SV24,ST25,-SU25) -> 0 | SW25: 46295 | TD25: =SUM(TD24,TB25,-TC25) -> 0 | TE25: 46295 | TL25: =SUM(TL24,TJ25,-TK25) -> 0 | TM25: 46295 | TT25: =SUM(TT24,TR25,-TS25) -> 0 | TU25: 46295 | UB25: =SUM(UB24,TZ25,-UA25) -> 0 | UC25: 46295 | UJ25: =SUM(UJ24,UH25,-UI25) -> 0 | UK25: 46295 | UR25: =SUM(UR24,UP25,-UQ25) -> 0 | US25: 46295 | UZ25: =SUM(UZ24,UX25,-UY25) -> 0 | VA25: 46295 | VH25: =SUM(VH24,VF25,-VG25) -> 0 | VI25: 46295 | VP25: =SUM(VP24,VN25,-VO25) -> 0 | VQ25: 46295 | VX25: =SUM(VX24,VV25,-VW25) -> 0 | VY25: 46295 | WF25: =SUM(WF24,WD25,-WE25) -> 0 | WG25: 46295 | WN25: =SUM(WN24,WL25,-WM25) -> 0 | WO25: 46295 | WV25: =SUM(WV24,WT25,-WU25) -> 0 | WW25: 46295 | XD25: =SUM(XD24,XB25,-XC25) -> 0 | XE25: 46295 | XL25: =SUM(XL24,XJ25,-XK25) -> 0 | XM25: 46295 | XT25: =SUM(XT24,XR25,-XS25) -> 0 | XU25: 46295 | YB25: =SUM(YB24,XZ25,-YA25) -> 0 | YC25: 46295 | YJ25: =SUM(YJ24,YH25,-YI25) -> 0 | YK25: 46295 | YR25: =SUM(YR24,YP25,-YQ25) -> 0 | YS25: 46295 | YZ25: =SUM(YZ24,YX25,-YY25) -> 0 | ZA25: 46295 | ZH25: =SUM(ZH24,ZF25,-ZG25) -> 0 | ZI25: 46295 | ZP25: =SUM(ZP24,ZN25,-ZO25) -> 0 | ZQ25: 46295 | ZX25: =SUM(ZX24,ZV25,-ZW25) -> 0 | ZY25: 46295 | AAF25: =SUM(AAF24,AAD25,-AAE25) -> 0 | AAG25: 46295 | AAN25: =SUM(AAN24,AAL25,-AAM25) -> 0 | AAO25: 46295 | AAV25: =SUM(AAV24,AAT25,-AAU25) -> 0 | AAW25: 46295 | ABD25: =SUM(ABD24,ABB25,-ABC25) -> 0 | ABE25: 46295 | ABL25: =SUM(ABL24,ABJ25,-ABK25) -> 0 | ABM25: 46295 | ABT25: =SUM(ABT24,ABR25,-ABS25) -> 0 | ABU25: 46295 | ACB25: =SUM(ACB24,ABZ25,-ACA25) -> 0 | ACC25: 46295
D26: =SUM(D25,B26,-C26) -> 1700 | E26: 46295 | L26: =SUM(L25,J26,-K26) -> 1000 | M26: 46295 | T26: =SUM(T25,R26,-S26) -> 4000 | U26: 46295 | AB26: =SUM(AB25,Z26,-AA26) -> 1000 | AC26: 46295 | AJ26: =SUM(AJ25,AH26,-AI26) -> 2000 | AK26: 46295 | AR26: =SUM(AR25,AP26,-AQ26) -> 1000 | AS26: 46295 | AZ26: =SUM(AZ25,AX26,-AY26) -> 1150 | BA26: 46295 | BH26: =SUM(BH25,BF26,-BG26) -> 7000 | BI26: 46295 | BP26: =SUM(BP25,BN26,-BO26) -> 1000 | BQ26: 46295 | BX26: =SUM(BX25,BV26,-BW26) -> 0 | BY26: 46295 | CF26: =SUM(CF25,CD26,-CE26) -> 0 | CG26: 46310 | CN26: =SUM(CN25,CL26,-CM26) -> 0 | CO26: 46310 | CV26: =SUM(CV25,CT26,-CU26) -> 0 | CW26: 46310 | DD26: =SUM(DD25,DB26,-DC26) -> 0 | DE26: 46310 | DL26: =SUM(DL25,DJ26,-DK26) -> 0 | DM26: 46295 | DT26: =SUM(DT25,DR26,-DS26) -> 0 | DU26: 46295 | EB26: =SUM(EB25,DZ26,-EA26) -> 0 | EC26: 46295 | EJ26: =SUM(EJ25,EH26,-EI26) -> 0 | EK26: 46295 | ER26: =SUM(ER25,EP26,-EQ26) -> 0 | ES26: 46295 | EZ26: =SUM(EZ25,EX26,-EY26) -> 0 | FA26: 46295 | FH26: =SUM(FH25,FF26,-FG26) -> 0 | FI26: 46295 | FP26: =SUM(FP25,FN26,-FO26) -> 0 | FQ26: 46295 | FX26: =SUM(FX25,FV26,-FW26) -> 0 | FY26: 46295 | GF26: =SUM(GF25,GD26,-GE26) -> 0 | GG26: 46295 | GN26: =SUM(GN25,GL26,-GM26) -> 0 | GO26: 46310 | GV26: =SUM(GV25,GT26,-GU26) -> 0 | GW26: 46310 | HD26: =SUM(HD25,HB26,-HC26) -> 0 | HE26: 46310 | HL26: =SUM(HL25,HJ26,-HK26) -> 0 | HM26: 46310 | HT26: =SUM(HT25,HR26,-HS26) -> 0 | HU26: 46310 | IB26: =SUM(IB25,HZ26,-IA26) -> 0 | IC26: 46310 | IJ26: =SUM(IJ25,IH26,-II26) -> 0 | IK26: 46310 | IL26: 0 | IM26: 0 | IR26: =SUM(IR25,IP26,-IQ26) -> 0 | IS26: 46310 | IZ26: =SUM(IZ25,IX26,-IY26) -> 0 | JA26: 46310 | JH26: =SUM(JH25,JF26,-JG26) -> 0 | JI26: 46310 | JP26: =SUM(JP25,JN26,-JO26) -> 0 | JQ26: 46310 | JX26: =SUM(JX25,JV26,-JW26) -> 0 | JY26: 46310 | KF26: =SUM(KF25,KD26,-KE26) -> 0 | KG26: 46310 | KN26: =SUM(KN25,KL26,-KM26) -> 0 | KO26: 46310 | KV26: =SUM(KV25,KT26,-KU26) -> 0 | KW26: 46310 | LD26: =SUM(LD25,LB26,-LC26) -> 0 | LE26: 46310 | LL26: =SUM(LL25,LJ26,-LK26) -> 0 | LM26: 46310 | LT26: =SUM(LT25,LR26,-LS26) -> 0 | LU26: 46310 | MB26: =SUM(MB25,LZ26,-MA26) -> 0 | MC26: 46310 | MJ26: =SUM(MJ25,MH26,-MI26) -> 0 | MK26: 46310 | MR26: =SUM(MR25,MP26,-MQ26) -> 0 | MS26: 46310 | MZ26: =SUM(MZ25,MX26,-MY26) -> 0 | NA26: 46310 | NH26: =SUM(NH25,NF26,-NG26) -> 0 | NI26: 46310 | NP26: =SUM(NP25,NN26,-NO26) -> 0 | NQ26: 46310 | NX26: =SUM(NX25,NV26,-NW26) -> 0 | NY26: 46310 | OF26: =SUM(OF25,OD26,-OE26) -> 0 | OG26: 46310 | ON26: =SUM(ON25,OL26,-OM26) -> 0 | OO26: 46310 | OV26: =SUM(OV25,OT26,-OU26) -> 0 | OW26: 46310 | PD26: =SUM(PD25,PB26,-PC26) -> 0 | PE26: 46310 | PL26: =SUM(PL25,PJ26,-PK26) -> 0 | PM26: 46310 | PT26: =SUM(PT25,PR26,-PS26) -> 0 | PU26: 46310 | QB26: =SUM(QB25,PZ26,-QA26) -> 0 | QC26: 46310 | QJ26: =SUM(QJ25,QH26,-QI26) -> 0 | QK26: 46310 | QR26: =SUM(QR25,QP26,-QQ26) -> 0 | QS26: 46310 | QZ26: =SUM(QZ25,QX26,-QY26) -> 0 | RA26: 46310 | RH26: =SUM(RH25,RF26,-RG26) -> 0 | RI26: 46310 | RP26: =SUM(RP25,RN26,-RO26) -> 0 | RQ26: 46310 | RX26: =SUM(RX25,RV26,-RW26) -> 0 | RY26: 46310 | SF26: =SUM(SF25,SD26,-SE26) -> 0 | SG26: 46310 | SN26: =SUM(SN25,SL26,-SM26) -> 0 | SO26: 46310 | SV26: =SUM(SV25,ST26,-SU26) -> 0 | SW26: 46310 | TD26: =SUM(TD25,TB26,-TC26) -> 0 | TE26: 46310 | TL26: =SUM(TL25,TJ26,-TK26) -> 0 | TM26: 46310 | TT26: =SUM(TT25,TR26,-TS26) -> 0 | TU26: 46310 | UB26: =SUM(UB25,TZ26,-UA26) -> 0 | UC26: 46310 | UJ26: =SUM(UJ25,UH26,-UI26) -> 0 | UK26: 46310 | UR26: =SUM(UR25,UP26,-UQ26) -> 0 | US26: 46310 | UZ26: =SUM(UZ25,UX26,-UY26) -> 0 | VA26: 46310 | VH26: =SUM(VH25,VF26,-VG26) -> 0 | VI26: 46310 | VP26: =SUM(VP25,VN26,-VO26) -> 0 | VQ26: 46310 | VX26: =SUM(VX25,VV26,-VW26) -> 0 | VY26: 46310 | WF26: =SUM(WF25,WD26,-WE26) -> 0 | WG26: 46310 | WN26: =SUM(WN25,WL26,-WM26) -> 0 | WO26: 46310 | WV26: =SUM(WV25,WT26,-WU26) -> 0 | WW26: 46310 | XD26: =SUM(XD25,XB26,-XC26) -> 0 | XE26: 46310 | XL26: =SUM(XL25,XJ26,-XK26) -> 0 | XM26: 46310 | XT26: =SUM(XT25,XR26,-XS26) -> 0 | XU26: 46310 | YB26: =SUM(YB25,XZ26,-YA26) -> 0 | YC26: 46310 | YJ26: =SUM(YJ25,YH26,-YI26) -> 0 | YK26: 46310 | YR26: =SUM(YR25,YP26,-YQ26) -> 0 | YS26: 46310 | YZ26: =SUM(YZ25,YX26,-YY26) -> 0 | ZA26: 46310 | ZH26: =SUM(ZH25,ZF26,-ZG26) -> 0 | ZI26: 46310 | ZP26: =SUM(ZP25,ZN26,-ZO26) -> 0 | ZQ26: 46310 | ZX26: =SUM(ZX25,ZV26,-ZW26) -> 0 | ZY26: 46310 | AAF26: =SUM(AAF25,AAD26,-AAE26) -> 0 | AAG26: 46310 | AAN26: =SUM(AAN25,AAL26,-AAM26) -> 0 | AAO26: 46310 | AAV26: =SUM(AAV25,AAT26,-AAU26) -> 0 | AAW26: 46310 | ABD26: =SUM(ABD25,ABB26,-ABC26) -> 0 | ABE26: 46310 | ABL26: =SUM(ABL25,ABJ26,-ABK26) -> 0 | ABM26: 46310 | ABT26: =SUM(ABT25,ABR26,-ABS26) -> 0 | ABU26: 46310 | ACB26: =SUM(ACB25,ABZ26,-ACA26) -> 0 | ACC26: 46310
D27: =SUM(D26,B27,-C27) -> 1700 | E27: 46310 | L27: =SUM(L26,J27,-K27) -> 1000 | M27: 46310 | T27: =SUM(T26,R27,-S27) -> 4000 | U27: 46310 | AB27: =SUM(AB26,Z27,-AA27) -> 1000 | AC27: 46310 | AJ27: =SUM(AJ26,AH27,-AI27) -> 2000 | AK27: 46310 | AR27: =SUM(AR26,AP27,-AQ27) -> 1000 | AS27: 46310 | AZ27: =SUM(AZ26,AX27,-AY27) -> 1150 | BA27: 46310 | BH27: =SUM(BH26,BF27,-BG27) -> 7000 | BI27: 46310 | BP27: =SUM(BP26,BN27,-BO27) -> 1000 | BQ27: 46310 | BX27: =SUM(BX26,BV27,-BW27) -> 0 | BY27: 46310 | CF27: =SUM(CF26,CD27,-CE27) -> 0 | CG27: 46325 | CN27: =SUM(CN26,CL27,-CM27) -> 0 | CO27: 46325 | CV27: =SUM(CV26,CT27,-CU27) -> 0 | CW27: 46325 | DD27: =SUM(DD26,DB27,-DC27) -> 0 | DE27: 46325 | DL27: =SUM(DL26,DJ27,-DK27) -> 0 | DM27: 46310 | DT27: =SUM(DT26,DR27,-DS27) -> 0 | DU27: 46310 | EB27: =SUM(EB26,DZ27,-EA27) -> 0 | EC27: 46310 | EJ27: =SUM(EJ26,EH27,-EI27) -> 0 | EK27: 46310 | ER27: =SUM(ER26,EP27,-EQ27) -> 0 | ES27: 46310 | EZ27: =SUM(EZ26,EX27,-EY27) -> 0 | FA27: 46310 | FH27: =SUM(FH26,FF27,-FG27) -> 0 | FI27: 46310 | FP27: =SUM(FP26,FN27,-FO27) -> 0 | FQ27: 46310 | FX27: =SUM(FX26,FV27,-FW27) -> 0 | FY27: 46310 | GF27: =SUM(GF26,GD27,-GE27) -> 0 | GG27: 46310 | GN27: =SUM(GN26,GL27,-GM27) -> 0 | GO27: 46325 | GV27: =SUM(GV26,GT27,-GU27) -> 0 | GW27: 46325 | HD27: =SUM(HD26,HB27,-HC27) -> 0 | HE27: 46325 | HL27: =SUM(HL26,HJ27,-HK27) -> 0 | HM27: 46325 | HT27: =SUM(HT26,HR27,-HS27) -> 0 | HU27: 46325 | IB27: =SUM(IB26,HZ27,-IA27) -> 0 | IC27: 46325 | IJ27: =SUM(IJ26,IH27,-II27) -> 0 | IK27: 46325 | IR27: =SUM(IR26,IP27,-IQ27) -> 0 | IS27: 46325 | IZ27: =SUM(IZ26,IX27,-IY27) -> 0 | JA27: 46325 | JH27: =SUM(JH26,JF27,-JG27) -> 0 | JI27: 46325 | JP27: =SUM(JP26,JN27,-JO27) -> 0 | JQ27: 46325 | JX27: =SUM(JX26,JV27,-JW27) -> 0 | JY27: 46325 | KF27: =SUM(KF26,KD27,-KE27) -> 0 | KG27: 46325 | KN27: =SUM(KN26,KL27,-KM27) -> 0 | KO27: 46325 | KV27: =SUM(KV26,KT27,-KU27) -> 0 | KW27: 46325 | LD27: =SUM(LD26,LB27,-LC27) -> 0 | LE27: 46325 | LL27: =SUM(LL26,LJ27,-LK27) -> 0 | LM27: 46325 | LT27: =SUM(LT26,LR27,-LS27) -> 0 | LU27: 46325 | MB27: =SUM(MB26,LZ27,-MA27) -> 0 | MC27: 46325 | MJ27: =SUM(MJ26,MH27,-MI27) -> 0 | MK27: 46325 | MR27: =SUM(MR26,MP27,-MQ27) -> 0 | MS27: 46325 | MZ27: =SUM(MZ26,MX27,-MY27) -> 0 | NA27: 46325 | NH27: =SUM(NH26,NF27,-NG27) -> 0 | NI27: 46325 | NP27: =SUM(NP26,NN27,-NO27) -> 0 | NQ27: 46325 | NX27: =SUM(NX26,NV27,-NW27) -> 0 | NY27: 46325 | OF27: =SUM(OF26,OD27,-OE27) -> 0 | OG27: 46325 | ON27: =SUM(ON26,OL27,-OM27) -> 0 | OO27: 46325 | OV27: =SUM(OV26,OT27,-OU27) -> 0 | OW27: 46325 | PD27: =SUM(PD26,PB27,-PC27) -> 0 | PE27: 46325 | PL27: =SUM(PL26,PJ27,-PK27) -> 0 | PM27: 46325 | PT27: =SUM(PT26,PR27,-PS27) -> 0 | PU27: 46325 | QB27: =SUM(QB26,PZ27,-QA27) -> 0 | QC27: 46325 | QJ27: =SUM(QJ26,QH27,-QI27) -> 0 | QK27: 46325 | QR27: =SUM(QR26,QP27,-QQ27) -> 0 | QS27: 46325 | QZ27: =SUM(QZ26,QX27,-QY27) -> 0 | RA27: 46325 | RH27: =SUM(RH26,RF27,-RG27) -> 0 | RI27: 46325 | RP27: =SUM(RP26,RN27,-RO27) -> 0 | RQ27: 46325 | RX27: =SUM(RX26,RV27,-RW27) -> 0 | RY27: 46325 | SF27: =SUM(SF26,SD27,-SE27) -> 0 | SG27: 46325 | SN27: =SUM(SN26,SL27,-SM27) -> 0 | SO27: 46325 | SV27: =SUM(SV26,ST27,-SU27) -> 0 | SW27: 46325 | TD27: =SUM(TD26,TB27,-TC27) -> 0 | TE27: 46325 | TL27: =SUM(TL26,TJ27,-TK27) -> 0 | TM27: 46325 | TT27: =SUM(TT26,TR27,-TS27) -> 0 | TU27: 46325 | UB27: =SUM(UB26,TZ27,-UA27) -> 0 | UC27: 46325 | UJ27: =SUM(UJ26,UH27,-UI27) -> 0 | UK27: 46325 | UR27: =SUM(UR26,UP27,-UQ27) -> 0 | US27: 46325 | UZ27: =SUM(UZ26,UX27,-UY27) -> 0 | VA27: 46325 | VH27: =SUM(VH26,VF27,-VG27) -> 0 | VI27: 46325 | VP27: =SUM(VP26,VN27,-VO27) -> 0 | VQ27: 46325 | VX27: =SUM(VX26,VV27,-VW27) -> 0 | VY27: 46325 | WF27: =SUM(WF26,WD27,-WE27) -> 0 | WG27: 46325 | WN27: =SUM(WN26,WL27,-WM27) -> 0 | WO27: 46325 | WV27: =SUM(WV26,WT27,-WU27) -> 0 | WW27: 46325 | XD27: =SUM(XD26,XB27,-XC27) -> 0 | XE27: 46325 | XL27: =SUM(XL26,XJ27,-XK27) -> 0 | XM27: 46325 | XT27: =SUM(XT26,XR27,-XS27) -> 0 | XU27: 46325 | YB27: =SUM(YB26,XZ27,-YA27) -> 0 | YC27: 46325 | YJ27: =SUM(YJ26,YH27,-YI27) -> 0 | YK27: 46325 | YR27: =SUM(YR26,YP27,-YQ27) -> 0 | YS27: 46325 | YZ27: =SUM(YZ26,YX27,-YY27) -> 0 | ZA27: 46325 | ZH27: =SUM(ZH26,ZF27,-ZG27) -> 0 | ZI27: 46325 | ZP27: =SUM(ZP26,ZN27,-ZO27) -> 0 | ZQ27: 46325 | ZX27: =SUM(ZX26,ZV27,-ZW27) -> 0 | ZY27: 46325 | AAF27: =SUM(AAF26,AAD27,-AAE27) -> 0 | AAG27: 46325 | AAN27: =SUM(AAN26,AAL27,-AAM27) -> 0 | AAO27: 46325 | AAV27: =SUM(AAV26,AAT27,-AAU27) -> 0 | AAW27: 46325 | ABD27: =SUM(ABD26,ABB27,-ABC27) -> 0 | ABE27: 46325 | ABL27: =SUM(ABL26,ABJ27,-ABK27) -> 0 | ABM27: 46325 | ABT27: =SUM(ABT26,ABR27,-ABS27) -> 0 | ABU27: 46325 | ACB27: =SUM(ACB26,ABZ27,-ACA27) -> 0 | ACC27: 46325
D28: =SUM(D27,B28,-C28) -> 1700 | E28: 46325 | L28: =SUM(L27,J28,-K28) -> 1000 | M28: 46325 | T28: =SUM(T27,R28,-S28) -> 4000 | U28: 46325 | AB28: =SUM(AB27,Z28,-AA28) -> 1000 | AC28: 46325 | AJ28: =SUM(AJ27,AH28,-AI28) -> 2000 | AK28: 46325 | AR28: =SUM(AR27,AP28,-AQ28) -> 1000 | AS28: 46325 | AZ28: =SUM(AZ27,AX28,-AY28) -> 1150 | BA28: 46325 | BH28: =SUM(BH27,BF28,-BG28) -> 7000 | BI28: 46325 | BP28: =SUM(BP27,BN28,-BO28) -> 1000 | BQ28: 46325 | BX28: =SUM(BX27,BV28,-BW28) -> 0 | BY28: 46325 | CF28: =SUM(CF27,CD28,-CE28) -> 0 | CG28: 46341 | CN28: =SUM(CN27,CL28,-CM28) -> 0 | CO28: 46341 | CV28: =SUM(CV27,CT28,-CU28) -> 0 | CW28: 46341 | DD28: =SUM(DD27,DB28,-DC28) -> 0 | DE28: 46341 | DL28: =SUM(DL27,DJ28,-DK28) -> 0 | DM28: 46325 | DT28: =SUM(DT27,DR28,-DS28) -> 0 | DU28: 46325 | EB28: =SUM(EB27,DZ28,-EA28) -> 0 | EC28: 46325 | EJ28: =SUM(EJ27,EH28,-EI28) -> 0 | EK28: 46325 | ER28: =SUM(ER27,EP28,-EQ28) -> 0 | ES28: 46325 | EZ28: =SUM(EZ27,EX28,-EY28) -> 0 | FA28: 46325 | FH28: =SUM(FH27,FF28,-FG28) -> 0 | FI28: 46325 | FP28: =SUM(FP27,FN28,-FO28) -> 0 | FQ28: 46325 | FX28: =SUM(FX27,FV28,-FW28) -> 0 | FY28: 46325 | GF28: =SUM(GF27,GD28,-GE28) -> 0 | GG28: 46325 | GN28: =SUM(GN27,GL28,-GM28) -> 0 | GO28: 46341 | GV28: =SUM(GV27,GT28,-GU28) -> 0 | GW28: 46341 | HD28: =SUM(HD27,HB28,-HC28) -> 0 | HE28: 46341 | HL28: =SUM(HL27,HJ28,-HK28) -> 0 | HM28: 46341 | HT28: =SUM(HT27,HR28,-HS28) -> 0 | HU28: 46341 | IB28: =SUM(IB27,HZ28,-IA28) -> 0 | IC28: 46341 | IJ28: =SUM(IJ27,IH28,-II28) -> 0 | IK28: 46341 | IR28: =SUM(IR27,IP28,-IQ28) -> 0 | IS28: 46341 | IZ28: =SUM(IZ27,IX28,-IY28) -> 0 | JA28: 46341 | JH28: =SUM(JH27,JF28,-JG28) -> 0 | JI28: 46341 | JP28: =SUM(JP27,JN28,-JO28) -> 0 | JQ28: 46341 | JX28: =SUM(JX27,JV28,-JW28) -> 0 | JY28: 46341 | KF28: =SUM(KF27,KD28,-KE28) -> 0 | KG28: 46341 | KN28: =SUM(KN27,KL28,-KM28) -> 0 | KO28: 46341 | KV28: =SUM(KV27,KT28,-KU28) -> 0 | KW28: 46341 | LD28: =SUM(LD27,LB28,-LC28) -> 0 | LE28: 46341 | LL28: =SUM(LL27,LJ28,-LK28) -> 0 | LM28: 46341 | LT28: =SUM(LT27,LR28,-LS28) -> 0 | LU28: 46341 | MB28: =SUM(MB27,LZ28,-MA28) -> 0 | MC28: 46341 | MJ28: =SUM(MJ27,MH28,-MI28) -> 0 | MK28: 46341 | MR28: =SUM(MR27,MP28,-MQ28) -> 0 | MS28: 46341 | MZ28: =SUM(MZ27,MX28,-MY28) -> 0 | NA28: 46341 | NH28: =SUM(NH27,NF28,-NG28) -> 0 | NI28: 46341 | NP28: =SUM(NP27,NN28,-NO28) -> 0 | NQ28: 46341 | NX28: =SUM(NX27,NV28,-NW28) -> 0 | NY28: 46341 | OF28: =SUM(OF27,OD28,-OE28) -> 0 | OG28: 46341 | ON28: =SUM(ON27,OL28,-OM28) -> 0 | OO28: 46341 | OV28: =SUM(OV27,OT28,-OU28) -> 0 | OW28: 46341 | PD28: =SUM(PD27,PB28,-PC28) -> 0 | PE28: 46341 | PL28: =SUM(PL27,PJ28,-PK28) -> 0 | PM28: 46341 | PT28: =SUM(PT27,PR28,-PS28) -> 0 | PU28: 46341 | QB28: =SUM(QB27,PZ28,-QA28) -> 0 | QC28: 46341 | QJ28: =SUM(QJ27,QH28,-QI28) -> 0 | QK28: 46341 | QR28: =SUM(QR27,QP28,-QQ28) -> 0 | QS28: 46341 | QZ28: =SUM(QZ27,QX28,-QY28) -> 0 | RA28: 46341 | RH28: =SUM(RH27,RF28,-RG28) -> 0 | RI28: 46341 | RP28: =SUM(RP27,RN28,-RO28) -> 0 | RQ28: 46341 | RX28: =SUM(RX27,RV28,-RW28) -> 0 | RY28: 46341 | SF28: =SUM(SF27,SD28,-SE28) -> 0 | SG28: 46341 | SN28: =SUM(SN27,SL28,-SM28) -> 0 | SO28: 46341 | SV28: =SUM(SV27,ST28,-SU28) -> 0 | SW28: 46341 | TD28: =SUM(TD27,TB28,-TC28) -> 0 | TE28: 46341 | TL28: =SUM(TL27,TJ28,-TK28) -> 0 | TM28: 46341 | TT28: =SUM(TT27,TR28,-TS28) -> 0 | TU28: 46341 | UB28: =SUM(UB27,TZ28,-UA28) -> 0 | UC28: 46341 | UJ28: =SUM(UJ27,UH28,-UI28) -> 0 | UK28: 46341 | UR28: =SUM(UR27,UP28,-UQ28) -> 0 | US28: 46341 | UZ28: =SUM(UZ27,UX28,-UY28) -> 0 | VA28: 46341 | VH28: =SUM(VH27,VF28,-VG28) -> 0 | VI28: 46341 | VP28: =SUM(VP27,VN28,-VO28) -> 0 | VQ28: 46341 | VX28: =SUM(VX27,VV28,-VW28) -> 0 | VY28: 46341 | WF28: =SUM(WF27,WD28,-WE28) -> 0 | WG28: 46341 | WN28: =SUM(WN27,WL28,-WM28) -> 0 | WO28: 46341 | WV28: =SUM(WV27,WT28,-WU28) -> 0 | WW28: 46341 | XD28: =SUM(XD27,XB28,-XC28) -> 0 | XE28: 46341 | XL28: =SUM(XL27,XJ28,-XK28) -> 0 | XM28: 46341 | XT28: =SUM(XT27,XR28,-XS28) -> 0 | XU28: 46341 | YB28: =SUM(YB27,XZ28,-YA28) -> 0 | YC28: 46341 | YJ28: =SUM(YJ27,YH28,-YI28) -> 0 | YK28: 46341 | YR28: =SUM(YR27,YP28,-YQ28) -> 0 | YS28: 46341 | YZ28: =SUM(YZ27,YX28,-YY28) -> 0 | ZA28: 46341 | ZH28: =SUM(ZH27,ZF28,-ZG28) -> 0 | ZI28: 46341 | ZP28: =SUM(ZP27,ZN28,-ZO28) -> 0 | ZQ28: 46341 | ZX28: =SUM(ZX27,ZV28,-ZW28) -> 0 | ZY28: 46341 | AAF28: =SUM(AAF27,AAD28,-AAE28) -> 0 | AAG28: 46341 | AAN28: =SUM(AAN27,AAL28,-AAM28) -> 0 | AAO28: 46341 | AAV28: =SUM(AAV27,AAT28,-AAU28) -> 0 | AAW28: 46341 | ABD28: =SUM(ABD27,ABB28,-ABC28) -> 0 | ABE28: 46341 | ABL28: =SUM(ABL27,ABJ28,-ABK28) -> 0 | ABM28: 46341 | ABT28: =SUM(ABT27,ABR28,-ABS28) -> 0 | ABU28: 46341 | ACB28: =SUM(ACB27,ABZ28,-ACA28) -> 0 | ACC28: 46341
D29: =SUM(D28,B29,-C29) -> 1700 | E29: 46341 | L29: =SUM(L28,J29,-K29) -> 1000 | M29: 46341 | T29: =SUM(T28,R29,-S29) -> 4000 | U29: 46341 | AB29: =SUM(AB28,Z29,-AA29) -> 1000 | AC29: 46341 | AJ29: =SUM(AJ28,AH29,-AI29) -> 2000 | AK29: 46341 | AR29: =SUM(AR28,AP29,-AQ29) -> 1000 | AS29: 46341 | AZ29: =SUM(AZ28,AX29,-AY29) -> 1150 | BA29: 46341 | BH29: =SUM(BH28,BF29,-BG29) -> 7000 | BI29: 46341 | BP29: =SUM(BP28,BN29,-BO29) -> 1000 | BQ29: 46341 | BX29: =SUM(BX28,BV29,-BW29) -> 0 | BY29: 46341 | CF29: =SUM(CF28,CD29,-CE29) -> 0 | CG29: 46356 | CN29: =SUM(CN28,CL29,-CM29) -> 0 | CO29: 46356 | CV29: =SUM(CV28,CT29,-CU29) -> 0 | CW29: 46356 | DD29: =SUM(DD28,DB29,-DC29) -> 0 | DE29: 46356 | DL29: =SUM(DL28,DJ29,-DK29) -> 0 | DM29: 46341 | DT29: =SUM(DT28,DR29,-DS29) -> 0 | DU29: 46341 | EB29: =SUM(EB28,DZ29,-EA29) -> 0 | EC29: 46341 | EJ29: =SUM(EJ28,EH29,-EI29) -> 0 | EK29: 46341 | ER29: =SUM(ER28,EP29,-EQ29) -> 0 | ES29: 46341 | EZ29: =SUM(EZ28,EX29,-EY29) -> 0 | FA29: 46341 | FH29: =SUM(FH28,FF29,-FG29) -> 0 | FI29: 46341 | FP29: =SUM(FP28,FN29,-FO29) -> 0 | FQ29: 46341 | FX29: =SUM(FX28,FV29,-FW29) -> 0 | FY29: 46341 | GF29: =SUM(GF28,GD29,-GE29) -> 0 | GG29: 46341 | GN29: =SUM(GN28,GL29,-GM29) -> 0 | GO29: 46356 | GV29: =SUM(GV28,GT29,-GU29) -> 0 | GW29: 46356 | HD29: =SUM(HD28,HB29,-HC29) -> 0 | HE29: 46356 | HL29: =SUM(HL28,HJ29,-HK29) -> 0 | HM29: 46356 | HT29: =SUM(HT28,HR29,-HS29) -> 0 | HU29: 46356 | IB29: =SUM(IB28,HZ29,-IA29) -> 0 | IC29: 46356 | IJ29: =SUM(IJ28,IH29,-II29) -> 0 | IK29: 46356 | IR29: =SUM(IR28,IP29,-IQ29) -> 0 | IS29: 46356 | IZ29: =SUM(IZ28,IX29,-IY29) -> 0 | JA29: 46356 | JH29: =SUM(JH28,JF29,-JG29) -> 0 | JI29: 46356 | JP29: =SUM(JP28,JN29,-JO29) -> 0 | JQ29: 46356 | JX29: =SUM(JX28,JV29,-JW29) -> 0 | JY29: 46356 | KF29: =SUM(KF28,KD29,-KE29) -> 0 | KG29: 46356 | KN29: =SUM(KN28,KL29,-KM29) -> 0 | KO29: 46356 | KV29: =SUM(KV28,KT29,-KU29) -> 0 | KW29: 46356 | LD29: =SUM(LD28,LB29,-LC29) -> 0 | LE29: 46356 | LL29: =SUM(LL28,LJ29,-LK29) -> 0 | LM29: 46356 | LT29: =SUM(LT28,LR29,-LS29) -> 0 | LU29: 46356 | MB29: =SUM(MB28,LZ29,-MA29) -> 0 | MC29: 46356 | MJ29: =SUM(MJ28,MH29,-MI29) -> 0 | MK29: 46356 | MR29: =SUM(MR28,MP29,-MQ29) -> 0 | MS29: 46356 | MZ29: =SUM(MZ28,MX29,-MY29) -> 0 | NA29: 46356 | NH29: =SUM(NH28,NF29,-NG29) -> 0 | NI29: 46356 | NP29: =SUM(NP28,NN29,-NO29) -> 0 | NQ29: 46356 | NX29: =SUM(NX28,NV29,-NW29) -> 0 | NY29: 46356 | OF29: =SUM(OF28,OD29,-OE29) -> 0 | OG29: 46356 | ON29: =SUM(ON28,OL29,-OM29) -> 0 | OO29: 46356 | OV29: =SUM(OV28,OT29,-OU29) -> 0 | OW29: 46356 | PD29: =SUM(PD28,PB29,-PC29) -> 0 | PE29: 46356 | PL29: =SUM(PL28,PJ29,-PK29) -> 0 | PM29: 46356 | PT29: =SUM(PT28,PR29,-PS29) -> 0 | PU29: 46356 | QB29: =SUM(QB28,PZ29,-QA29) -> 0 | QC29: 46356 | QJ29: =SUM(QJ28,QH29,-QI29) -> 0 | QK29: 46356 | QR29: =SUM(QR28,QP29,-QQ29) -> 0 | QS29: 46356 | QZ29: =SUM(QZ28,QX29,-QY29) -> 0 | RA29: 46356 | RH29: =SUM(RH28,RF29,-RG29) -> 0 | RI29: 46356 | RP29: =SUM(RP28,RN29,-RO29) -> 0 | RQ29: 46356 | RX29: =SUM(RX28,RV29,-RW29) -> 0 | RY29: 46356 | SF29: =SUM(SF28,SD29,-SE29) -> 0 | SG29: 46356 | SN29: =SUM(SN28,SL29,-SM29) -> 0 | SO29: 46356 | SV29: =SUM(SV28,ST29,-SU29) -> 0 | SW29: 46356 | TD29: =SUM(TD28,TB29,-TC29) -> 0 | TE29: 46356 | TL29: =SUM(TL28,TJ29,-TK29) -> 0 | TM29: 46356 | TT29: =SUM(TT28,TR29,-TS29) -> 0 | TU29: 46356 | UB29: =SUM(UB28,TZ29,-UA29) -> 0 | UC29: 46356 | UJ29: =SUM(UJ28,UH29,-UI29) -> 0 | UK29: 46356 | UR29: =SUM(UR28,UP29,-UQ29) -> 0 | US29: 46356 | UZ29: =SUM(UZ28,UX29,-UY29) -> 0 | VA29: 46356 | VH29: =SUM(VH28,VF29,-VG29) -> 0 | VI29: 46356 | VP29: =SUM(VP28,VN29,-VO29) -> 0 | VQ29: 46356 | VX29: =SUM(VX28,VV29,-VW29) -> 0 | VY29: 46356 | WF29: =SUM(WF28,WD29,-WE29) -> 0 | WG29: 46356 | WN29: =SUM(WN28,WL29,-WM29) -> 0 | WO29: 46356 | WV29: =SUM(WV28,WT29,-WU29) -> 0 | WW29: 46356 | XD29: =SUM(XD28,XB29,-XC29) -> 0 | XE29: 46356 | XL29: =SUM(XL28,XJ29,-XK29) -> 0 | XM29: 46356 | XT29: =SUM(XT28,XR29,-XS29) -> 0 | XU29: 46356 | YB29: =SUM(YB28,XZ29,-YA29) -> 0 | YC29: 46356 | YJ29: =SUM(YJ28,YH29,-YI29) -> 0 | YK29: 46356 | YR29: =SUM(YR28,YP29,-YQ29) -> 0 | YS29: 46356 | YZ29: =SUM(YZ28,YX29,-YY29) -> 0 | ZA29: 46356 | ZH29: =SUM(ZH28,ZF29,-ZG29) -> 0 | ZI29: 46356 | ZP29: =SUM(ZP28,ZN29,-ZO29) -> 0 | ZQ29: 46356 | ZX29: =SUM(ZX28,ZV29,-ZW29) -> 0 | ZY29: 46356 | AAF29: =SUM(AAF28,AAD29,-AAE29) -> 0 | AAG29: 46356 | AAN29: =SUM(AAN28,AAL29,-AAM29) -> 0 | AAO29: 46356 | AAV29: =SUM(AAV28,AAT29,-AAU29) -> 0 | AAW29: 46356 | ABD29: =SUM(ABD28,ABB29,-ABC29) -> 0 | ABE29: 46356 | ABL29: =SUM(ABL28,ABJ29,-ABK29) -> 0 | ABM29: 46356 | ABT29: =SUM(ABT28,ABR29,-ABS29) -> 0 | ABU29: 46356 | ACB29: =SUM(ACB28,ABZ29,-ACA29) -> 0 | ACC29: 46356
D30: =SUM(D29,B30,-C30) -> 1700 | E30: 46356 | L30: =SUM(L29,J30,-K30) -> 1000 | M30: 46356 | T30: =SUM(T29,R30,-S30) -> 4000 | U30: 46356 | AB30: =SUM(AB29,Z30,-AA30) -> 1000 | AC30: 46356 | AJ30: =SUM(AJ29,AH30,-AI30) -> 2000 | AK30: 46356 | AR30: =SUM(AR29,AP30,-AQ30) -> 1000 | AS30: 46356 | AZ30: =SUM(AZ29,AX30,-AY30) -> 1150 | BA30: 46356 | BH30: =SUM(BH29,BF30,-BG30) -> 7000 | BI30: 46356 | BP30: =SUM(BP29,BN30,-BO30) -> 1000 | BQ30: 46356 | BX30: =SUM(BX29,BV30,-BW30) -> 0 | BY30: 46356 | CF30: =SUM(CF29,CD30,-CE30) -> 0 | CG30: 46371 | CN30: =SUM(CN29,CL30,-CM30) -> 0 | CO30: 46371 | CV30: =SUM(CV29,CT30,-CU30) -> 0 | CW30: 46371 | DD30: =SUM(DD29,DB30,-DC30) -> 0 | DE30: 46371 | DL30: =SUM(DL29,DJ30,-DK30) -> 0 | DM30: 46356 | DT30: =SUM(DT29,DR30,-DS30) -> 0 | DU30: 46356 | EB30: =SUM(EB29,DZ30,-EA30) -> 0 | EC30: 46356 | EJ30: =SUM(EJ29,EH30,-EI30) -> 0 | EK30: 46356 | ER30: =SUM(ER29,EP30,-EQ30) -> 0 | ES30: 46356 | EZ30: =SUM(EZ29,EX30,-EY30) -> 0 | FA30: 46356 | FH30: =SUM(FH29,FF30,-FG30) -> 0 | FI30: 46356 | FP30: =SUM(FP29,FN30,-FO30) -> 0 | FQ30: 46356 | FX30: =SUM(FX29,FV30,-FW30) -> 0 | FY30: 46356 | GF30: =SUM(GF29,GD30,-GE30) -> 0 | GG30: 46356 | GN30: =SUM(GN29,GL30,-GM30) -> 0 | GO30: 46371 | GV30: =SUM(GV29,GT30,-GU30) -> 0 | GW30: 46371 | HD30: =SUM(HD29,HB30,-HC30) -> 0 | HE30: 46371 | HL30: =SUM(HL29,HJ30,-HK30) -> 0 | HM30: 46371 | HT30: =SUM(HT29,HR30,-HS30) -> 0 | HU30: 46371 | IB30: =SUM(IB29,HZ30,-IA30) -> 0 | IC30: 46371 | IJ30: =SUM(IJ29,IH30,-II30) -> 0 | IK30: 46371 | IR30: =SUM(IR29,IP30,-IQ30) -> 0 | IS30: 46371 | IZ30: =SUM(IZ29,IX30,-IY30) -> 0 | JA30: 46371 | JH30: =SUM(JH29,JF30,-JG30) -> 0 | JI30: 46371 | JP30: =SUM(JP29,JN30,-JO30) -> 0 | JQ30: 42719 | JX30: =SUM(JX29,JV30,-JW30) -> 0 | JY30: 46371 | KF30: =SUM(KF29,KD30,-KE30) -> 0 | KG30: 46371 | KN30: =SUM(KN29,KL30,-KM30) -> 0 | KO30: 46371 | KV30: =SUM(KV29,KT30,-KU30) -> 0 | KW30: 46371 | KZ30: 0 | LD30: =SUM(LD29,LB30,-LC30) -> 0 | LE30: 43084 | LL30: =SUM(LL29,LJ30,-LK30) -> 0 | LM30: 46371 | LT30: =SUM(LT29,LR30,-LS30) -> 0 | LU30: 43084 | MB30: =SUM(MB29,LZ30,-MA30) -> 0 | MC30: 46371 | MJ30: =SUM(MJ29,MH30,-MI30) -> 0 | MK30: 46371 | MR30: =SUM(MR29,MP30,-MQ30) -> 0 | MS30: 46371 | MZ30: =SUM(MZ29,MX30,-MY30) -> 0 | NA30: 46371 | NH30: =SUM(NH29,NF30,-NG30) -> 0 | NI30: 46371 | NP30: =SUM(NP29,NN30,-NO30) -> 0 | NQ30: 46371 | NX30: =SUM(NX29,NV30,-NW30) -> 0 | NY30: 46371 | OF30: =SUM(OF29,OD30,-OE30) -> 0 | OG30: 46371 | ON30: =SUM(ON29,OL30,-OM30) -> 0 | OO30: 46371 | OV30: =SUM(OV29,OT30,-OU30) -> 0 | OW30: 46371 | PD30: =SUM(PD29,PB30,-PC30) -> 0 | PE30: 46371 | PL30: =SUM(PL29,PJ30,-PK30) -> 0 | PM30: 46371 | PT30: =SUM(PT29,PR30,-PS30) -> 0 | PU30: 46371 | QB30: =SUM(QB29,PZ30,-QA30) -> 0 | QC30: 46371 | QJ30: =SUM(QJ29,QH30,-QI30) -> 0 | QK30: 46371 | QR30: =SUM(QR29,QP30,-QQ30) -> 0 | QS30: 46371 | QZ30: =SUM(QZ29,QX30,-QY30) -> 0 | RA30: 46371 | RH30: =SUM(RH29,RF30,-RG30) -> 0 | RI30: 46371 | RP30: =SUM(RP29,RN30,-RO30) -> 0 | RQ30: 43084 | RX30: =SUM(RX29,RV30,-RW30) -> 0 | RY30: 46371 | SF30: =SUM(SF29,SD30,-SE30) -> 0 | SG30: 46371 | SN30: =SUM(SN29,SL30,-SM30) -> 0 | SO30: 46371 | SV30: =SUM(SV29,ST30,-SU30) -> 0 | SW30: 42719 | TD30: =SUM(TD29,TB30,-TC30) -> 0 | TE30: 46371 | TL30: =SUM(TL29,TJ30,-TK30) -> 0 | TM30: 46371 | TT30: =SUM(TT29,TR30,-TS30) -> 0 | TU30: 46371 | UB30: =SUM(UB29,TZ30,-UA30) -> 0 | UC30: 46371 | UJ30: =SUM(UJ29,UH30,-UI30) -> 0 | UK30: 46371 | UR30: =SUM(UR29,UP30,-UQ30) -> 0 | US30: 46371 | UZ30: =SUM(UZ29,UX30,-UY30) -> 0 | VA30: 46371 | VH30: =SUM(VH29,VF30,-VG30) -> 0 | VI30: 46371 | VP30: =SUM(VP29,VN30,-VO30) -> 0 | VQ30: 46371 | VX30: =SUM(VX29,VV30,-VW30) -> 0 | VY30: 46371 | WF30: =SUM(WF29,WD30,-WE30) -> 0 | WG30: 46371 | WN30: =SUM(WN29,WL30,-WM30) -> 0 | WO30: 46371 | WV30: =SUM(WV29,WT30,-WU30) -> 0 | WW30: 46371 | XD30: =SUM(XD29,XB30,-XC30) -> 0 | XE30: 46371 | XL30: =SUM(XL29,XJ30,-XK30) -> 0 | XM30: 46371 | XT30: =SUM(XT29,XR30,-XS30) -> 0 | XU30: 46371 | YB30: =SUM(YB29,XZ30,-YA30) -> 0 | YC30: 46371 | YJ30: =SUM(YJ29,YH30,-YI30) -> 0 | YK30: 46371 | YR30: =SUM(YR29,YP30,-YQ30) -> 0 | YS30: 46371 | YZ30: =SUM(YZ29,YX30,-YY30) -> 0 | ZA30: 46371 | ZH30: =SUM(ZH29,ZF30,-ZG30) -> 0 | ZI30: 46371 | ZP30: =SUM(ZP29,ZN30,-ZO30) -> 0 | ZQ30: 46371 | ZX30: =SUM(ZX29,ZV30,-ZW30) -> 0 | ZY30: 46371 | AAF30: =SUM(AAF29,AAD30,-AAE30) -> 0 | AAG30: 46371 | AAN30: =SUM(AAN29,AAL30,-AAM30) -> 0 | AAO30: 46371 | AAV30: =SUM(AAV29,AAT30,-AAU30) -> 0 | AAW30: 46371 | ABD30: =SUM(ABD29,ABB30,-ABC30) -> 0 | ABE30: 46371 | ABL30: =SUM(ABL29,ABJ30,-ABK30) -> 0 | ABM30: 46371 | ABT30: =SUM(ABT29,ABR30,-ABS30) -> 0 | ABU30: 46371 | ACB30: =SUM(ACB29,ABZ30,-ACA30) -> 0 | ACC30: 46371
D31: =SUM(D30,B31,-C31) -> 1700 | E31: 46371 | L31: =SUM(L30,J31,-K31) -> 1000 | M31: 46371 | T31: =SUM(T30,R31,-S31) -> 4000 | U31: 46371 | AB31: =SUM(AB30,Z31,-AA31) -> 1000 | AC31: 46371 | AJ31: =SUM(AJ30,AH31,-AI31) -> 2000 | AK31: 46371 | AR31: =SUM(AR30,AP31,-AQ31) -> 1000 | AS31: 46371 | AZ31: =SUM(AZ30,AX31,-AY31) -> 1150 | BA31: 46371 | BH31: =SUM(BH30,BF31,-BG31) -> 7000 | BI31: 46371 | BP31: =SUM(BP30,BN31,-BO31) -> 1000 | BQ31: 46371 | BX31: =SUM(BX30,BV31,-BW31) -> 0 | BY31: 46371 | CF31: =SUM(CF30,CD31,-CE31) -> 0 | CG31: 46386 | CN31: =SUM(CN30,CL31,-CM31) -> 0 | CO31: 46386 | CV31: =SUM(CV30,CT31,-CU31) -> 0 | CW31: 46386 | DD31: =SUM(DD30,DB31,-DC31) -> 0 | DE31: 46386 | DL31: =SUM(DL30,DJ31,-DK31) -> 0 | DM31: 46371 | DT31: =SUM(DT30,DR31,-DS31) -> 0 | DU31: 46371 | EB31: =SUM(EB30,DZ31,-EA31) -> 0 | EC31: 46371 | EJ31: =SUM(EJ30,EH31,-EI31) -> 0 | EK31: 46371 | ER31: =SUM(ER30,EP31,-EQ31) -> 0 | ES31: 46371 | EZ31: =SUM(EZ30,EX31,-EY31) -> 0 | FA31: 46371 | FH31: =SUM(FH30,FF31,-FG31) -> 0 | FI31: 46371 | FP31: =SUM(FP30,FN31,-FO31) -> 0 | FQ31: 46371 | FX31: =SUM(FX30,FV31,-FW31) -> 0 | FY31: 46371 | GF31: =SUM(GF30,GD31,-GE31) -> 0 | GG31: 46371 | GN31: =SUM(GN30,GL31,-GM31) -> 0 | GO31: 46386 | GV31: =SUM(GV30,GT31,-GU31) -> 0 | GW31: 46386 | HD31: =SUM(HD30,HB31,-HC31) -> 0 | HE31: 46386 | HL31: =SUM(HL30,HJ31,-HK31) -> 0 | HM31: 46386 | HT31: =SUM(HT30,HR31,-HS31) -> 0 | HU31: 46386 | IB31: =SUM(IB30,HZ31,-IA31) -> 0 | IC31: 46386 | IJ31: =SUM(IJ30,IH31,-II31) -> 0 | IK31: 46386 | IR31: =SUM(IR30,IP31,-IQ31) -> 0 | IS31: 46386 | IZ31: =SUM(IZ30,IX31,-IY31) -> 0 | JA31: 46386 | JH31: =SUM(JH30,JF31,-JG31) -> 0 | JI31: 46386 | JP31: =SUM(JP30,JN31,-JO31) -> 0 | JQ31: 42734 | JX31: =SUM(JX30,JV31,-JW31) -> 0 | JY31: 46386 | KF31: =SUM(KF30,KD31,-KE31) -> 0 | KG31: 46386 | KN31: =SUM(KN30,KL31,-KM31) -> 0 | KO31: 46386 | KV31: =SUM(KV30,KT31,-KU31) -> 0 | KW31: 46386 | KZ31: 0 | LD31: =SUM(LD30,LB31,-LC31) -> 0 | LE31: 43099 | LL31: =SUM(LL30,LJ31,-LK31) -> 0 | LM31: 46386 | LT31: =SUM(LT30,LR31,-LS31) -> 0 | LU31: 43099 | MB31: =SUM(MB30,LZ31,-MA31) -> 0 | MC31: 46386 | MJ31: =SUM(MJ30,MH31,-MI31) -> 0 | MK31: 46386 | MR31: =SUM(MR30,MP31,-MQ31) -> 0 | MS31: 46386 | MZ31: =SUM(MZ30,MX31,-MY31) -> 0 | NA31: 46386 | NH31: =SUM(NH30,NF31,-NG31) -> 0 | NI31: 46386 | NP31: =SUM(NP30,NN31,-NO31) -> 0 | NQ31: 46386 | NX31: =SUM(NX30,NV31,-NW31) -> 0 | NY31: 46386 | OF31: =SUM(OF30,OD31,-OE31) -> 0 | OG31: 46386 | ON31: =SUM(ON30,OL31,-OM31) -> 0 | OO31: 46386 | OV31: =SUM(OV30,OT31,-OU31) -> 0 | OW31: 46386 | PD31: =SUM(PD30,PB31,-PC31) -> 0 | PE31: 46386 | PL31: =SUM(PL30,PJ31,-PK31) -> 0 | PM31: 46386 | PT31: =SUM(PT30,PR31,-PS31) -> 0 | PU31: 46386 | QB31: =SUM(QB30,PZ31,-QA31) -> 0 | QC31: 46386 | QJ31: =SUM(QJ30,QH31,-QI31) -> 0 | QK31: 46386 | QR31: =SUM(QR30,QP31,-QQ31) -> 0 | QS31: 46386 | QZ31: =SUM(QZ30,QX31,-QY31) -> 0 | RA31: 46386 | RH31: =SUM(RH30,RF31,-RG31) -> 0 | RI31: 46386 | RP31: =SUM(RP30,RN31,-RO31) -> 0 | RQ31: 43099 | RX31: =SUM(RX30,RV31,-RW31) -> 0 | RY31: 46386 | SF31: =SUM(SF30,SD31,-SE31) -> 0 | SG31: 46386 | SN31: =SUM(SN30,SL31,-SM31) -> 0 | SO31: 46386 | SV31: =SUM(SV30,ST31,-SU31) -> 0 | SW31: 42734 | TD31: =SUM(TD30,TB31,-TC31) -> 0 | TE31: 46386 | TL31: =SUM(TL30,TJ31,-TK31) -> 0 | TM31: 46386 | TT31: =SUM(TT30,TR31,-TS31) -> 0 | TU31: 46386 | UB31: =SUM(UB30,TZ31,-UA31) -> 0 | UC31: 46386 | UJ31: =SUM(UJ30,UH31,-UI31) -> 0 | UK31: 46386 | UR31: =SUM(UR30,UP31,-UQ31) -> 0 | US31: 46386 | UZ31: =SUM(UZ30,UX31,-UY31) -> 0 | VA31: 46386 | VH31: =SUM(VH30,VF31,-VG31) -> 0 | VI31: 46386 | VP31: =SUM(VP30,VN31,-VO31) -> 0 | VQ31: 46386 | VX31: =SUM(VX30,VV31,-VW31) -> 0 | VY31: 46386 | WF31: =SUM(WF30,WD31,-WE31) -> 0 | WG31: 46386 | WN31: =SUM(WN30,WL31,-WM31) -> 0 | WO31: 46386 | WV31: =SUM(WV30,WT31,-WU31) -> 0 | WW31: 46386 | XD31: =SUM(XD30,XB31,-XC31) -> 0 | XE31: 46386 | XL31: =SUM(XL30,XJ31,-XK31) -> 0 | XM31: 46386 | XT31: =SUM(XT30,XR31,-XS31) -> 0 | XU31: 46386 | YB31: =SUM(YB30,XZ31,-YA31) -> 0 | YC31: 46386 | YJ31: =SUM(YJ30,YH31,-YI31) -> 0 | YK31: 46386 | YR31: =SUM(YR30,YP31,-YQ31) -> 0 | YS31: 46386 | YZ31: =SUM(YZ30,YX31,-YY31) -> 0 | ZA31: 46386 | ZH31: =SUM(ZH30,ZF31,-ZG31) -> 0 | ZI31: 46386 | ZP31: =SUM(ZP30,ZN31,-ZO31) -> 0 | ZQ31: 46386 | ZX31: =SUM(ZX30,ZV31,-ZW31) -> 0 | ZY31: 46386 | AAF31: =SUM(AAF30,AAD31,-AAE31) -> 0 | AAG31: 46386 | AAN31: =SUM(AAN30,AAL31,-AAM31) -> 0 | AAO31: 46386 | AAV31: =SUM(AAV30,AAT31,-AAU31) -> 0 | AAW31: 46386 | ABD31: =SUM(ABD30,ABB31,-ABC31) -> 0 | ABE31: 46386 | ABL31: =SUM(ABL30,ABJ31,-ABK31) -> 0 | ABM31: 46386 | ABT31: =SUM(ABT30,ABR31,-ABS31) -> 0 | ABU31: 46386 | ACB31: =SUM(ACB30,ABZ31,-ACA31) -> 0 | ACC31: 46386
D32: =SUM(D31,B32,-C32) -> 1700 | E32: 46386 | L32: =SUM(L31,J32,-K32) -> 1000 | M32: 46386 | T32: =SUM(T31,R32,-S32) -> 4000 | U32: 46386 | AB32: =SUM(AB31,Z32,-AA32) -> 1000 | AC32: 46386 | AJ32: =SUM(AJ31,AH32,-AI32) -> 2000 | AK32: 46386 | AR32: =SUM(AR31,AP32,-AQ32) -> 1000 | AS32: 46386 | AZ32: =SUM(AZ31,AX32,-AY32) -> 1150 | BA32: 46386 | BH32: =SUM(BH31,BF32,-BG32) -> 7000 | BI32: 46386 | BP32: =SUM(BP31,BN32,-BO32) -> 1000 | BQ32: 46386 | BX32: =SUM(BX31,BV32,-BW32) -> 0 | BY32: 46386 | CF32: =SUM(CF31,CD32,-CE32) -> 0 | CN32: =SUM(CN31,CL32,-CM32) -> 0 | CV32: =SUM(CV31,CT32,-CU32) -> 0 | DD32: =SUM(DD31,DB32,-DC32) -> 0 | DL32: =SUM(DL31,DJ32,-DK32) -> 0 | DM32: 46386 | DT32: =SUM(DT31,DR32,-DS32) -> 0 | DU32: 46386 | EB32: =SUM(EB31,DZ32,-EA32) -> 0 | EC32: 46386 | EJ32: =SUM(EJ31,EH32,-EI32) -> 0 | EK32: 46386 | ER32: =SUM(ER31,EP32,-EQ32) -> 0 | ES32: 46386 | EZ32: =SUM(EZ31,EX32,-EY32) -> 0 | FA32: 46386 | FH32: =SUM(FH31,FF32,-FG32) -> 0 | FI32: 46386 | FP32: =SUM(FP31,FN32,-FO32) -> 0 | FQ32: 46386 | FX32: =SUM(FX31,FV32,-FW32) -> 0 | FY32: 46386 | GF32: =SUM(GF31,GD32,-GE32) -> 0 | GG32: 46386 | GN32: =SUM(GN31,GL32,-GM32) -> 0 | GV32: =SUM(GV31,GT32,-GU32) -> 0 | HD32: =SUM(HD31,HB32,-HC32) -> 0 | HL32: =SUM(HL31,HJ32,-HK32) -> 0 | HT32: =SUM(HT31,HR32,-HS32) -> 0 | IB32: =SUM(IB31,HZ32,-IA32) -> 0 | IJ32: =SUM(IJ31,IH32,-II32) -> 0 | IR32: =SUM(IR31,IP32,-IQ32) -> 0 | IZ32: =SUM(IZ31,IX32,-IY32) -> 0 | JH32: =SUM(JH31,JF32,-JG32) -> 0 | JP32: =SUM(JP31,JN32,-JO32) -> 0 | JX32: =SUM(JX31,JV32,-JW32) -> 0 | KF32: =SUM(KF31,KD32,-KE32) -> 0 | KN32: =SUM(KN31,KL32,-KM32) -> 0 | KV32: =SUM(KV31,KT32,-KU32) -> 0 | LD32: =SUM(LD31,LB32,-LC32) -> 0 | LL32: =SUM(LL31,LJ32,-LK32) -> 0 | LT32: =SUM(LT31,LR32,-LS32) -> 0 | MB32: =SUM(MB31,LZ32,-MA32) -> 0 | MJ32: =SUM(MJ31,MH32,-MI32) -> 0 | MR32: =SUM(MR31,MP32,-MQ32) -> 0 | MZ32: =SUM(MZ31,MX32,-MY32) -> 0 | NH32: =SUM(NH31,NF32,-NG32) -> 0 | NP32: =SUM(NP31,NN32,-NO32) -> 0 | NX32: =SUM(NX31,NV32,-NW32) -> 0 | OF32: =SUM(OF31,OD32,-OE32) -> 0 | ON32: =SUM(ON31,OL32,-OM32) -> 0 | OV32: =SUM(OV31,OT32,-OU32) -> 0 | PD32: =SUM(PD31,PB32,-PC32) -> 0 | PL32: =SUM(PL31,PJ32,-PK32) -> 0 | PT32: =SUM(PT31,PR32,-PS32) -> 0 | QB32: =SUM(QB31,PZ32,-QA32) -> 0 | QJ32: =SUM(QJ31,QH32,-QI32) -> 0 | QR32: =SUM(QR31,QP32,-QQ32) -> 0 | QZ32: =SUM(QZ31,QX32,-QY32) -> 0 | RH32: =SUM(RH31,RF32,-RG32) -> 0 | RP32: =SUM(RP31,RN32,-RO32) -> 0 | RX32: =SUM(RX31,RV32,-RW32) -> 0 | SF32: =SUM(SF31,SD32,-SE32) -> 0 | SN32: =SUM(SN31,SL32,-SM32) -> 0 | SV32: =SUM(SV31,ST32,-SU32) -> 0 | TD32: =SUM(TD31,TB32,-TC32) -> 0 | TL32: =SUM(TL31,TJ32,-TK32) -> 0 | TT32: =SUM(TT31,TR32,-TS32) -> 0 | UB32: =SUM(UB31,TZ32,-UA32) -> 0 | UJ32: =SUM(UJ31,UH32,-UI32) -> 0 | UR32: =SUM(UR31,UP32,-UQ32) -> 0 | UZ32: =SUM(UZ31,UX32,-UY32) -> 0 | VH32: =SUM(VH31,VF32,-VG32) -> 0 | VP32: =SUM(VP31,VN32,-VO32) -> 0 | VX32: =SUM(VX31,VV32,-VW32) -> 0 | WF32: =SUM(WF31,WD32,-WE32) -> 0 | WN32: =SUM(WN31,WL32,-WM32) -> 0 | WV32: =SUM(WV31,WT32,-WU32) -> 0 | XD32: =SUM(XD31,XB32,-XC32) -> 0 | XL32: =SUM(XL31,XJ32,-XK32) -> 0 | XT32: =SUM(XT31,XR32,-XS32) -> 0 | YB32: =SUM(YB31,XZ32,-YA32) -> 0 | YJ32: =SUM(YJ31,YH32,-YI32) -> 0 | YR32: =SUM(YR31,YP32,-YQ32) -> 0 | YZ32: =SUM(YZ31,YX32,-YY32) -> 0 | ZH32: =SUM(ZH31,ZF32,-ZG32) -> 0 | ZP32: =SUM(ZP31,ZN32,-ZO32) -> 0 | ZX32: =SUM(ZX31,ZV32,-ZW32) -> 0 | AAF32: =SUM(AAF31,AAD32,-AAE32) -> 0 | AAN32: =SUM(AAN31,AAL32,-AAM32) -> 0 | AAV32: =SUM(AAV31,AAT32,-AAU32) -> 0 | ABD32: =SUM(ABD31,ABB32,-ABC32) -> 0 | ABL32: =SUM(ABL31,ABJ32,-ABK32) -> 0 | ABT32: =SUM(ABT31,ABR32,-ABS32) -> 0 | ACB32: =SUM(ACB31,ABZ32,-ACA32) -> 0
D33: =SUM(D32,B33,-C33) -> 1700 | L33: =SUM(L32,J33,-K33) -> 1000 | T33: =SUM(T32,R33,-S33) -> 4000 | AB33: =SUM(AB32,Z33,-AA33) -> 1000 | AJ33: =SUM(AJ32,AH33,-AI33) -> 2000 | AR33: =SUM(AR32,AP33,-AQ33) -> 1000 | AZ33: =SUM(AZ32,AX33,-AY33) -> 1150 | BH33: =SUM(BH32,BF33,-BG33) -> 7000 | BP33: =SUM(BP32,BN33,-BO33) -> 1000 | BX33: =SUM(BX32,BV33,-BW33) -> 0 | CF33: =SUM(CF32,CD33,-CE33) -> 0 | CN33: =SUM(CN32,CL33,-CM33) -> 0 | CV33: =SUM(CV32,CT33,-CU33) -> 0 | DD33: =SUM(DD32,DB33,-DC33) -> 0 | DL33: =SUM(DL32,DJ33,-DK33) -> 0 | DT33: =SUM(DT32,DR33,-DS33) -> 0 | EB33: =SUM(EB32,DZ33,-EA33) -> 0 | EJ33: =SUM(EJ32,EH33,-EI33) -> 0 | ER33: =SUM(ER32,EP33,-EQ33) -> 0 | EZ33: =SUM(EZ32,EX33,-EY33) -> 0 | FH33: =SUM(FH32,FF33,-FG33) -> 0 | FP33: =SUM(FP32,FN33,-FO33) -> 0 | FX33: =SUM(FX32,FV33,-FW33) -> 0 | GF33: =SUM(GF32,GD33,-GE33) -> 0 | GN33: =SUM(GN32,GL33,-GM33) -> 0 | GV33: =SUM(GV32,GT33,-GU33) -> 0 | HD33: =SUM(HD32,HB33,-HC33) -> 0 | HL33: =SUM(HL32,HJ33,-HK33) -> 0 | HT33: =SUM(HT32,HR33,-HS33) -> 0 | IB33: =SUM(IB32,HZ33,-IA33) -> 0 | IJ33: =SUM(IJ32,IH33,-II33) -> 0 | IR33: =SUM(IR32,IP33,-IQ33) -> 0 | IZ33: =SUM(IZ32,IX33,-IY33) -> 0 | JH33: =SUM(JH32,JF33,-JG33) -> 0 | JP33: =SUM(JP32,JN33,-JO33) -> 0 | JX33: =SUM(JX32,JV33,-JW33) -> 0 | KF33: =SUM(KF32,KD33,-KE33) -> 0 | KN33: =SUM(KN32,KL33,-KM33) -> 0 | KV33: =SUM(KV32,KT33,-KU33) -> 0 | LD33: =SUM(LD32,LB33,-LC33) -> 0 | LL33: =SUM(LL32,LJ33,-LK33) -> 0 | LT33: =SUM(LT32,LR33,-LS33) -> 0 | MB33: =SUM(MB32,LZ33,-MA33) -> 0 | MJ33: =SUM(MJ32,MH33,-MI33) -> 0 | MR33: =SUM(MR32,MP33,-MQ33) -> 0 | MZ33: =SUM(MZ32,MX33,-MY33) -> 0 | NH33: =SUM(NH32,NF33,-NG33) -> 0 | NP33: =SUM(NP32,NN33,-NO33) -> 0 | NX33: =SUM(NX32,NV33,-NW33) -> 0 | OF33: =SUM(OF32,OD33,-OE33) -> 0 | ON33: =SUM(ON32,OL33,-OM33) -> 0 | OV33: =SUM(OV32,OT33,-OU33) -> 0 | PD33: =SUM(PD32,PB33,-PC33) -> 0 | PL33: =SUM(PL32,PJ33,-PK33) -> 0 | PT33: =SUM(PT32,PR33,-PS33) -> 0 | QB33: =SUM(QB32,PZ33,-QA33) -> 0 | QJ33: =SUM(QJ32,QH33,-QI33) -> 0 | QR33: =SUM(QR32,QP33,-QQ33) -> 0 | QZ33: =SUM(QZ32,QX33,-QY33) -> 0 | RH33: =SUM(RH32,RF33,-RG33) -> 0 | RP33: =SUM(RP32,RN33,-RO33) -> 0 | RX33: =SUM(RX32,RV33,-RW33) -> 0 | SF33: =SUM(SF32,SD33,-SE33) -> 0 | SN33: =SUM(SN32,SL33,-SM33) -> 0 | SV33: =SUM(SV32,ST33,-SU33) -> 0 | TD33: =SUM(TD32,TB33,-TC33) -> 0 | TL33: =SUM(TL32,TJ33,-TK33) -> 0 | TT33: =SUM(TT32,TR33,-TS33) -> 0 | UB33: =SUM(UB32,TZ33,-UA33) -> 0 | UJ33: =SUM(UJ32,UH33,-UI33) -> 0 | UR33: =SUM(UR32,UP33,-UQ33) -> 0 | UZ33: =SUM(UZ32,UX33,-UY33) -> 0 | VH33: =SUM(VH32,VF33,-VG33) -> 0 | VP33: =SUM(VP32,VN33,-VO33) -> 0 | VX33: =SUM(VX32,VV33,-VW33) -> 0 | WF33: =SUM(WF32,WD33,-WE33) -> 0 | WN33: =SUM(WN32,WL33,-WM33) -> 0 | WV33: =SUM(WV32,WT33,-WU33) -> 0 | XD33: =SUM(XD32,XB33,-XC33) -> 0 | XL33: =SUM(XL32,XJ33,-XK33) -> 0 | XT33: =SUM(XT32,XR33,-XS33) -> 0 | YB33: =SUM(YB32,XZ33,-YA33) -> 0 | YJ33: =SUM(YJ32,YH33,-YI33) -> 0 | YR33: =SUM(YR32,YP33,-YQ33) -> 0 | YZ33: =SUM(YZ32,YX33,-YY33) -> 0 | ZH33: =SUM(ZH32,ZF33,-ZG33) -> 0 | ZP33: =SUM(ZP32,ZN33,-ZO33) -> 0 | ZX33: =SUM(ZX32,ZV33,-ZW33) -> 0 | AAF33: =SUM(AAF32,AAD33,-AAE33) -> 0 | AAN33: =SUM(AAN32,AAL33,-AAM33) -> 0 | AAV33: =SUM(AAV32,AAT33,-AAU33) -> 0 | ABD33: =SUM(ABD32,ABB33,-ABC33) -> 0 | ABL33: =SUM(ABL32,ABJ33,-ABK33) -> 0 | ABT33: =SUM(ABT32,ABR33,-ABS33) -> 0 | ACB33: =SUM(ACB32,ABZ33,-ACA33) -> 0
D34: =SUM(D33,B34,-C34) -> 1700 | L34: =SUM(L33,J34,-K34) -> 1000 | T34: =SUM(T33,R34,-S34) -> 4000 | AB34: =SUM(AB33,Z34,-AA34) -> 1000 | AJ34: =SUM(AJ33,AH34,-AI34) -> 2000 | AR34: =SUM(AR33,AP34,-AQ34) -> 1000 | AZ34: =SUM(AZ33,AX34,-AY34) -> 1150 | BH34: =SUM(BH33,BF34,-BG34) -> 7000 | BP34: =SUM(BP33,BN34,-BO34) -> 1000 | BX34: =SUM(BX33,BV34,-BW34) -> 0 | CF34: =SUM(CF33,CD34,-CE34) -> 0 | CN34: =SUM(CN33,CL34,-CM34) -> 0 | CV34: =SUM(CV33,CT34,-CU34) -> 0 | DD34: =SUM(DD33,DB34,-DC34) -> 0 | DL34: =SUM(DL33,DJ34,-DK34) -> 0 | DT34: =SUM(DT33,DR34,-DS34) -> 0 | EB34: =SUM(EB33,DZ34,-EA34) -> 0 | EJ34: =SUM(EJ33,EH34,-EI34) -> 0 | ER34: =SUM(ER33,EP34,-EQ34) -> 0 | EZ34: =SUM(EZ33,EX34,-EY34) -> 0 | FH34: =SUM(FH33,FF34,-FG34) -> 0 | FP34: =SUM(FP33,FN34,-FO34) -> 0 | FX34: =SUM(FX33,FV34,-FW34) -> 0 | GF34: =SUM(GF33,GD34,-GE34) -> 0 | GN34: =SUM(GN33,GL34,-GM34) -> 0 | GV34: =SUM(GV33,GT34,-GU34) -> 0 | HD34: =SUM(HD33,HB34,-HC34) -> 0 | HL34: =SUM(HL33,HJ34,-HK34) -> 0 | HT34: =SUM(HT33,HR34,-HS34) -> 0 | IB34: =SUM(IB33,HZ34,-IA34) -> 0 | IJ34: =SUM(IJ33,IH34,-II34) -> 0 | IR34: =SUM(IR33,IP34,-IQ34) -> 0 | IZ34: =SUM(IZ33,IX34,-IY34) -> 0 | JH34: =SUM(JH33,JF34,-JG34) -> 0 | JP34: =SUM(JP33,JN34,-JO34) -> 0 | JX34: =SUM(JX33,JV34,-JW34) -> 0 | KF34: =SUM(KF33,KD34,-KE34) -> 0 | KN34: =SUM(KN33,KL34,-KM34) -> 0 | KV34: =SUM(KV33,KT34,-KU34) -> 0 | LD34: =SUM(LD33,LB34,-LC34) -> 0 | LL34: =SUM(LL33,LJ34,-LK34) -> 0 | LT34: =SUM(LT33,LR34,-LS34) -> 0 | MB34: =SUM(MB33,LZ34,-MA34) -> 0 | MJ34: =SUM(MJ33,MH34,-MI34) -> 0 | MR34: =SUM(MR33,MP34,-MQ34) -> 0 | MZ34: =SUM(MZ33,MX34,-MY34) -> 0 | NH34: =SUM(NH33,NF34,-NG34) -> 0 | NP34: =SUM(NP33,NN34,-NO34) -> 0 | NX34: =SUM(NX33,NV34,-NW34) -> 0 | OF34: =SUM(OF33,OD34,-OE34) -> 0 | ON34: =SUM(ON33,OL34,-OM34) -> 0 | OV34: =SUM(OV33,OT34,-OU34) -> 0 | PD34: =SUM(PD33,PB34,-PC34) -> 0 | PL34: =SUM(PL33,PJ34,-PK34) -> 0 | PT34: =SUM(PT33,PR34,-PS34) -> 0 | QB34: =SUM(QB33,PZ34,-QA34) -> 0 | QJ34: =SUM(QJ33,QH34,-QI34) -> 0 | QR34: =SUM(QR33,QP34,-QQ34) -> 0 | QZ34: =SUM(QZ33,QX34,-QY34) -> 0 | RH34: =SUM(RH33,RF34,-RG34) -> 0 | RP34: =SUM(RP33,RN34,-RO34) -> 0 | RX34: =SUM(RX33,RV34,-RW34) -> 0 | SF34: =SUM(SF33,SD34,-SE34) -> 0 | SN34: =SUM(SN33,SL34,-SM34) -> 0 | SV34: =SUM(SV33,ST34,-SU34) -> 0 | TD34: =SUM(TD33,TB34,-TC34) -> 0 | TL34: =SUM(TL33,TJ34,-TK34) -> 0 | TT34: =SUM(TT33,TR34,-TS34) -> 0 | UB34: =SUM(UB33,TZ34,-UA34) -> 0 | UJ34: =SUM(UJ33,UH34,-UI34) -> 0 | UR34: =SUM(UR33,UP34,-UQ34) -> 0 | UZ34: =SUM(UZ33,UX34,-UY34) -> 0 | VH34: =SUM(VH33,VF34,-VG34) -> 0 | VP34: =SUM(VP33,VN34,-VO34) -> 0 | VX34: =SUM(VX33,VV34,-VW34) -> 0 | WF34: =SUM(WF33,WD34,-WE34) -> 0 | WN34: =SUM(WN33,WL34,-WM34) -> 0 | WV34: =SUM(WV33,WT34,-WU34) -> 0 | XD34: =SUM(XD33,XB34,-XC34) -> 0 | XL34: =SUM(XL33,XJ34,-XK34) -> 0 | XT34: =SUM(XT33,XR34,-XS34) -> 0 | YB34: =SUM(YB33,XZ34,-YA34) -> 0 | YJ34: =SUM(YJ33,YH34,-YI34) -> 0 | YR34: =SUM(YR33,YP34,-YQ34) -> 0 | YZ34: =SUM(YZ33,YX34,-YY34) -> 0 | ZH34: =SUM(ZH33,ZF34,-ZG34) -> 0 | ZP34: =SUM(ZP33,ZN34,-ZO34) -> 0 | ZX34: =SUM(ZX33,ZV34,-ZW34) -> 0 | AAF34: =SUM(AAF33,AAD34,-AAE34) -> 0 | AAN34: =SUM(AAN33,AAL34,-AAM34) -> 0 | AAV34: =SUM(AAV33,AAT34,-AAU34) -> 0 | ABD34: =SUM(ABD33,ABB34,-ABC34) -> 0 | ABL34: =SUM(ABL33,ABJ34,-ABK34) -> 0 | ABT34: =SUM(ABT33,ABR34,-ABS34) -> 0 | ACB34: =SUM(ACB33,ABZ34,-ACA34) -> 0
D35: =SUM(D34,B35,-C35) -> 1700 | L35: =SUM(L34,J35,-K35) -> 1000 | T35: =SUM(T34,R35,-S35) -> 4000 | AB35: =SUM(AB34,Z35,-AA35) -> 1000 | AJ35: =SUM(AJ34,AH35,-AI35) -> 2000 | AR35: =SUM(AR34,AP35,-AQ35) -> 1000 | AZ35: =SUM(AZ34,AX35,-AY35) -> 1150 | BH35: =SUM(BH34,BF35,-BG35) -> 7000 | BP35: =SUM(BP34,BN35,-BO35) -> 1000 | BX35: =SUM(BX34,BV35,-BW35) -> 0 | CF35: =SUM(CF34,CD35,-CE35) -> 0 | CN35: =SUM(CN34,CL35,-CM35) -> 0 | CV35: =SUM(CV34,CT35,-CU35) -> 0 | DD35: =SUM(DD34,DB35,-DC35) -> 0 | DL35: =SUM(DL34,DJ35,-DK35) -> 0 | DT35: =SUM(DT34,DR35,-DS35) -> 0 | EB35: =SUM(EB34,DZ35,-EA35) -> 0 | EJ35: =SUM(EJ34,EH35,-EI35) -> 0 | ER35: =SUM(ER34,EP35,-EQ35) -> 0 | EZ35: =SUM(EZ34,EX35,-EY35) -> 0 | FH35: =SUM(FH34,FF35,-FG35) -> 0 | FP35: =SUM(FP34,FN35,-FO35) -> 0 | FX35: =SUM(FX34,FV35,-FW35) -> 0 | GF35: =SUM(GF34,GD35,-GE35) -> 0 | GN35: =SUM(GN34,GL35,-GM35) -> 0 | GV35: =SUM(GV34,GT35,-GU35) -> 0 | HD35: =SUM(HD34,HB35,-HC35) -> 0 | HL35: =SUM(HL34,HJ35,-HK35) -> 0 | HT35: =SUM(HT34,HR35,-HS35) -> 0 | IB35: =SUM(IB34,HZ35,-IA35) -> 0 | IJ35: =SUM(IJ34,IH35,-II35) -> 0 | IR35: =SUM(IR34,IP35,-IQ35) -> 0 | IZ35: =SUM(IZ34,IX35,-IY35) -> 0 | JH35: =SUM(JH34,JF35,-JG35) -> 0 | JP35: =SUM(JP34,JN35,-JO35) -> 0 | JX35: =SUM(JX34,JV35,-JW35) -> 0 | KF35: =SUM(KF34,KD35,-KE35) -> 0 | KN35: =SUM(KN34,KL35,-KM35) -> 0 | KV35: =SUM(KV34,KT35,-KU35) -> 0 | LD35: =SUM(LD34,LB35,-LC35) -> 0 | LL35: =SUM(LL34,LJ35,-LK35) -> 0 | LT35: =SUM(LT34,LR35,-LS35) -> 0 | MB35: =SUM(MB34,LZ35,-MA35) -> 0 | MJ35: =SUM(MJ34,MH35,-MI35) -> 0 | MR35: =SUM(MR34,MP35,-MQ35) -> 0 | MZ35: =SUM(MZ34,MX35,-MY35) -> 0 | NH35: =SUM(NH34,NF35,-NG35) -> 0 | NP35: =SUM(NP34,NN35,-NO35) -> 0 | NX35: =SUM(NX34,NV35,-NW35) -> 0 | OF35: =SUM(OF34,OD35,-OE35) -> 0 | ON35: =SUM(ON34,OL35,-OM35) -> 0 | OV35: =SUM(OV34,OT35,-OU35) -> 0 | PD35: =SUM(PD34,PB35,-PC35) -> 0 | PL35: =SUM(PL34,PJ35,-PK35) -> 0 | PT35: =SUM(PT34,PR35,-PS35) -> 0 | QB35: =SUM(QB34,PZ35,-QA35) -> 0 | QJ35: =SUM(QJ34,QH35,-QI35) -> 0 | QR35: =SUM(QR34,QP35,-QQ35) -> 0 | QZ35: =SUM(QZ34,QX35,-QY35) -> 0 | RH35: =SUM(RH34,RF35,-RG35) -> 0 | RP35: =SUM(RP34,RN35,-RO35) -> 0 | RX35: =SUM(RX34,RV35,-RW35) -> 0 | SF35: =SUM(SF34,SD35,-SE35) -> 0 | SN35: =SUM(SN34,SL35,-SM35) -> 0 | SV35: =SUM(SV34,ST35,-SU35) -> 0 | TD35: =SUM(TD34,TB35,-TC35) -> 0 | TL35: =SUM(TL34,TJ35,-TK35) -> 0 | TT35: =SUM(TT34,TR35,-TS35) -> 0 | UB35: =SUM(UB34,TZ35,-UA35) -> 0 | UJ35: =SUM(UJ34,UH35,-UI35) -> 0 | UR35: =SUM(UR34,UP35,-UQ35) -> 0 | UZ35: =SUM(UZ34,UX35,-UY35) -> 0 | VH35: =SUM(VH34,VF35,-VG35) -> 0 | VP35: =SUM(VP34,VN35,-VO35) -> 0 | VX35: =SUM(VX34,VV35,-VW35) -> 0 | WF35: =SUM(WF34,WD35,-WE35) -> 0 | WN35: =SUM(WN34,WL35,-WM35) -> 0 | WV35: =SUM(WV34,WT35,-WU35) -> 0 | XD35: =SUM(XD34,XB35,-XC35) -> 0 | XL35: =SUM(XL34,XJ35,-XK35) -> 0 | XT35: =SUM(XT34,XR35,-XS35) -> 0 | YB35: =SUM(YB34,XZ35,-YA35) -> 0 | YJ35: =SUM(YJ34,YH35,-YI35) -> 0 | YR35: =SUM(YR34,YP35,-YQ35) -> 0 | YZ35: =SUM(YZ34,YX35,-YY35) -> 0 | ZH35: =SUM(ZH34,ZF35,-ZG35) -> 0 | ZP35: =SUM(ZP34,ZN35,-ZO35) -> 0 | ZX35: =SUM(ZX34,ZV35,-ZW35) -> 0 | AAF35: =SUM(AAF34,AAD35,-AAE35) -> 0 | AAN35: =SUM(AAN34,AAL35,-AAM35) -> 0 | AAV35: =SUM(AAV34,AAT35,-AAU35) -> 0 | ABD35: =SUM(ABD34,ABB35,-ABC35) -> 0 | ABL35: =SUM(ABL34,ABJ35,-ABK35) -> 0 | ABT35: =SUM(ABT34,ABR35,-ABS35) -> 0 | ACB35: =SUM(ACB34,ABZ35,-ACA35) -> 0
D36: =SUM(D35,B36,-C36) -> 1700 | L36: =SUM(L35,J36,-K36) -> 1000 | T36: =SUM(T35,R36,-S36) -> 4000 | AB36: =SUM(AB35,Z36,-AA36) -> 1000 | AJ36: =SUM(AJ35,AH36,-AI36) -> 2000 | AR36: =SUM(AR35,AP36,-AQ36) -> 1000 | AZ36: =SUM(AZ35,AX36,-AY36) -> 1150 | BH36: =SUM(BH35,BF36,-BG36) -> 7000 | BP36: =SUM(BP35,BN36,-BO36) -> 1000 | BX36: =SUM(BX35,BV36,-BW36) -> 0 | CF36: =SUM(CF35,CD36,-CE36) -> 0 | CN36: =SUM(CN35,CL36,-CM36) -> 0 | CV36: =SUM(CV35,CT36,-CU36) -> 0 | DD36: =SUM(DD35,DB36,-DC36) -> 0 | DL36: =SUM(DL35,DJ36,-DK36) -> 0 | DT36: =SUM(DT35,DR36,-DS36) -> 0 | EB36: =SUM(EB35,DZ36,-EA36) -> 0 | EJ36: =SUM(EJ35,EH36,-EI36) -> 0 | ER36: =SUM(ER35,EP36,-EQ36) -> 0 | EZ36: =SUM(EZ35,EX36,-EY36) -> 0 | FH36: =SUM(FH35,FF36,-FG36) -> 0 | FP36: =SUM(FP35,FN36,-FO36) -> 0 | FX36: =SUM(FX35,FV36,-FW36) -> 0 | GF36: =SUM(GF35,GD36,-GE36) -> 0 | GN36: =SUM(GN35,GL36,-GM36) -> 0 | GV36: =SUM(GV35,GT36,-GU36) -> 0 | HD36: =SUM(HD35,HB36,-HC36) -> 0 | HL36: =SUM(HL35,HJ36,-HK36) -> 0 | HT36: =SUM(HT35,HR36,-HS36) -> 0 | IB36: =SUM(IB35,HZ36,-IA36) -> 0 | IJ36: =SUM(IJ35,IH36,-II36) -> 0 | IR36: =SUM(IR35,IP36,-IQ36) -> 0 | IZ36: =SUM(IZ35,IX36,-IY36) -> 0 | JH36: =SUM(JH35,JF36,-JG36) -> 0 | JP36: =SUM(JP35,JN36,-JO36) -> 0 | JX36: =SUM(JX35,JV36,-JW36) -> 0 | KF36: =SUM(KF35,KD36,-KE36) -> 0 | KN36: =SUM(KN35,KL36,-KM36) -> 0 | KV36: =SUM(KV35,KT36,-KU36) -> 0 | LD36: =SUM(LD35,LB36,-LC36) -> 0 | LL36: =SUM(LL35,LJ36,-LK36) -> 0 | LT36: =SUM(LT35,LR36,-LS36) -> 0 | MB36: =SUM(MB35,LZ36,-MA36) -> 0 | MJ36: =SUM(MJ35,MH36,-MI36) -> 0 | MR36: =SUM(MR35,MP36,-MQ36) -> 0 | MZ36: =SUM(MZ35,MX36,-MY36) -> 0 | NH36: =SUM(NH35,NF36,-NG36) -> 0 | NP36: =SUM(NP35,NN36,-NO36) -> 0 | NX36: =SUM(NX35,NV36,-NW36) -> 0 | OF36: =SUM(OF35,OD36,-OE36) -> 0 | ON36: =SUM(ON35,OL36,-OM36) -> 0 | OV36: =SUM(OV35,OT36,-OU36) -> 0 | PD36: =SUM(PD35,PB36,-PC36) -> 0 | PL36: =SUM(PL35,PJ36,-PK36) -> 0 | PT36: =SUM(PT35,PR36,-PS36) -> 0 | QB36: =SUM(QB35,PZ36,-QA36) -> 0 | QJ36: =SUM(QJ35,QH36,-QI36) -> 0 | QR36: =SUM(QR35,QP36,-QQ36) -> 0 | QZ36: =SUM(QZ35,QX36,-QY36) -> 0 | RH36: =SUM(RH35,RF36,-RG36) -> 0 | RP36: =SUM(RP35,RN36,-RO36) -> 0 | RX36: =SUM(RX35,RV36,-RW36) -> 0 | SF36: =SUM(SF35,SD36,-SE36) -> 0 | SN36: =SUM(SN35,SL36,-SM36) -> 0 | SV36: =SUM(SV35,ST36,-SU36) -> 0 | TD36: =SUM(TD35,TB36,-TC36) -> 0 | TL36: =SUM(TL35,TJ36,-TK36) -> 0 | TT36: =SUM(TT35,TR36,-TS36) -> 0 | UB36: =SUM(UB35,TZ36,-UA36) -> 0 | UJ36: =SUM(UJ35,UH36,-UI36) -> 0 | UR36: =SUM(UR35,UP36,-UQ36) -> 0 | UZ36: =SUM(UZ35,UX36,-UY36) -> 0 | VH36: =SUM(VH35,VF36,-VG36) -> 0 | VP36: =SUM(VP35,VN36,-VO36) -> 0 | VX36: =SUM(VX35,VV36,-VW36) -> 0 | WF36: =SUM(WF35,WD36,-WE36) -> 0 | WN36: =SUM(WN35,WL36,-WM36) -> 0 | WV36: =SUM(WV35,WT36,-WU36) -> 0 | XD36: =SUM(XD35,XB36,-XC36) -> 0 | XL36: =SUM(XL35,XJ36,-XK36) -> 0 | XT36: =SUM(XT35,XR36,-XS36) -> 0 | YB36: =SUM(YB35,XZ36,-YA36) -> 0 | YJ36: =SUM(YJ35,YH36,-YI36) -> 0 | YR36: =SUM(YR35,YP36,-YQ36) -> 0 | YZ36: =SUM(YZ35,YX36,-YY36) -> 0 | ZH36: =SUM(ZH35,ZF36,-ZG36) -> 0 | ZP36: =SUM(ZP35,ZN36,-ZO36) -> 0 | ZX36: =SUM(ZX35,ZV36,-ZW36) -> 0 | AAF36: =SUM(AAF35,AAD36,-AAE36) -> 0 | AAN36: =SUM(AAN35,AAL36,-AAM36) -> 0 | AAV36: =SUM(AAV35,AAT36,-AAU36) -> 0 | ABD36: =SUM(ABD35,ABB36,-ABC36) -> 0 | ABL36: =SUM(ABL35,ABJ36,-ABK36) -> 0 | ABT36: =SUM(ABT35,ABR36,-ABS36) -> 0 | ACB36: =SUM(ACB35,ABZ36,-ACA36) -> 0
D37: =SUM(D36,B37,-C37) -> 1700 | L37: =SUM(L36,J37,-K37) -> 1000 | T37: =SUM(T36,R37,-S37) -> 4000 | AB37: =SUM(AB36,Z37,-AA37) -> 1000 | AJ37: =SUM(AJ36,AH37,-AI37) -> 2000 | AR37: =SUM(AR36,AP37,-AQ37) -> 1000 | AZ37: =SUM(AZ36,AX37,-AY37) -> 1150 | BH37: =SUM(BH36,BF37,-BG37) -> 7000 | BP37: =SUM(BP36,BN37,-BO37) -> 1000 | BX37: =SUM(BX36,BV37,-BW37) -> 0 | CF37: =SUM(CF36,CD37,-CE37) -> 0 | CN37: =SUM(CN36,CL37,-CM37) -> 0 | CV37: =SUM(CV36,CT37,-CU37) -> 0 | DD37: =SUM(DD36,DB37,-DC37) -> 0 | DL37: =SUM(DL36,DJ37,-DK37) -> 0 | DT37: =SUM(DT36,DR37,-DS37) -> 0 | EB37: =SUM(EB36,DZ37,-EA37) -> 0 | EJ37: =SUM(EJ36,EH37,-EI37) -> 0 | ER37: =SUM(ER36,EP37,-EQ37) -> 0 | EZ37: =SUM(EZ36,EX37,-EY37) -> 0 | FH37: =SUM(FH36,FF37,-FG37) -> 0 | FP37: =SUM(FP36,FN37,-FO37) -> 0 | FX37: =SUM(FX36,FV37,-FW37) -> 0 | GF37: =SUM(GF36,GD37,-GE37) -> 0 | GN37: =SUM(GN36,GL37,-GM37) -> 0 | GV37: =SUM(GV36,GT37,-GU37) -> 0 | HD37: =SUM(HD36,HB37,-HC37) -> 0 | HL37: =SUM(HL36,HJ37,-HK37) -> 0 | HT37: =SUM(HT36,HR37,-HS37) -> 0 | IB37: =SUM(IB36,HZ37,-IA37) -> 0 | IJ37: =SUM(IJ36,IH37,-II37) -> 0 | IR37: =SUM(IR36,IP37,-IQ37) -> 0 | IZ37: =SUM(IZ36,IX37,-IY37) -> 0 | JH37: =SUM(JH36,JF37,-JG37) -> 0 | JP37: =SUM(JP36,JN37,-JO37) -> 0 | JX37: =SUM(JX36,JV37,-JW37) -> 0 | KF37: =SUM(KF36,KD37,-KE37) -> 0 | KN37: =SUM(KN36,KL37,-KM37) -> 0 | KV37: =SUM(KV36,KT37,-KU37) -> 0 | LD37: =SUM(LD36,LB37,-LC37) -> 0 | LL37: =SUM(LL36,LJ37,-LK37) -> 0 | LT37: =SUM(LT36,LR37,-LS37) -> 0 | MB37: =SUM(MB36,LZ37,-MA37) -> 0 | MJ37: =SUM(MJ36,MH37,-MI37) -> 0 | MR37: =SUM(MR36,MP37,-MQ37) -> 0 | MZ37: =SUM(MZ36,MX37,-MY37) -> 0 | NH37: =SUM(NH36,NF37,-NG37) -> 0 | NP37: =SUM(NP36,NN37,-NO37) -> 0 | NX37: =SUM(NX36,NV37,-NW37) -> 0 | OF37: =SUM(OF36,OD37,-OE37) -> 0 | ON37: =SUM(ON36,OL37,-OM37) -> 0 | OV37: =SUM(OV36,OT37,-OU37) -> 0 | PD37: =SUM(PD36,PB37,-PC37) -> 0 | PL37: =SUM(PL36,PJ37,-PK37) -> 0 | PT37: =SUM(PT36,PR37,-PS37) -> 0 | QB37: =SUM(QB36,PZ37,-QA37) -> 0 | QJ37: =SUM(QJ36,QH37,-QI37) -> 0 | QR37: =SUM(QR36,QP37,-QQ37) -> 0 | QZ37: =SUM(QZ36,QX37,-QY37) -> 0 | RH37: =SUM(RH36,RF37,-RG37) -> 0 | RP37: =SUM(RP36,RN37,-RO37) -> 0 | RX37: =SUM(RX36,RV37,-RW37) -> 0 | SF37: =SUM(SF36,SD37,-SE37) -> 0 | SN37: =SUM(SN36,SL37,-SM37) -> 0 | SV37: =SUM(SV36,ST37,-SU37) -> 0 | TD37: =SUM(TD36,TB37,-TC37) -> 0 | TL37: =SUM(TL36,TJ37,-TK37) -> 0 | TT37: =SUM(TT36,TR37,-TS37) -> 0 | UB37: =SUM(UB36,TZ37,-UA37) -> 0 | UJ37: =SUM(UJ36,UH37,-UI37) -> 0 | UR37: =SUM(UR36,UP37,-UQ37) -> 0 | UZ37: =SUM(UZ36,UX37,-UY37) -> 0 | VH37: =SUM(VH36,VF37,-VG37) -> 0 | VP37: =SUM(VP36,VN37,-VO37) -> 0 | VX37: =SUM(VX36,VV37,-VW37) -> 0 | WF37: =SUM(WF36,WD37,-WE37) -> 0 | WN37: =SUM(WN36,WL37,-WM37) -> 0 | WV37: =SUM(WV36,WT37,-WU37) -> 0 | XD37: =SUM(XD36,XB37,-XC37) -> 0 | XL37: =SUM(XL36,XJ37,-XK37) -> 0 | XT37: =SUM(XT36,XR37,-XS37) -> 0 | YB37: =SUM(YB36,XZ37,-YA37) -> 0 | YJ37: =SUM(YJ36,YH37,-YI37) -> 0 | YR37: =SUM(YR36,YP37,-YQ37) -> 0 | YZ37: =SUM(YZ36,YX37,-YY37) -> 0 | ZH37: =SUM(ZH36,ZF37,-ZG37) -> 0 | ZP37: =SUM(ZP36,ZN37,-ZO37) -> 0 | ZX37: =SUM(ZX36,ZV37,-ZW37) -> 0 | AAF37: =SUM(AAF36,AAD37,-AAE37) -> 0 | AAN37: =SUM(AAN36,AAL37,-AAM37) -> 0 | AAV37: =SUM(AAV36,AAT37,-AAU37) -> 0 | ABD37: =SUM(ABD36,ABB37,-ABC37) -> 0 | ABL37: =SUM(ABL36,ABJ37,-ABK37) -> 0 | ABT37: =SUM(ABT36,ABR37,-ABS37) -> 0 | ACB37: =SUM(ACB36,ABZ37,-ACA37) -> 0
D38: =SUM(D37,B38,-C38) -> 1700 | L38: =SUM(L37,J38,-K38) -> 1000 | T38: =SUM(T37,R38,-S38) -> 4000 | AB38: =SUM(AB37,Z38,-AA38) -> 1000 | AJ38: =SUM(AJ37,AH38,-AI38) -> 2000 | AR38: =SUM(AR37,AP38,-AQ38) -> 1000 | AZ38: =SUM(AZ37,AX38,-AY38) -> 1150 | BH38: =SUM(BH37,BF38,-BG38) -> 7000 | BP38: =SUM(BP37,BN38,-BO38) -> 1000 | BX38: =SUM(BX37,BV38,-BW38) -> 0 | CF38: =SUM(CF37,CD38,-CE38) -> 0 | CN38: =SUM(CN37,CL38,-CM38) -> 0 | CV38: =SUM(CV37,CT38,-CU38) -> 0 | DD38: =SUM(DD37,DB38,-DC38) -> 0 | DL38: =SUM(DL37,DJ38,-DK38) -> 0 | DT38: =SUM(DT37,DR38,-DS38) -> 0 | EB38: =SUM(EB37,DZ38,-EA38) -> 0 | EJ38: =SUM(EJ37,EH38,-EI38) -> 0 | ER38: =SUM(ER37,EP38,-EQ38) -> 0 | EZ38: =SUM(EZ37,EX38,-EY38) -> 0 | FH38: =SUM(FH37,FF38,-FG38) -> 0 | FP38: =SUM(FP37,FN38,-FO38) -> 0 | FX38: =SUM(FX37,FV38,-FW38) -> 0 | GF38: =SUM(GF37,GD38,-GE38) -> 0 | GN38: =SUM(GN37,GL38,-GM38) -> 0 | GV38: =SUM(GV37,GT38,-GU38) -> 0 | HD38: =SUM(HD37,HB38,-HC38) -> 0 | HL38: =SUM(HL37,HJ38,-HK38) -> 0 | HT38: =SUM(HT37,HR38,-HS38) -> 0 | IB38: =SUM(IB37,HZ38,-IA38) -> 0 | IJ38: =SUM(IJ37,IH38,-II38) -> 0 | IR38: =SUM(IR37,IP38,-IQ38) -> 0 | IZ38: =SUM(IZ37,IX38,-IY38) -> 0 | JH38: =SUM(JH37,JF38,-JG38) -> 0 | JP38: =SUM(JP37,JN38,-JO38) -> 0 | JX38: =SUM(JX37,JV38,-JW38) -> 0 | KF38: =SUM(KF37,KD38,-KE38) -> 0 | KN38: =SUM(KN37,KL38,-KM38) -> 0 | KV38: =SUM(KV37,KT38,-KU38) -> 0 | LD38: =SUM(LD37,LB38,-LC38) -> 0 | LL38: =SUM(LL37,LJ38,-LK38) -> 0 | LT38: =SUM(LT37,LR38,-LS38) -> 0 | MB38: =SUM(MB37,LZ38,-MA38) -> 0 | MJ38: =SUM(MJ37,MH38,-MI38) -> 0 | MR38: =SUM(MR37,MP38,-MQ38) -> 0 | MZ38: =SUM(MZ37,MX38,-MY38) -> 0 | NH38: =SUM(NH37,NF38,-NG38) -> 0 | NP38: =SUM(NP37,NN38,-NO38) -> 0 | NX38: =SUM(NX37,NV38,-NW38) -> 0 | OF38: =SUM(OF37,OD38,-OE38) -> 0 | ON38: =SUM(ON37,OL38,-OM38) -> 0 | OV38: =SUM(OV37,OT38,-OU38) -> 0 | PD38: =SUM(PD37,PB38,-PC38) -> 0 | PL38: =SUM(PL37,PJ38,-PK38) -> 0 | PT38: =SUM(PT37,PR38,-PS38) -> 0 | QB38: =SUM(QB37,PZ38,-QA38) -> 0 | QJ38: =SUM(QJ37,QH38,-QI38) -> 0 | QR38: =SUM(QR37,QP38,-QQ38) -> 0 | QZ38: =SUM(QZ37,QX38,-QY38) -> 0 | RH38: =SUM(RH37,RF38,-RG38) -> 0 | RP38: =SUM(RP37,RN38,-RO38) -> 0 | RX38: =SUM(RX37,RV38,-RW38) -> 0 | SF38: =SUM(SF37,SD38,-SE38) -> 0 | SN38: =SUM(SN37,SL38,-SM38) -> 0 | SV38: =SUM(SV37,ST38,-SU38) -> 0 | TD38: =SUM(TD37,TB38,-TC38) -> 0 | TL38: =SUM(TL37,TJ38,-TK38) -> 0 | TT38: =SUM(TT37,TR38,-TS38) -> 0 | UB38: =SUM(UB37,TZ38,-UA38) -> 0 | UJ38: =SUM(UJ37,UH38,-UI38) -> 0 | UR38: =SUM(UR37,UP38,-UQ38) -> 0 | UZ38: =SUM(UZ37,UX38,-UY38) -> 0 | VH38: =SUM(VH37,VF38,-VG38) -> 0 | VP38: =SUM(VP37,VN38,-VO38) -> 0 | VX38: =SUM(VX37,VV38,-VW38) -> 0 | WF38: =SUM(WF37,WD38,-WE38) -> 0 | WN38: =SUM(WN37,WL38,-WM38) -> 0 | WV38: =SUM(WV37,WT38,-WU38) -> 0 | XD38: =SUM(XD37,XB38,-XC38) -> 0 | XL38: =SUM(XL37,XJ38,-XK38) -> 0 | XT38: =SUM(XT37,XR38,-XS38) -> 0 | YB38: =SUM(YB37,XZ38,-YA38) -> 0 | YJ38: =SUM(YJ37,YH38,-YI38) -> 0 | YR38: =SUM(YR37,YP38,-YQ38) -> 0 | YZ38: =SUM(YZ37,YX38,-YY38) -> 0 | ZH38: =SUM(ZH37,ZF38,-ZG38) -> 0 | ZP38: =SUM(ZP37,ZN38,-ZO38) -> 0 | ZX38: =SUM(ZX37,ZV38,-ZW38) -> 0 | AAF38: =SUM(AAF37,AAD38,-AAE38) -> 0 | AAN38: =SUM(AAN37,AAL38,-AAM38) -> 0 | AAV38: =SUM(AAV37,AAT38,-AAU38) -> 0 | ABD38: =SUM(ABD37,ABB38,-ABC38) -> 0 | ABL38: =SUM(ABL37,ABJ38,-ABK38) -> 0 | ABT38: =SUM(ABT37,ABR38,-ABS38) -> 0 | ACB38: =SUM(ACB37,ABZ38,-ACA38) -> 0
D39: =SUM(D38,B39,-C39) -> 1700 | L39: =SUM(L38,J39,-K39) -> 1000 | T39: =SUM(T38,R39,-S39) -> 4000 | AB39: =SUM(AB38,Z39,-AA39) -> 1000 | AJ39: =SUM(AJ38,AH39,-AI39) -> 2000 | AR39: =SUM(AR38,AP39,-AQ39) -> 1000 | AZ39: =SUM(AZ38,AX39,-AY39) -> 1150 | BH39: =SUM(BH38,BF39,-BG39) -> 7000 | BP39: =SUM(BP38,BN39,-BO39) -> 1000 | BX39: =SUM(BX38,BV39,-BW39) -> 0 | CF39: =SUM(CF38,CD39,-CE39) -> 0 | CN39: =SUM(CN38,CL39,-CM39) -> 0 | CV39: =SUM(CV38,CT39,-CU39) -> 0 | DD39: =SUM(DD38,DB39,-DC39) -> 0 | DL39: =SUM(DL38,DJ39,-DK39) -> 0 | DT39: =SUM(DT38,DR39,-DS39) -> 0 | EB39: =SUM(EB38,DZ39,-EA39) -> 0 | EJ39: =SUM(EJ38,EH39,-EI39) -> 0 | ER39: =SUM(ER38,EP39,-EQ39) -> 0 | EZ39: =SUM(EZ38,EX39,-EY39) -> 0 | FH39: =SUM(FH38,FF39,-FG39) -> 0 | FP39: =SUM(FP38,FN39,-FO39) -> 0 | FX39: =SUM(FX38,FV39,-FW39) -> 0 | GF39: =SUM(GF38,GD39,-GE39) -> 0 | GN39: =SUM(GN38,GL39,-GM39) -> 0 | GV39: =SUM(GV38,GT39,-GU39) -> 0 | HD39: =SUM(HD38,HB39,-HC39) -> 0 | HL39: =SUM(HL38,HJ39,-HK39) -> 0 | HT39: =SUM(HT38,HR39,-HS39) -> 0 | IB39: =SUM(IB38,HZ39,-IA39) -> 0 | IJ39: =SUM(IJ38,IH39,-II39) -> 0 | IR39: =SUM(IR38,IP39,-IQ39) -> 0 | IZ39: =SUM(IZ38,IX39,-IY39) -> 0 | JH39: =SUM(JH38,JF39,-JG39) -> 0 | JP39: =SUM(JP38,JN39,-JO39) -> 0 | JX39: =SUM(JX38,JV39,-JW39) -> 0 | KF39: =SUM(KF38,KD39,-KE39) -> 0 | KN39: =SUM(KN38,KL39,-KM39) -> 0 | KV39: =SUM(KV38,KT39,-KU39) -> 0 | LD39: =SUM(LD38,LB39,-LC39) -> 0 | LL39: =SUM(LL38,LJ39,-LK39) -> 0 | LT39: =SUM(LT38,LR39,-LS39) -> 0 | MB39: =SUM(MB38,LZ39,-MA39) -> 0 | MJ39: =SUM(MJ38,MH39,-MI39) -> 0 | MR39: =SUM(MR38,MP39,-MQ39) -> 0 | MZ39: =SUM(MZ38,MX39,-MY39) -> 0 | NH39: =SUM(NH38,NF39,-NG39) -> 0 | NP39: =SUM(NP38,NN39,-NO39) -> 0 | NX39: =SUM(NX38,NV39,-NW39) -> 0 | OF39: =SUM(OF38,OD39,-OE39) -> 0 | ON39: =SUM(ON38,OL39,-OM39) -> 0 | OV39: =SUM(OV38,OT39,-OU39) -> 0 | PD39: =SUM(PD38,PB39,-PC39) -> 0 | PL39: =SUM(PL38,PJ39,-PK39) -> 0 | PT39: =SUM(PT38,PR39,-PS39) -> 0 | QB39: =SUM(QB38,PZ39,-QA39) -> 0 | QJ39: =SUM(QJ38,QH39,-QI39) -> 0 | QR39: =SUM(QR38,QP39,-QQ39) -> 0 | QZ39: =SUM(QZ38,QX39,-QY39) -> 0 | RH39: =SUM(RH38,RF39,-RG39) -> 0 | RP39: =SUM(RP38,RN39,-RO39) -> 0 | RX39: =SUM(RX38,RV39,-RW39) -> 0 | SF39: =SUM(SF38,SD39,-SE39) -> 0 | SN39: =SUM(SN38,SL39,-SM39) -> 0 | SV39: =SUM(SV38,ST39,-SU39) -> 0 | TD39: =SUM(TD38,TB39,-TC39) -> 0 | TL39: =SUM(TL38,TJ39,-TK39) -> 0 | TT39: =SUM(TT38,TR39,-TS39) -> 0 | UB39: =SUM(UB38,TZ39,-UA39) -> 0 | UJ39: =SUM(UJ38,UH39,-UI39) -> 0 | UR39: =SUM(UR38,UP39,-UQ39) -> 0 | UZ39: =SUM(UZ38,UX39,-UY39) -> 0 | VH39: =SUM(VH38,VF39,-VG39) -> 0 | VP39: =SUM(VP38,VN39,-VO39) -> 0 | VX39: =SUM(VX38,VV39,-VW39) -> 0 | WF39: =SUM(WF38,WD39,-WE39) -> 0 | WN39: =SUM(WN38,WL39,-WM39) -> 0 | WV39: =SUM(WV38,WT39,-WU39) -> 0 | XD39: =SUM(XD38,XB39,-XC39) -> 0 | XL39: =SUM(XL38,XJ39,-XK39) -> 0 | XT39: =SUM(XT38,XR39,-XS39) -> 0 | YB39: =SUM(YB38,XZ39,-YA39) -> 0 | YJ39: =SUM(YJ38,YH39,-YI39) -> 0 | YR39: =SUM(YR38,YP39,-YQ39) -> 0 | YZ39: =SUM(YZ38,YX39,-YY39) -> 0 | ZH39: =SUM(ZH38,ZF39,-ZG39) -> 0 | ZP39: =SUM(ZP38,ZN39,-ZO39) -> 0 | ZX39: =SUM(ZX38,ZV39,-ZW39) -> 0 | AAF39: =SUM(AAF38,AAD39,-AAE39) -> 0 | AAN39: =SUM(AAN38,AAL39,-AAM39) -> 0 | AAV39: =SUM(AAV38,AAT39,-AAU39) -> 0 | ABD39: =SUM(ABD38,ABB39,-ABC39) -> 0 | ABL39: =SUM(ABL38,ABJ39,-ABK39) -> 0 | ABT39: =SUM(ABT38,ABR39,-ABS39) -> 0 | ACB39: =SUM(ACB38,ABZ39,-ACA39) -> 0
D40: =SUM(D39,B40,-C40) -> 1700 | L40: =SUM(L39,J40,-K40) -> 1000 | T40: =SUM(T39,R40,-S40) -> 4000 | AB40: =SUM(AB39,Z40,-AA40) -> 1000 | AJ40: =SUM(AJ39,AH40,-AI40) -> 2000 | AR40: =SUM(AR39,AP40,-AQ40) -> 1000 | AZ40: =SUM(AZ39,AX40,-AY40) -> 1150 | BH40: =SUM(BH39,BF40,-BG40) -> 7000 | BP40: =SUM(BP39,BN40,-BO40) -> 1000 | BX40: =SUM(BX39,BV40,-BW40) -> 0 | CF40: =SUM(CF39,CD40,-CE40) -> 0 | CN40: =SUM(CN39,CL40,-CM40) -> 0 | CV40: =SUM(CV39,CT40,-CU40) -> 0 | DD40: =SUM(DD39,DB40,-DC40) -> 0 | DL40: =SUM(DL39,DJ40,-DK40) -> 0 | DT40: =SUM(DT39,DR40,-DS40) -> 0 | EB40: =SUM(EB39,DZ40,-EA40) -> 0 | EJ40: =SUM(EJ39,EH40,-EI40) -> 0 | ER40: =SUM(ER39,EP40,-EQ40) -> 0 | EZ40: =SUM(EZ39,EX40,-EY40) -> 0 | FH40: =SUM(FH39,FF40,-FG40) -> 0 | FP40: =SUM(FP39,FN40,-FO40) -> 0 | FX40: =SUM(FX39,FV40,-FW40) -> 0 | GF40: =SUM(GF39,GD40,-GE40) -> 0 | GN40: =SUM(GN39,GL40,-GM40) -> 0 | GV40: =SUM(GV39,GT40,-GU40) -> 0 | HD40: =SUM(HD39,HB40,-HC40) -> 0 | HL40: =SUM(HL39,HJ40,-HK40) -> 0 | HT40: =SUM(HT39,HR40,-HS40) -> 0 | IB40: =SUM(IB39,HZ40,-IA40) -> 0 | IJ40: =SUM(IJ39,IH40,-II40) -> 0 | IR40: =SUM(IR39,IP40,-IQ40) -> 0 | IZ40: =SUM(IZ39,IX40,-IY40) -> 0 | JH40: =SUM(JH39,JF40,-JG40) -> 0 | JP40: =SUM(JP39,JN40,-JO40) -> 0 | JX40: =SUM(JX39,JV40,-JW40) -> 0 | KF40: =SUM(KF39,KD40,-KE40) -> 0 | KN40: =SUM(KN39,KL40,-KM40) -> 0 | KV40: =SUM(KV39,KT40,-KU40) -> 0 | LD40: =SUM(LD39,LB40,-LC40) -> 0 | LL40: =SUM(LL39,LJ40,-LK40) -> 0 | LT40: =SUM(LT39,LR40,-LS40) -> 0 | MB40: =SUM(MB39,LZ40,-MA40) -> 0 | MJ40: =SUM(MJ39,MH40,-MI40) -> 0 | MR40: =SUM(MR39,MP40,-MQ40) -> 0 | MZ40: =SUM(MZ39,MX40,-MY40) -> 0 | NH40: =SUM(NH39,NF40,-NG40) -> 0 | NP40: =SUM(NP39,NN40,-NO40) -> 0 | NX40: =SUM(NX39,NV40,-NW40) -> 0 | OF40: =SUM(OF39,OD40,-OE40) -> 0 | ON40: =SUM(ON39,OL40,-OM40) -> 0 | OV40: =SUM(OV39,OT40,-OU40) -> 0 | PD40: =SUM(PD39,PB40,-PC40) -> 0 | PL40: =SUM(PL39,PJ40,-PK40) -> 0 | PT40: =SUM(PT39,PR40,-PS40) -> 0 | QB40: =SUM(QB39,PZ40,-QA40) -> 0 | QJ40: =SUM(QJ39,QH40,-QI40) -> 0 | QR40: =SUM(QR39,QP40,-QQ40) -> 0 | QZ40: =SUM(QZ39,QX40,-QY40) -> 0 | RH40: =SUM(RH39,RF40,-RG40) -> 0 | RP40: =SUM(RP39,RN40,-RO40) -> 0 | RX40: =SUM(RX39,RV40,-RW40) -> 0 | SF40: =SUM(SF39,SD40,-SE40) -> 0 | SN40: =SUM(SN39,SL40,-SM40) -> 0 | SV40: =SUM(SV39,ST40,-SU40) -> 0 | TD40: =SUM(TD39,TB40,-TC40) -> 0 | TL40: =SUM(TL39,TJ40,-TK40) -> 0 | TT40: =SUM(TT39,TR40,-TS40) -> 0 | UB40: =SUM(UB39,TZ40,-UA40) -> 0 | UJ40: =SUM(UJ39,UH40,-UI40) -> 0 | UR40: =SUM(UR39,UP40,-UQ40) -> 0 | UZ40: =SUM(UZ39,UX40,-UY40) -> 0 | VH40: =SUM(VH39,VF40,-VG40) -> 0 | VP40: =SUM(VP39,VN40,-VO40) -> 0 | VX40: =SUM(VX39,VV40,-VW40) -> 0 | WF40: =SUM(WF39,WD40,-WE40) -> 0 | WN40: =SUM(WN39,WL40,-WM40) -> 0 | WV40: =SUM(WV39,WT40,-WU40) -> 0 | XD40: =SUM(XD39,XB40,-XC40) -> 0 | XL40: =SUM(XL39,XJ40,-XK40) -> 0 | XT40: =SUM(XT39,XR40,-XS40) -> 0 | YB40: =SUM(YB39,XZ40,-YA40) -> 0 | YJ40: =SUM(YJ39,YH40,-YI40) -> 0 | YR40: =SUM(YR39,YP40,-YQ40) -> 0 | YZ40: =SUM(YZ39,YX40,-YY40) -> 0 | ZH40: =SUM(ZH39,ZF40,-ZG40) -> 0 | ZP40: =SUM(ZP39,ZN40,-ZO40) -> 0 | ZX40: =SUM(ZX39,ZV40,-ZW40) -> 0 | AAF40: =SUM(AAF39,AAD40,-AAE40) -> 0 | AAN40: =SUM(AAN39,AAL40,-AAM40) -> 0 | AAV40: =SUM(AAV39,AAT40,-AAU40) -> 0 | ABD40: =SUM(ABD39,ABB40,-ABC40) -> 0 | ABL40: =SUM(ABL39,ABJ40,-ABK40) -> 0 | ABT40: =SUM(ABT39,ABR40,-ABS40) -> 0 | ACB40: =SUM(ACB39,ABZ40,-ACA40) -> 0
D41: =SUM(D40,B41,-C41) -> 1700 | L41: =SUM(L40,J41,-K41) -> 1000 | T41: =SUM(T40,R41,-S41) -> 4000 | AB41: =SUM(AB40,Z41,-AA41) -> 1000 | AJ41: =SUM(AJ40,AH41,-AI41) -> 2000 | AR41: =SUM(AR40,AP41,-AQ41) -> 1000 | AZ41: =SUM(AZ40,AX41,-AY41) -> 1150 | BH41: =SUM(BH40,BF41,-BG41) -> 7000 | BP41: =SUM(BP40,BN41,-BO41) -> 1000 | BX41: =SUM(BX40,BV41,-BW41) -> 0 | CF41: =SUM(CF40,CD41,-CE41) -> 0 | CN41: =SUM(CN40,CL41,-CM41) -> 0 | CV41: =SUM(CV40,CT41,-CU41) -> 0 | DD41: =SUM(DD40,DB41,-DC41) -> 0 | DL41: =SUM(DL40,DJ41,-DK41) -> 0 | DT41: =SUM(DT40,DR41,-DS41) -> 0 | EB41: =SUM(EB40,DZ41,-EA41) -> 0 | EJ41: =SUM(EJ40,EH41,-EI41) -> 0 | ER41: =SUM(ER40,EP41,-EQ41) -> 0 | EZ41: =SUM(EZ40,EX41,-EY41) -> 0 | FH41: =SUM(FH40,FF41,-FG41) -> 0 | FP41: =SUM(FP40,FN41,-FO41) -> 0 | FX41: =SUM(FX40,FV41,-FW41) -> 0 | GF41: =SUM(GF40,GD41,-GE41) -> 0 | GN41: =SUM(GN40,GL41,-GM41) -> 0 | GV41: =SUM(GV40,GT41,-GU41) -> 0 | HD41: =SUM(HD40,HB41,-HC41) -> 0 | HL41: =SUM(HL40,HJ41,-HK41) -> 0 | HT41: =SUM(HT40,HR41,-HS41) -> 0 | IB41: =SUM(IB40,HZ41,-IA41) -> 0 | IJ41: =SUM(IJ40,IH41,-II41) -> 0 | IR41: =SUM(IR40,IP41,-IQ41) -> 0 | IZ41: =SUM(IZ40,IX41,-IY41) -> 0 | JH41: =SUM(JH40,JF41,-JG41) -> 0 | JP41: =SUM(JP40,JN41,-JO41) -> 0 | JX41: =SUM(JX40,JV41,-JW41) -> 0 | KF41: =SUM(KF40,KD41,-KE41) -> 0 | KN41: =SUM(KN40,KL41,-KM41) -> 0 | KV41: =SUM(KV40,KT41,-KU41) -> 0 | LD41: =SUM(LD40,LB41,-LC41) -> 0 | LL41: =SUM(LL40,LJ41,-LK41) -> 0 | LT41: =SUM(LT40,LR41,-LS41) -> 0 | MB41: =SUM(MB40,LZ41,-MA41) -> 0 | MJ41: =SUM(MJ40,MH41,-MI41) -> 0 | MR41: =SUM(MR40,MP41,-MQ41) -> 0 | MZ41: =SUM(MZ40,MX41,-MY41) -> 0 | NH41: =SUM(NH40,NF41,-NG41) -> 0 | NP41: =SUM(NP40,NN41,-NO41) -> 0 | NX41: =SUM(NX40,NV41,-NW41) -> 0 | OF41: =SUM(OF40,OD41,-OE41) -> 0 | ON41: =SUM(ON40,OL41,-OM41) -> 0 | OV41: =SUM(OV40,OT41,-OU41) -> 0 | PD41: =SUM(PD40,PB41,-PC41) -> 0 | PL41: =SUM(PL40,PJ41,-PK41) -> 0 | PT41: =SUM(PT40,PR41,-PS41) -> 0 | QB41: =SUM(QB40,PZ41,-QA41) -> 0 | QJ41: =SUM(QJ40,QH41,-QI41) -> 0 | QR41: =SUM(QR40,QP41,-QQ41) -> 0 | QZ41: =SUM(QZ40,QX41,-QY41) -> 0 | RH41: =SUM(RH40,RF41,-RG41) -> 0 | RP41: =SUM(RP40,RN41,-RO41) -> 0 | RX41: =SUM(RX40,RV41,-RW41) -> 0 | SF41: =SUM(SF40,SD41,-SE41) -> 0 | SN41: =SUM(SN40,SL41,-SM41) -> 0 | SV41: =SUM(SV40,ST41,-SU41) -> 0 | TD41: =SUM(TD40,TB41,-TC41) -> 0 | TL41: =SUM(TL40,TJ41,-TK41) -> 0 | TT41: =SUM(TT40,TR41,-TS41) -> 0 | UB41: =SUM(UB40,TZ41,-UA41) -> 0 | UJ41: =SUM(UJ40,UH41,-UI41) -> 0 | UR41: =SUM(UR40,UP41,-UQ41) -> 0 | UZ41: =SUM(UZ40,UX41,-UY41) -> 0 | VH41: =SUM(VH40,VF41,-VG41) -> 0 | VP41: =SUM(VP40,VN41,-VO41) -> 0 | VX41: =SUM(VX40,VV41,-VW41) -> 0 | WF41: =SUM(WF40,WD41,-WE41) -> 0 | WN41: =SUM(WN40,WL41,-WM41) -> 0 | WV41: =SUM(WV40,WT41,-WU41) -> 0 | XD41: =SUM(XD40,XB41,-XC41) -> 0 | XL41: =SUM(XL40,XJ41,-XK41) -> 0 | XT41: =SUM(XT40,XR41,-XS41) -> 0 | YB41: =SUM(YB40,XZ41,-YA41) -> 0 | YJ41: =SUM(YJ40,YH41,-YI41) -> 0 | YR41: =SUM(YR40,YP41,-YQ41) -> 0 | YZ41: =SUM(YZ40,YX41,-YY41) -> 0 | ZH41: =SUM(ZH40,ZF41,-ZG41) -> 0 | ZP41: =SUM(ZP40,ZN41,-ZO41) -> 0 | ZX41: =SUM(ZX40,ZV41,-ZW41) -> 0 | AAF41: =SUM(AAF40,AAD41,-AAE41) -> 0 | AAN41: =SUM(AAN40,AAL41,-AAM41) -> 0 | AAV41: =SUM(AAV40,AAT41,-AAU41) -> 0 | ABD41: =SUM(ABD40,ABB41,-ABC41) -> 0 | ABL41: =SUM(ABL40,ABJ41,-ABK41) -> 0 | ABT41: =SUM(ABT40,ABR41,-ABS41) -> 0 | ACB41: =SUM(ACB40,ABZ41,-ACA41) -> 0
D42: =SUM(D41,B42,-C42) -> 1700 | L42: =SUM(L41,J42,-K42) -> 1000 | T42: =SUM(T41,R42,-S42) -> 4000 | AB42: =SUM(AB41,Z42,-AA42) -> 1000 | AJ42: =SUM(AJ41,AH42,-AI42) -> 2000 | AR42: =SUM(AR41,AP42,-AQ42) -> 1000 | AZ42: =SUM(AZ41,AX42,-AY42) -> 1150 | BH42: =SUM(BH41,BF42,-BG42) -> 7000 | BP42: =SUM(BP41,BN42,-BO42) -> 1000 | BX42: =SUM(BX41,BV42,-BW42) -> 0 | CF42: =SUM(CF41,CD42,-CE42) -> 0 | CN42: =SUM(CN41,CL42,-CM42) -> 0 | CV42: =SUM(CV41,CT42,-CU42) -> 0 | DD42: =SUM(DD41,DB42,-DC42) -> 0 | DL42: =SUM(DL41,DJ42,-DK42) -> 0 | DT42: =SUM(DT41,DR42,-DS42) -> 0 | EB42: =SUM(EB41,DZ42,-EA42) -> 0 | EJ42: =SUM(EJ41,EH42,-EI42) -> 0 | ER42: =SUM(ER41,EP42,-EQ42) -> 0 | EZ42: =SUM(EZ41,EX42,-EY42) -> 0 | FH42: =SUM(FH41,FF42,-FG42) -> 0 | FP42: =SUM(FP41,FN42,-FO42) -> 0 | FX42: =SUM(FX41,FV42,-FW42) -> 0 | GF42: =SUM(GF41,GD42,-GE42) -> 0 | GN42: =SUM(GN41,GL42,-GM42) -> 0 | GV42: =SUM(GV41,GT42,-GU42) -> 0 | HD42: =SUM(HD41,HB42,-HC42) -> 0 | HL42: =SUM(HL41,HJ42,-HK42) -> 0 | HT42: =SUM(HT41,HR42,-HS42) -> 0 | IB42: =SUM(IB41,HZ42,-IA42) -> 0 | IJ42: =SUM(IJ41,IH42,-II42) -> 0 | IR42: =SUM(IR41,IP42,-IQ42) -> 0 | IZ42: =SUM(IZ41,IX42,-IY42) -> 0 | JH42: =SUM(JH41,JF42,-JG42) -> 0 | JP42: =SUM(JP41,JN42,-JO42) -> 0 | JX42: =SUM(JX41,JV42,-JW42) -> 0 | KF42: =SUM(KF41,KD42,-KE42) -> 0 | KN42: =SUM(KN41,KL42,-KM42) -> 0 | KV42: =SUM(KV41,KT42,-KU42) -> 0 | LD42: =SUM(LD41,LB42,-LC42) -> 0 | LL42: =SUM(LL41,LJ42,-LK42) -> 0 | LT42: =SUM(LT41,LR42,-LS42) -> 0 | MB42: =SUM(MB41,LZ42,-MA42) -> 0 | MJ42: =SUM(MJ41,MH42,-MI42) -> 0 | MR42: =SUM(MR41,MP42,-MQ42) -> 0 | MZ42: =SUM(MZ41,MX42,-MY42) -> 0 | NH42: =SUM(NH41,NF42,-NG42) -> 0 | NP42: =SUM(NP41,NN42,-NO42) -> 0 | NX42: =SUM(NX41,NV42,-NW42) -> 0 | OF42: =SUM(OF41,OD42,-OE42) -> 0 | ON42: =SUM(ON41,OL42,-OM42) -> 0 | OV42: =SUM(OV41,OT42,-OU42) -> 0 | PD42: =SUM(PD41,PB42,-PC42) -> 0 | PL42: =SUM(PL41,PJ42,-PK42) -> 0 | PT42: =SUM(PT41,PR42,-PS42) -> 0 | QB42: =SUM(QB41,PZ42,-QA42) -> 0 | QJ42: =SUM(QJ41,QH42,-QI42) -> 0 | QR42: =SUM(QR41,QP42,-QQ42) -> 0 | QZ42: =SUM(QZ41,QX42,-QY42) -> 0 | RH42: =SUM(RH41,RF42,-RG42) -> 0 | RP42: =SUM(RP41,RN42,-RO42) -> 0 | RX42: =SUM(RX41,RV42,-RW42) -> 0 | SF42: =SUM(SF41,SD42,-SE42) -> 0 | SN42: =SUM(SN41,SL42,-SM42) -> 0 | SV42: =SUM(SV41,ST42,-SU42) -> 0 | TD42: =SUM(TD41,TB42,-TC42) -> 0 | TL42: =SUM(TL41,TJ42,-TK42) -> 0 | TT42: =SUM(TT41,TR42,-TS42) -> 0 | UB42: =SUM(UB41,TZ42,-UA42) -> 0 | UJ42: =SUM(UJ41,UH42,-UI42) -> 0 | UR42: =SUM(UR41,UP42,-UQ42) -> 0 | UZ42: =SUM(UZ41,UX42,-UY42) -> 0 | VH42: =SUM(VH41,VF42,-VG42) -> 0 | VP42: =SUM(VP41,VN42,-VO42) -> 0 | VX42: =SUM(VX41,VV42,-VW42) -> 0 | WF42: =SUM(WF41,WD42,-WE42) -> 0 | WN42: =SUM(WN41,WL42,-WM42) -> 0 | WV42: =SUM(WV41,WT42,-WU42) -> 0 | XD42: =SUM(XD41,XB42,-XC42) -> 0 | XL42: =SUM(XL41,XJ42,-XK42) -> 0 | XT42: =SUM(XT41,XR42,-XS42) -> 0 | YB42: =SUM(YB41,XZ42,-YA42) -> 0 | YJ42: =SUM(YJ41,YH42,-YI42) -> 0 | YR42: =SUM(YR41,YP42,-YQ42) -> 0 | YZ42: =SUM(YZ41,YX42,-YY42) -> 0 | ZH42: =SUM(ZH41,ZF42,-ZG42) -> 0 | ZP42: =SUM(ZP41,ZN42,-ZO42) -> 0 | ZX42: =SUM(ZX41,ZV42,-ZW42) -> 0 | AAF42: =SUM(AAF41,AAD42,-AAE42) -> 0 | AAN42: =SUM(AAN41,AAL42,-AAM42) -> 0 | AAV42: =SUM(AAV41,AAT42,-AAU42) -> 0 | ABD42: =SUM(ABD41,ABB42,-ABC42) -> 0 | ABL42: =SUM(ABL41,ABJ42,-ABK42) -> 0 | ABT42: =SUM(ABT41,ABR42,-ABS42) -> 0 | ACB42: =SUM(ACB41,ABZ42,-ACA42) -> 0
D43: =SUM(D42,B43,-C43) -> 1700 | L43: =SUM(L42,J43,-K43) -> 1000 | T43: =SUM(T42,R43,-S43) -> 4000 | AB43: =SUM(AB42,Z43,-AA43) -> 1000 | AJ43: =SUM(AJ42,AH43,-AI43) -> 2000 | AR43: =SUM(AR42,AP43,-AQ43) -> 1000 | AZ43: =SUM(AZ42,AX43,-AY43) -> 1150 | BH43: =SUM(BH42,BF43,-BG43) -> 7000 | BP43: =SUM(BP42,BN43,-BO43) -> 1000 | BX43: =SUM(BX42,BV43,-BW43) -> 0 | CF43: =SUM(CF42,CD43,-CE43) -> 0 | CN43: =SUM(CN42,CL43,-CM43) -> 0 | CV43: =SUM(CV42,CT43,-CU43) -> 0 | DD43: =SUM(DD42,DB43,-DC43) -> 0 | DL43: =SUM(DL42,DJ43,-DK43) -> 0 | DT43: =SUM(DT42,DR43,-DS43) -> 0 | EB43: =SUM(EB42,DZ43,-EA43) -> 0 | EJ43: =SUM(EJ42,EH43,-EI43) -> 0 | ER43: =SUM(ER42,EP43,-EQ43) -> 0 | EZ43: =SUM(EZ42,EX43,-EY43) -> 0 | FH43: =SUM(FH42,FF43,-FG43) -> 0 | FP43: =SUM(FP42,FN43,-FO43) -> 0 | FX43: =SUM(FX42,FV43,-FW43) -> 0 | GF43: =SUM(GF42,GD43,-GE43) -> 0 | GN43: =SUM(GN42,GL43,-GM43) -> 0 | GV43: =SUM(GV42,GT43,-GU43) -> 0 | HD43: =SUM(HD42,HB43,-HC43) -> 0 | HL43: =SUM(HL42,HJ43,-HK43) -> 0 | HT43: =SUM(HT42,HR43,-HS43) -> 0 | IB43: =SUM(IB42,HZ43,-IA43) -> 0 | IJ43: =SUM(IJ42,IH43,-II43) -> 0 | IR43: =SUM(IR42,IP43,-IQ43) -> 0 | IZ43: =SUM(IZ42,IX43,-IY43) -> 0 | JH43: =SUM(JH42,JF43,-JG43) -> 0 | JP43: =SUM(JP42,JN43,-JO43) -> 0 | JX43: =SUM(JX42,JV43,-JW43) -> 0 | KF43: =SUM(KF42,KD43,-KE43) -> 0 | KN43: =SUM(KN42,KL43,-KM43) -> 0 | KV43: =SUM(KV42,KT43,-KU43) -> 0 | LD43: =SUM(LD42,LB43,-LC43) -> 0 | LL43: =SUM(LL42,LJ43,-LK43) -> 0 | LT43: =SUM(LT42,LR43,-LS43) -> 0 | MB43: =SUM(MB42,LZ43,-MA43) -> 0 | MJ43: =SUM(MJ42,MH43,-MI43) -> 0 | MR43: =SUM(MR42,MP43,-MQ43) -> 0 | MZ43: =SUM(MZ42,MX43,-MY43) -> 0 | NH43: =SUM(NH42,NF43,-NG43) -> 0 | NP43: =SUM(NP42,NN43,-NO43) -> 0 | NX43: =SUM(NX42,NV43,-NW43) -> 0 | OF43: =SUM(OF42,OD43,-OE43) -> 0 | ON43: =SUM(ON42,OL43,-OM43) -> 0 | OV43: =SUM(OV42,OT43,-OU43) -> 0 | PD43: =SUM(PD42,PB43,-PC43) -> 0 | PL43: =SUM(PL42,PJ43,-PK43) -> 0 | PT43: =SUM(PT42,PR43,-PS43) -> 0 | QB43: =SUM(QB42,PZ43,-QA43) -> 0 | QJ43: =SUM(QJ42,QH43,-QI43) -> 0 | QR43: =SUM(QR42,QP43,-QQ43) -> 0 | QZ43: =SUM(QZ42,QX43,-QY43) -> 0 | RH43: =SUM(RH42,RF43,-RG43) -> 0 | RP43: =SUM(RP42,RN43,-RO43) -> 0 | RX43: =SUM(RX42,RV43,-RW43) -> 0 | SF43: =SUM(SF42,SD43,-SE43) -> 0 | SN43: =SUM(SN42,SL43,-SM43) -> 0 | SV43: =SUM(SV42,ST43,-SU43) -> 0 | TD43: =SUM(TD42,TB43,-TC43) -> 0 | TL43: =SUM(TL42,TJ43,-TK43) -> 0 | TT43: =SUM(TT42,TR43,-TS43) -> 0 | UB43: =SUM(UB42,TZ43,-UA43) -> 0 | UJ43: =SUM(UJ42,UH43,-UI43) -> 0 | UR43: =SUM(UR42,UP43,-UQ43) -> 0 | UZ43: =SUM(UZ42,UX43,-UY43) -> 0 | VH43: =SUM(VH42,VF43,-VG43) -> 0 | VP43: =SUM(VP42,VN43,-VO43) -> 0 | VX43: =SUM(VX42,VV43,-VW43) -> 0 | WF43: =SUM(WF42,WD43,-WE43) -> 0 | WN43: =SUM(WN42,WL43,-WM43) -> 0 | WV43: =SUM(WV42,WT43,-WU43) -> 0 | XD43: =SUM(XD42,XB43,-XC43) -> 0 | XL43: =SUM(XL42,XJ43,-XK43) -> 0 | XT43: =SUM(XT42,XR43,-XS43) -> 0 | YB43: =SUM(YB42,XZ43,-YA43) -> 0 | YJ43: =SUM(YJ42,YH43,-YI43) -> 0 | YR43: =SUM(YR42,YP43,-YQ43) -> 0 | YZ43: =SUM(YZ42,YX43,-YY43) -> 0 | ZH43: =SUM(ZH42,ZF43,-ZG43) -> 0 | ZP43: =SUM(ZP42,ZN43,-ZO43) -> 0 | ZX43: =SUM(ZX42,ZV43,-ZW43) -> 0 | AAF43: =SUM(AAF42,AAD43,-AAE43) -> 0 | AAN43: =SUM(AAN42,AAL43,-AAM43) -> 0 | AAV43: =SUM(AAV42,AAT43,-AAU43) -> 0 | ABD43: =SUM(ABD42,ABB43,-ABC43) -> 0 | ABL43: =SUM(ABL42,ABJ43,-ABK43) -> 0 | ABT43: =SUM(ABT42,ABR43,-ABS43) -> 0 | ACB43: =SUM(ACB42,ABZ43,-ACA43) -> 0
D44: =SUM(D43,B44,-C44) -> 1700 | L44: =SUM(L43,J44,-K44) -> 1000 | T44: =SUM(T43,R44,-S44) -> 4000 | AB44: =SUM(AB43,Z44,-AA44) -> 1000 | AJ44: =SUM(AJ43,AH44,-AI44) -> 2000 | AR44: =SUM(AR43,AP44,-AQ44) -> 1000 | AZ44: =SUM(AZ43,AX44,-AY44) -> 1150 | BH44: =SUM(BH43,BF44,-BG44) -> 7000 | BP44: =SUM(BP43,BN44,-BO44) -> 1000 | BX44: =SUM(BX43,BV44,-BW44) -> 0 | CF44: =SUM(CF43,CD44,-CE44) -> 0 | CN44: =SUM(CN43,CL44,-CM44) -> 0 | CV44: =SUM(CV43,CT44,-CU44) -> 0 | DD44: =SUM(DD43,DB44,-DC44) -> 0 | DL44: =SUM(DL43,DJ44,-DK44) -> 0 | DT44: =SUM(DT43,DR44,-DS44) -> 0 | EB44: =SUM(EB43,DZ44,-EA44) -> 0 | EJ44: =SUM(EJ43,EH44,-EI44) -> 0 | ER44: =SUM(ER43,EP44,-EQ44) -> 0 | EZ44: =SUM(EZ43,EX44,-EY44) -> 0 | FH44: =SUM(FH43,FF44,-FG44) -> 0 | FP44: =SUM(FP43,FN44,-FO44) -> 0 | FX44: =SUM(FX43,FV44,-FW44) -> 0 | GF44: =SUM(GF43,GD44,-GE44) -> 0 | GN44: =SUM(GN43,GL44,-GM44) -> 0 | GV44: =SUM(GV43,GT44,-GU44) -> 0 | HD44: =SUM(HD43,HB44,-HC44) -> 0 | HL44: =SUM(HL43,HJ44,-HK44) -> 0 | HT44: =SUM(HT43,HR44,-HS44) -> 0 | IB44: =SUM(IB43,HZ44,-IA44) -> 0 | IJ44: =SUM(IJ43,IH44,-II44) -> 0 | IR44: =SUM(IR43,IP44,-IQ44) -> 0 | IZ44: =SUM(IZ43,IX44,-IY44) -> 0 | JH44: =SUM(JH43,JF44,-JG44) -> 0 | JP44: =SUM(JP43,JN44,-JO44) -> 0 | JX44: =SUM(JX43,JV44,-JW44) -> 0 | KF44: =SUM(KF43,KD44,-KE44) -> 0 | KN44: =SUM(KN43,KL44,-KM44) -> 0 | KV44: =SUM(KV43,KT44,-KU44) -> 0 | LD44: =SUM(LD43,LB44,-LC44) -> 0 | LL44: =SUM(LL43,LJ44,-LK44) -> 0 | LT44: =SUM(LT43,LR44,-LS44) -> 0 | MB44: =SUM(MB43,LZ44,-MA44) -> 0 | MJ44: =SUM(MJ43,MH44,-MI44) -> 0 | MR44: =SUM(MR43,MP44,-MQ44) -> 0 | MZ44: =SUM(MZ43,MX44,-MY44) -> 0 | NH44: =SUM(NH43,NF44,-NG44) -> 0 | NP44: =SUM(NP43,NN44,-NO44) -> 0 | NX44: =SUM(NX43,NV44,-NW44) -> 0 | OF44: =SUM(OF43,OD44,-OE44) -> 0 | ON44: =SUM(ON43,OL44,-OM44) -> 0 | OV44: =SUM(OV43,OT44,-OU44) -> 0 | PD44: =SUM(PD43,PB44,-PC44) -> 0 | PL44: =SUM(PL43,PJ44,-PK44) -> 0 | PT44: =SUM(PT43,PR44,-PS44) -> 0 | QB44: =SUM(QB43,PZ44,-QA44) -> 0 | QJ44: =SUM(QJ43,QH44,-QI44) -> 0 | QR44: =SUM(QR43,QP44,-QQ44) -> 0 | QZ44: =SUM(QZ43,QX44,-QY44) -> 0 | RH44: =SUM(RH43,RF44,-RG44) -> 0 | RP44: =SUM(RP43,RN44,-RO44) -> 0 | RX44: =SUM(RX43,RV44,-RW44) -> 0 | SF44: =SUM(SF43,SD44,-SE44) -> 0 | SN44: =SUM(SN43,SL44,-SM44) -> 0 | SV44: =SUM(SV43,ST44,-SU44) -> 0 | TD44: =SUM(TD43,TB44,-TC44) -> 0 | TL44: =SUM(TL43,TJ44,-TK44) -> 0 | TT44: =SUM(TT43,TR44,-TS44) -> 0 | UB44: =SUM(UB43,TZ44,-UA44) -> 0 | UJ44: =SUM(UJ43,UH44,-UI44) -> 0 | UR44: =SUM(UR43,UP44,-UQ44) -> 0 | UZ44: =SUM(UZ43,UX44,-UY44) -> 0 | VH44: =SUM(VH43,VF44,-VG44) -> 0 | VP44: =SUM(VP43,VN44,-VO44) -> 0 | VX44: =SUM(VX43,VV44,-VW44) -> 0 | WF44: =SUM(WF43,WD44,-WE44) -> 0 | WN44: =SUM(WN43,WL44,-WM44) -> 0 | WV44: =SUM(WV43,WT44,-WU44) -> 0 | XD44: =SUM(XD43,XB44,-XC44) -> 0 | XL44: =SUM(XL43,XJ44,-XK44) -> 0 | XT44: =SUM(XT43,XR44,-XS44) -> 0 | YB44: =SUM(YB43,XZ44,-YA44) -> 0 | YJ44: =SUM(YJ43,YH44,-YI44) -> 0 | YR44: =SUM(YR43,YP44,-YQ44) -> 0 | YZ44: =SUM(YZ43,YX44,-YY44) -> 0 | ZH44: =SUM(ZH43,ZF44,-ZG44) -> 0 | ZP44: =SUM(ZP43,ZN44,-ZO44) -> 0 | ZX44: =SUM(ZX43,ZV44,-ZW44) -> 0 | AAF44: =SUM(AAF43,AAD44,-AAE44) -> 0 | AAN44: =SUM(AAN43,AAL44,-AAM44) -> 0 | AAV44: =SUM(AAV43,AAT44,-AAU44) -> 0 | ABD44: =SUM(ABD43,ABB44,-ABC44) -> 0 | ABL44: =SUM(ABL43,ABJ44,-ABK44) -> 0 | ABT44: =SUM(ABT43,ABR44,-ABS44) -> 0 | ACB44: =SUM(ACB43,ABZ44,-ACA44) -> 0
... D55: =SUM(D54,B55,-C55) -> 1700 | L55: =SUM(L54,J55,-K55) -> 1000 | T55: =SUM(T54,R55,-S55) -> 4000 | AB55: =SUM(AB54,Z55,-AA55) -> 1000 | AJ55: =SUM(AJ54,AH55,-AI55) -> 2000 | AR55: =SUM(AR54,AP55,-AQ55) -> 1000 | AZ55: =SUM(AZ54,AX55,-AY55) -> 1150 | BH55: =SUM(BH54,BF55,-BG55) -> 7000 | BP55: =SUM(BP54,BN55,-BO55) -> 1000 | BX55: =SUM(BX54,BV55,-BW55) -> 0 | CF55: =SUM(CF54,CD55,-CE55) -> 0 | CN55: =SUM(CN54,CL55,-CM55) -> 0 | CV55: =SUM(CV54,CT55,-CU55) -> 0 | DD55: =SUM(DD54,DB55,-DC55) -> 0 | DL55: =SUM(DL54,DJ55,-DK55) -> 0 | DT55: =SUM(DT54,DR55,-DS55) -> 0 | EB55: =SUM(EB54,DZ55,-EA55) -> 0 | EJ55: =SUM(EJ54,EH55,-EI55) -> 0 | ER55: =SUM(ER54,EP55,-EQ55) -> 0 | EZ55: =SUM(EZ54,EX55,-EY55) -> 0 | FH55: =SUM(FH54,FF55,-FG55) -> 0 | FP55: =SUM(FP54,FN55,-FO55) -> 0 | FX55: =SUM(FX54,FV55,-FW55) -> 0 | GF55: =SUM(GF54,GD55,-GE55) -> 0 | GN55: =SUM(GN54,GL55,-GM55) -> 0 | GV55: =SUM(GV54,GT55,-GU55) -> 0 | HD55: =SUM(HD54,HB55,-HC55) -> 0 | HL55: =SUM(HL54,HJ55,-HK55) -> 0 | HT55: =SUM(HT54,HR55,-HS55) -> 0 | IB55: =SUM(IB54,HZ55,-IA55) -> 0 | IJ55: =SUM(IJ54,IH55,-II55) -> 0 | IR55: =SUM(IR54,IP55,-IQ55) -> 0 | IZ55: =SUM(IZ54,IX55,-IY55) -> 0 | JH55: =SUM(JH54,JF55,-JG55) -> 0 | JP55: =SUM(JP54,JN55,-JO55) -> 0 | JX55: =SUM(JX54,JV55,-JW55) -> 0 | KF55: =SUM(KF54,KD55,-KE55) -> 0 | KN55: =SUM(KN54,KL55,-KM55) -> 0 | KV55: =SUM(KV54,KT55,-KU55) -> 0 | LD55: =SUM(LD54,LB55,-LC55) -> 0 | LL55: =SUM(LL54,LJ55,-LK55) -> 0 | LT55: =SUM(LT54,LR55,-LS55) -> 0 | MB55: =SUM(MB54,LZ55,-MA55) -> 0 | MJ55: =SUM(MJ54,MH55,-MI55) -> 0 | MR55: =SUM(MR54,MP55,-MQ55) -> 0 | MZ55: =SUM(MZ54,MX55,-MY55) -> 0 | NH55: =SUM(NH54,NF55,-NG55) -> 0 | NP55: =SUM(NP54,NN55,-NO55) -> 0 | NX55: =SUM(NX54,NV55,-NW55) -> 0 | OF55: =SUM(OF54,OD55,-OE55) -> 0 | ON55: =SUM(ON54,OL55,-OM55) -> 0 | OV55: =SUM(OV54,OT55,-OU55) -> 0 | PD55: =SUM(PD54,PB55,-PC55) -> 0 | PL55: =SUM(PL54,PJ55,-PK55) -> 0 | PT55: =SUM(PT54,PR55,-PS55) -> 0 | QB55: =SUM(QB54,PZ55,-QA55) -> 0 | QJ55: =SUM(QJ54,QH55,-QI55) -> 0 | QR55: =SUM(QR54,QP55,-QQ55) -> 0 | QZ55: =SUM(QZ54,QX55,-QY55) -> 0 | RH55: =SUM(RH54,RF55,-RG55) -> 0 | RP55: =SUM(RP54,RN55,-RO55) -> 0 | RX55: =SUM(RX54,RV55,-RW55) -> 0 | SF55: =SUM(SF54,SD55,-SE55) -> 0 | SN55: =SUM(SN54,SL55,-SM55) -> 0 | SV55: =SUM(SV54,ST55,-SU55) -> 0 | TD55: =SUM(TD54,TB55,-TC55) -> 0 | TL55: =SUM(TL54,TJ55,-TK55) -> 0 | TT55: =SUM(TT54,TR55,-TS55) -> 0 | UB55: =SUM(UB54,TZ55,-UA55) -> 0 | UJ55: =SUM(UJ54,UH55,-UI55) -> 0 | UR55: =SUM(UR54,UP55,-UQ55) -> 0 | UZ55: =SUM(UZ54,UX55,-UY55) -> 0 | VH55: =SUM(VH54,VF55,-VG55) -> 0 | VP55: =SUM(VP54,VN55,-VO55) -> 0 | VX55: =SUM(VX54,VV55,-VW55) -> 0 | WF55: =SUM(WF54,WD55,-WE55) -> 0 | WN55: =SUM(WN54,WL55,-WM55) -> 0 | WV55: =SUM(WV54,WT55,-WU55) -> 0 | XD55: =SUM(XD54,XB55,-XC55) -> 0 | XL55: =SUM(XL54,XJ55,-XK55) -> 0 | XT55: =SUM(XT54,XR55,-XS55) -> 0 | YB55: =SUM(YB54,XZ55,-YA55) -> 0 | YJ55: =SUM(YJ54,YH55,-YI55) -> 0 | YR55: =SUM(YR54,YP55,-YQ55) -> 0 | YZ55: =SUM(YZ54,YX55,-YY55) -> 0 | ZH55: =SUM(ZH54,ZF55,-ZG55) -> 0 | ZP55: =SUM(ZP54,ZN55,-ZO55) -> 0 | ZX55: =SUM(ZX54,ZV55,-ZW55) -> 0 | AAF55: =SUM(AAF54,AAD55,-AAE55) -> 0 | AAN55: =SUM(AAN54,AAL55,-AAM55) -> 0 | AAV55: =SUM(AAV54,AAT55,-AAU55) -> 0 | ABD55: =SUM(ABD54,ABB55,-ABC55) -> 0 | ABL55: =SUM(ABL54,ABJ55,-ABK55) -> 0 | ABT55: =SUM(ABT54,ABR55,-ABS55) -> 0 | ACB55: =SUM(ACB54,ABZ55,-ACA55) -> 0
C56: TOTAL | D56: =D55 -> 1700 | F56: =SUM(F8:F55) -> 100 | G56: =SUM(G8:G55) -> 0 | L56: =L55 -> 1000 | N56: =SUM(N8:N55) -> 24 | O56: =SUM(O8:O55) -> 0 | S56: TOTAL | T56: =T55 -> 4000 | V56: =SUM(V8:V55) -> 84 | W56: =SUM(W8:W55) -> 0 | AA56: TOTAL | AB56: =AB55 -> 1000 | AD56: =SUM(AD8:AD55) -> 0 | AE56: =SUM(AE8:AE55) -> 40 | AI56: TOTAL | AJ56: =AJ55 -> 2000 | AL56: =SUM(AL8:AL55) -> 40 | AM56: =SUM(AM8:AM55) -> 0 | AQ56: TOTAL | AR56: =AR55 -> 1000 | AT56: =SUM(AT8:AT55) -> 0 | AU56: =SUM(AU8:AU55) -> 35 | AY56: TOTAL | AZ56: =AZ55 -> 1150 | BB56: =SUM(BB8:BB55) -> 42 | BC56: =SUM(BC8:BC55) -> 0 | BG56: TOTAL | BH56: =BH55 -> 7000 | BJ56: =SUM(BJ8:BJ55) -> 225 | BK56: =SUM(BK8:BK55) -> 0 | BO56: TOTAL | BP56: =BP55 -> 1000 | BR56: =SUM(BR8:BR55) -> 0 | BS56: =SUM(BS8:BS55) -> 45 | BW56: TOTAL | BX56: =BX55 -> 0 | BZ56: =SUM(BZ8:BZ55) -> 75 | CA56: =SUM(CA8:CA55) -> 0 | CE56: TOTAL | CF56: =CF55 -> 0 | CH56: =SUM(CH8:CH55) -> 0 | CI56: =SUM(CI8:CI55) -> 0 | CM56: TOTAL | CN56: =CN55 -> 0 | CP56: =SUM(CP8:CP55) -> 0 | CQ56: =SUM(CQ8:CQ55) -> 0 | CU56: TOTAL | CV56: =CV55 -> 0 | CX56: =SUM(CX8:CX55) -> 0 | CY56: =SUM(CY8:CY55) -> 0 | DC56: TOTAL | DD56: =DD55 -> 0 | DF56: =SUM(DF8:DF55) -> 0 | DG56: =SUM(DG8:DG55) -> 0 | DK56: TOTAL | DL56: =DL55 -> 0 | DN56: =SUM(DN8:DN55) -> 0 | DO56: =SUM(DO8:DO55) -> 0 | DS56: TOTAL | DT56: =DT55 -> 0 | DV56: =SUM(DV8:DV55) -> 0 | DW56: =SUM(DW8:DW55) -> 0 | EA56: TOTAL | EB56: =EB55 -> 0 | ED56: =SUM(ED8:ED55) -> 0 | EE56: =SUM(EE8:EE55) -> 0 | EI56: TOTAL | EJ56: =EJ55 -> 0 | EL56: =SUM(EL8:EL55) -> 0 | EM56: =SUM(EM8:EM55) -> 0 | EQ56: TOTAL | ER56: =ER55 -> 0 | ET56: =SUM(ET8:ET55) -> 0 | EU56: =SUM(EU8:EU55) -> 0 | EY56: TOTAL | EZ56: =EZ55 -> 0 | FB56: =SUM(FB8:FB55) -> 0 | FC56: =SUM(FC8:FC55) -> 0 | FG56: TOTAL | FH56: =FH55 -> 0 | FJ56: =SUM(FJ8:FJ55) -> 0 | FK56: =SUM(FK8:FK55) -> 0 | FO56: TOTAL | FP56: =FP55 -> 0 | FR56: =SUM(FR8:FR55) -> 0 | FS56: =SUM(FS8:FS55) -> 0 | FW56: TOTAL | FX56: =FX55 -> 0 | FZ56: =SUM(FZ8:FZ55) -> 0 | GA56: =SUM(GA8:GA55) -> 0 | GE56: TOTAL | GF56: =GF55 -> 0 | GH56: =SUM(GH8:GH55) -> 0 | GI56: =SUM(GI8:GI55) -> 0 | GM56: TOTAL | GN56: =GN55 -> 0 | GP56: =SUM(GP8:GP55) -> 0 | GQ56: =SUM(GQ8:GQ55) -> 0 | GU56: TOTAL | GV56: =GV55 -> 0 | GX56: =SUM(GX8:GX55) -> 0 | GY56: =SUM(GY8:GY55) -> 0 | HC56: TOTAL | HD56: =HD55 -> 0 | HF56: =SUM(HF8:HF55) -> 0 | HG56: =SUM(HG8:HG55) -> 0 | HK56: TOTAL | HL56: =HL55 -> 0 | HN56: =SUM(HN8:HN55) -> 0 | HO56: =SUM(HO8:HO55) -> 0 | HS56: TOTAL | HT56: =HT55 -> 0 | HV56: =SUM(HV8:HV55) -> 0 | HW56: =SUM(HW8:HW55) -> 0 | IA56: TOTAL | IB56: =IB55 -> 0 | ID56: =SUM(ID8:ID55) -> 0 | IE56: =SUM(IE8:IE55) -> 0 | II56: TOTAL | IJ56: =IJ55 -> 0 | IL56: =SUM(IL8:IL55) -> 0 | IM56: =SUM(IM8:IM55) -> 0 | IQ56: TOTAL | IR56: =IR55 -> 0 | IT56: =SUM(IT8:IT55) -> 0 | IU56: =SUM(IU8:IU55) -> 0 | IY56: TOTAL | IZ56: =IZ55 -> 0 | JB56: =SUM(JB8:JB55) -> 0 | JC56: =SUM(JC8:JC55) -> 0 | JG56: TOTAL | JH56: =JH55 -> 0 | JJ56: =SUM(JJ8:JJ55) -> 0 | JK56: =SUM(JK8:JK55) -> 0 | JO56: TOTAL | JP56: =JP55 -> 0 | JR56: =SUM(JR8:JR55) -> 0 | JS56: =SUM(JS8:JS55) -> 0 | JW56: TOTAL | JX56: =JX55 -> 0 | JZ56: =SUM(JZ8:JZ55) -> 0 | KA56: =SUM(KA8:KA55) -> 0 | KE56: TOTAL | KF56: =KF55 -> 0 | KH56: =SUM(KH8:KH55) -> 0 | KI56: =SUM(KI8:KI55) -> 0 | KM56: TOTAL | KN56: =KN55 -> 0 | KP56: =SUM(KP8:KP55) -> 0 | KQ56: =SUM(KQ8:KQ55) -> 0 | KU56: TOTAL | KV56: =KV55 -> 0 | KX56: =SUM(KX8:KX55) -> 0 | KY56: =SUM(KY8:KY55) -> 0 | LC56: TOTAL | LD56: =LD55 -> 0 | LF56: =SUM(LF8:LF55) -> 0 | LG56: =SUM(LG8:LG55) -> 0 | LK56: TOTAL | LL56: =LL55 -> 0 | LN56: =SUM(LN8:LN55) -> 0 | LO56: =SUM(LO8:LO55) -> 0 | LS56: TOTAL | LT56: =LT55 -> 0 | LV56: =SUM(LV8:LV55) -> 0 | LW56: =SUM(LW8:LW55) -> 0 | MA56: TOTAL | MB56: =MB55 -> 0 | MD56: =SUM(MD8:MD55) -> 0 | ME56: =SUM(ME8:ME55) -> 0 | MI56: TOTAL | MJ56: =MJ55 -> 0 | ML56: =SUM(ML8:ML55) -> 0 | MM56: =SUM(MM8:MM55) -> 0 | MQ56: TOTAL | MR56: =MR55 -> 0 | MT56: =SUM(MT8:MT55) -> 0 | MU56: =SUM(MU8:MU55) -> 0 | MY56: TOTAL | MZ56: =MZ55 -> 0 | NB56: =SUM(NB8:NB55) -> 0 | NC56: =SUM(NC8:NC55) -> 0 | NG56: TOTAL | NH56: =NH55 -> 0 | NJ56: =SUM(NJ8:NJ55) -> 0 | NK56: =SUM(NK8:NK55) -> 0 | NO56: TOTAL | NP56: =NP55 -> 0 | NR56: =SUM(NR8:NR55) -> 0 | NS56: =SUM(NS8:NS55) -> 0 | NW56: TOTAL | NX56: =NX55 -> 0 | NZ56: =SUM(NZ8:NZ55) -> 0 | OA56: =SUM(OA8:OA55) -> 0 | OE56: TOTAL | OF56: =OF55 -> 0 | OH56: =SUM(OH8:OH55) -> 0 | OI56: =SUM(OI8:OI55) -> 0 | OM56: TOTAL | ON56: =ON55 -> 0 | OP56: =SUM(OP8:OP55) -> 0 | OQ56: =SUM(OQ8:OQ55) -> 0 | OU56: TOTAL | OV56: =OV55 -> 0 | OX56: =SUM(OX8:OX55) -> 0 | OY56: =SUM(OY8:OY55) -> 0 | PC56: TOTAL | PD56: =PD55 -> 0 | PF56: =SUM(PF8:PF55) -> 0 | PG56: =SUM(PG8:PG55) -> 0 | PK56: TOTAL | PL56: =PL55 -> 0 | PN56: =SUM(PN8:PN55) -> 0 | PO56: =SUM(PO8:PO55) -> 0 | PS56: TOTAL | PT56: =PT55 -> 0 | PV56: =SUM(PV8:PV55) -> 0 | PW56: =SUM(PW8:PW55) -> 0 | QA56: TOTAL | QB56: =QB55 -> 0 | QD56: =SUM(QD8:QD55) -> 0 | QE56: =SUM(QE8:QE55) -> 0 | QI56: TOTAL | QJ56: =QJ55 -> 0 | QL56: =SUM(QL8:QL55) -> 0 | QM56: =SUM(QM8:QM55) -> 0 | QQ56: TOTAL | QR56: =QR55 -> 0 | QT56: =SUM(QT8:QT55) -> 0 | QU56: =SUM(QU8:QU55) -> 0 | QY56: TOTAL | QZ56: =QZ55 -> 0 | RB56: =SUM(RB8:RB55) -> 0 | RC56: =SUM(RC8:RC55) -> 0 | RG56: TOTAL | RH56: =RH55 -> 0 | RJ56: =SUM(RJ8:RJ55) -> 0 | RK56: =SUM(RK8:RK55) -> 0 | RO56: TOTAL | RP56: =RP55 -> 0 | RR56: =SUM(RR8:RR55) -> 0 | RS56: =SUM(RS8:RS55) -> 0 | RW56: TOTAL | RX56: =RX55 -> 0 | RZ56: =SUM(RZ8:RZ55) -> 0 | SA56: =SUM(SA8:SA55) -> 0 | SE56: TOTAL | SF56: =SF55 -> 0 | SH56: =SUM(SH8:SH55) -> 0 | SI56: =SUM(SI8:SI55) -> 0 | SM56: TOTAL | SN56: =SN55 -> 0 | SP56: =SUM(SP8:SP55) -> 0 | SQ56: =SUM(SQ8:SQ55) -> 0 | SU56: TOTAL | SV56: =SV55 -> 0 | SX56: =SUM(SX8:SX55) -> 0 | SY56: =SUM(SY8:SY55) -> 0 | TC56: TOTAL | TD56: =TD55 -> 0 | TF56: =SUM(TF8:TF55) -> 0 | TG56: =SUM(TG8:TG55) -> 0 | TK56: TOTAL | TL56: =TL55 -> 0 | TN56: =SUM(TN8:TN55) -> 0 | TO56: =SUM(TO8:TO55) -> 0 | TS56: TOTAL | TT56: =TT55 -> 0 | TV56: =SUM(TV8:TV55) -> 0 | TW56: =SUM(TW8:TW55) -> 0 | UA56: TOTAL | UB56: =UB55 -> 0 | UD56: =SUM(UD8:UD55) -> 0 | UE56: =SUM(UE8:UE55) -> 0 | UI56: TOTAL | UJ56: =UJ55 -> 0 | UL56: =SUM(UL8:UL55) -> 0 | UM56: =SUM(UM8:UM55) -> 0 | UQ56: TOTAL | UR56: =UR55 -> 0 | UT56: =SUM(UT8:UT55) -> 0 | UU56: =SUM(UU8:UU55) -> 0 | UY56: TOTAL | UZ56: =UZ55 -> 0 | VB56: =SUM(VB8:VB55) -> 0 | VC56: =SUM(VC8:VC55) -> 0 | VG56: TOTAL | VH56: =VH55 -> 0 | VJ56: =SUM(VJ8:VJ55) -> 0 | VK56: =SUM(VK8:VK55) -> 0 | VO56: TOTAL | VP56: =VP55 -> 0 | VR56: =SUM(VR8:VR55) -> 0 | VS56: =SUM(VS8:VS55) -> 0 | VW56: TOTAL | VX56: =VX55 -> 0 | VZ56: =SUM(VZ8:VZ55) -> 0 | WA56: =SUM(WA8:WA55) -> 0 | WE56: TOTAL | WF56: =WF55 -> 0 | WH56: =SUM(WH8:WH55) -> 0 | WI56: =SUM(WI8:WI55) -> 0 | WM56: TOTAL | WN56: =WN55 -> 0 | WP56: =SUM(WP8:WP55) -> 0 | WQ56: =SUM(WQ8:WQ55) -> 0 | WU56: TOTAL | WV56: =WV55 -> 0 | WX56: =SUM(WX8:WX55) -> 0 | WY56: =SUM(WY8:WY55) -> 0 | XC56: TOTAL | XD56: =XD55 -> 0 | XF56: =SUM(XF8:XF55) -> 0 | XG56: =SUM(XG8:XG55) -> 0 | XK56: TOTAL | XL56: =XL55 -> 0 | XN56: =SUM(XN8:XN55) -> 0 | XO56: =SUM(XO8:XO55) -> 0 | XS56: TOTAL | XT56: =XT55 -> 0 | XV56: =SUM(XV8:XV55) -> 0 | XW56: =SUM(XW8:XW55) -> 0 | YA56: TOTAL | YB56: =YB55 -> 0 | YD56: =SUM(YD8:YD55) -> 0 | YE56: =SUM(YE8:YE55) -> 0 | YI56: TOTAL | YJ56: =YJ55 -> 0 | YL56: =SUM(YL8:YL55) -> 0 | YM56: =SUM(YM8:YM55) -> 0 | YQ56: TOTAL | YR56: =YR55 -> 0 | YT56: =SUM(YT8:YT55) -> 0 | YU56: =SUM(YU8:YU55) -> 0 | YY56: TOTAL | YZ56: =YZ55 -> 0 | ZB56: =SUM(ZB8:ZB55) -> 0 | ZC56: =SUM(ZC8:ZC55) -> 0 | ZG56: TOTAL | ZH56: =ZH55 -> 0 | ZJ56: =SUM(ZJ8:ZJ55) -> 0 | ZK56: =SUM(ZK8:ZK55) -> 0 | ZO56: TOTAL | ZP56: =ZP55 -> 0 | ZR56: =SUM(ZR8:ZR55) -> 0 | ZS56: =SUM(ZS8:ZS55) -> 0 | ZW56: TOTAL | ZX56: =ZX55 -> 0 | ZZ56: =SUM(ZZ8:ZZ55) -> 0 | AAA56: =SUM(AAA8:AAA55) -> 0 | AAE56: TOTAL | AAF56: =AAF55 -> 0 | AAH56: =SUM(AAH8:AAH55) -> 0 | AAI56: =SUM(AAI8:AAI55) -> 0 | AAM56: TOTAL | AAN56: =AAN55 -> 0 | AAP56: =SUM(AAP8:AAP55) -> 0 | AAQ56: =SUM(AAQ8:AAQ55) -> 0 | AAU56: TOTAL | AAV56: =AAV55 -> 0 | AAX56: =SUM(AAX8:AAX55) -> 0 | AAY56: =SUM(AAY8:AAY55) -> 0 | ABC56: TOTAL | ABD56: =ABD55 -> 0 | ABF56: =SUM(ABF8:ABF55) -> 0 | ABG56: =SUM(ABG8:ABG55) -> 0 | ABK56: TOTAL | ABL56: =ABL55 -> 0 | ABN56: =SUM(ABN8:ABN55) -> 0 | ABO56: =SUM(ABO8:ABO55) -> 0 | ABS56: TOTAL | ABT56: =ABT55 -> 0 | ABV56: =SUM(ABV8:ABV55) -> 0 | ABW56: =SUM(ABW8:ABW55) -> 0 | ACA56: TOTAL | ACB56: =ACB55 -> 0 | ACD56: =SUM(ACD8:ACD55) -> 0 | ACE56: =SUM(ACE8:ACE55) -> 0
A58: TOTAL DE PRESTAMOS EN CIRCULACION | H58: =D56+L56+T56+AB56+AJ56+AR56+AZ56+BH56+BP56+BX56+CF56+CN56+CV56+DD56+DL56+DT56+EB56+EJ56+ER56+EZ56+FH56+FP56+FX56+GF56+GN56+GV56+HD56+HL56+HT56+IB56+IJ56+IR56+IZ56+JH56+JP56+JX56+KF56+KN56+KV56+LD56+LL56+LT56+MB56+MJ56+MR56+MZ56+NH56+C68+NP56+NX56+OF56+ON56+OV56+PD56+PL56+PT56+QB56+QJ56+QR56+QZ56+RH56+RP56+RX56+SF56+SN56+SV56+TD56+TL56+TT56+UB56+UJ56+UR56+UZ56+VH56+VP56+VX56+WF56+WN56+WV56+XD56+XL56+XT56+YB56+YJ56+YR56+YZ56+ZH56+ZP56+ZX56+AAF56+AAN56+AAV56+ABD56+ABL56+ABT56+ACB56 -> 19850
A59: TOTAL DE INTERESES RECIBIDOS POR PRESTAMOS | H59: =F56+N56+V56+AD56+AL56+AT56+BB56+BJ56+BR56+BZ56+CH56+CP56+CX56+DF56+DN56+DV56+ED56+EL56+ET56+FB56+FJ56+FR56+FZ56+GH56+GP56+GX56+HF56+HN56+HV56+ID56+IL56+IT56+JB56+JJ56+JR56+JZ56+KH56+KP56+KX56+LF56+LN56+LV56+MD56+ML56+MT56+NB56+NJ56+NR56+NZ56+OH56+OP56+OX56+PF56+PN56+PV56+QD56+QL56+QT56+RB56+RJ56+RR56+RZ56+SH56+SP56+SX56+TF56+TN56+TV56+UD56+UL56+UT56+VB56+VJ56+VR56+VZ56+WH56+WP56+WX56+XF56+XN56+XV56+YD56+YL56+YT56+ZB56+ZJ56+ZR56+ZZ56+AAH56+AAP56+AAX56+ABF56+ABN56+ABV56+ACD56 -> 590
A61: TOTAL DE INTERESES POR COBRAR PRESTAMOS | H61: =G56+O56+W56+AE56+AM56+AU56+BC56+BK56+BS56+CA56+CI56+CQ56+CY56+DG56+DO56+DW56+EE56+EM56+EU56+FC56+FK56+FS56+GA56+GI56+GQ56+GY56+HG56+HO56+HW56+IE56+IM56+IU56+JC56+JK56+JS56+KA56+KI56+KQ56+KY56+LG56+LO56+LW56+ME56+MM56+MU56+NC56+NK56+NS56+OA56+OI56+OQ56+OY56+PG56+PO56+PW56+QE56+QM56+QU56+RC56+RK56+RS56+SA56+SI56+SQ56+SY56+TG56+TO56+TW56+UE56+UM56+UU56+VC56+VK56+VS56+WA56+WI56+WQ56+WY56+XG56+XO56+XW56+YE56+YM56+YU56+ZC56+ZK56+ZS56+AAA56+AAI56+AAQ56+AAY56+ABG56+ABO56+ABW56+ACE56 -> 120

Sheet INVERS
AK1: No.1 | AL1: 3000 | AM1: 0.025 | AN1: =AL1*AM1 -> 75 | AO1: =AL1+AN1 -> 3075
AX3: 0.02 | BF3: 0.025
AE4: 0.0125 | AF4: ACREDITAR A CTA. 12-345-6789-0 | AK4: TOTAL | AL4: =SUM(AL1:AL3) -> 3000 | AM4: - | AN4: =SUM(AN1:AN3) -> 75 | AP4: 0.025
C5: INVERSIONISTA 1 | N5: INVERSIONISTA 2 | Y5: INVERSIONISTA 3 | AF5: ANA MARIA RAMIREZ | AJ5: INVERSIONISTA 4 | AS5: INVERSIONISTA 5 | BA5: INVERSIONISTA 6
C6: FECHA | D6: PRESTAMOS | E6: ABONO | F6: NUEVO | G6: FECHA DE | H6: INTERSES | I6: INTERESES | J6: ACREDITAR A CTA. 12-345-6789-0 | N6: FECHA | O6: PRESTAMOS | P6: ABONO | Q6: NUEVO | R6: FECHA DE | S6: INTERSES | T6: INTERESES | U6: ACREDITAR A CTA. 12-345-6789-0 | Y6: FECHA | Z6: PRESTAMOS | AA6: ABONO | AB6: NUEVO | AC6: FECHA DE | AD6: INTERSES | AE6: INTERESES | AF6: INVERSIÓN | AG6: MONTO | AH6: TASA | AI6: INTERES | AJ6: FECHA | AK6: PRESTAMOS | AL6: ABONO | AM6: NUEVO | AN6: FECHA DE | AO6: INTERSES | AP6: INTERESES | AS6: FECHA | AT6: PRESTAMOS | AU6: ABONO | AV6: NUEVO | AW6: FECHA DE | AX6: INTERSES | AY6: INTERESES | BA6: FECHA | BB6: PRESTAMOS | BC6: ABONO | BD6: NUEVO | BE6: FECHA DE | BF6: INTERSES | BG6: INTERESES
D7: RECIBIDO | F7: SALDO | G7: INTERES | H7: PAGADOS | I7: PENDIENTES | J7: INVERSIÓN | K7: MONTO | L7: TASA | M7: INTERES | O7: RECIBIDO | Q7: SALDO | R7: INTERES | S7: PAGADOS | T7: PENDIENTES | U7: INVERSIÓN | V7: MONTO | W7: TASA | X7: INTERES | Z7: RECIBIDO | AB7: SALDO | AC7: INTERES | AD7: PAGADOS | AE7: PENDIENTES | AF7: No.1 | AG7: 12000 | AH7: 0.0125 | AI7: =AG7*AH7 -> 150 | AK7: RECIBIDO | AM7: SALDO | AN7: INTERES | AO7: PAGADOS | AP7: PENDIENTES | AT7: RECIBIDO | AV7: SALDO | AW7: INTERES | AX7: PAGADOS | AY7: PENDIENTES | BB7: RECIBIDO | BD7: SALDO | BE7: INTERES | BF7: PAGADOS | BG7: PENDIENTES
C8: 46023 | D8: 10000 | F8: =D8 -> 10000 | G8: 46037 | J8: No.1 | K8: 3000 | L8: 0.0125 | M8: =K8*L8 -> 37.5 | N8: 46023 | O8: 7000 | Q8: =O8 -> 7000 | R8: 46037 | T8: 89 | U8: No.1 | V8: 4000 | W8: 0.015 | X8: =V8*W8 -> 60 | Y8: 46023 | Z8: 12000 | AB8: =Z8 -> 12000 | AC8: 46037 | AE8: 150 | AJ8: 46023 | AK8: 3000 | AM8: =AK8 -> 3000 | AN8: 46037 | AO8: 75 | AS8: 46023 | AT8: 0 | AU8: 0 | AV8: =AT8 -> 0 | AW8: 46037 | BA8: 46023 | BD8: =BB8 -> 0 | BE8: 46037
C9: 46037 | E9: 3000 | F9: =SUM(F8,D9,-E9) -> 7000 | G9: 46052 | H9: 72.5 | J9: No. 2 | K9: 7000 | L9: 0.005 | M9: =K9*L9 -> 35 | Q9: =SUM(Q8,O9,-P9) -> 7000 | R9: 46052 | V9: 2000 | W9: 0.012 | X9: =V9*W9 -> 24 | AB9: =SUM(AB8,Z9,-AA9) -> 12000 | AC9: 46052 | AJ9: 46037 | AK9: 2000 | AM9: =SUM(AM8,AK9,-AL9) -> 5000 | AN9: 46052 | AV9: =SUM(AV8,AT9,-AU9) -> 0 | AW9: 46052 | BD9: =SUM(BD8,BB9,-BC9) -> 0 | BE9: 46052
F10: =SUM(F9,D10,-E10) -> 7000 | G10: 46068 | J10: TOTAL | K10: =SUM(K8:K9) -> 10000 | L10: - | M10: =SUM(M8:M9) -> 72.5 | Q10: =SUM(Q9,O10,-P10) -> 7000 | R10: 46068 | U10: No. 2 | V10: 1000 | W10: 0.005 | X10: =V10*W10 -> 5 | AB10: =SUM(AB9,Z10,-AA10) -> 12000 | AC10: 46068 | AF10: TOTAL | AG10: =SUM(AG7:AG9) -> 12000 | AH10: - | AI10: =SUM(AI7:AI9) -> 150 | AM10: =SUM(AM9,AK10,-AL10) -> 5000 | AN10: 46068 | AV10: =SUM(AV9,AT10,-AU10) -> 0 | AW10: 46068 | BD10: =SUM(BD9,BB10,-BC10) -> 0 | BE10: 46068
F11: =SUM(F10,D11,-E11) -> 7000 | G11: 46081 | Q11: =SUM(Q10,O11,-P11) -> 7000 | R11: 46081 | U11: TOTAL | V11: =SUM(V8:V10) -> 7000 | W11: - | X11: =SUM(X8:X10) -> 89 | AB11: =SUM(AB10,Z11,-AA11) -> 12000 | AC11: 46081 | AM11: =SUM(AM10,AK11,-AL11) -> 5000 | AN11: 46081 | AV11: =SUM(AV10,AT11,-AU11) -> 0 | AW11: 46081 | BD11: =SUM(BD10,BB11,-BC11) -> 0 | BE11: 46081
F12: =SUM(F11,D12,-E12) -> 7000 | G12: 46096 | Q12: =SUM(Q11,O12,-P12) -> 7000 | R12: 46096 | AB12: =SUM(AB11,Z12,-AA12) -> 12000 | AC12: 46096 | AM12: =SUM(AM11,AK12,-AL12) -> 5000 | AN12: 46096 | AV12: =SUM(AV11,AT12,-AU12) -> 0 | AW12: 46096 | BD12: =SUM(BD11,BB12,-BC12) -> 0 | BE12: 46096
F13: =SUM(F12,D13,-E13) -> 7000 | G13: 46111 | Q13: =SUM(Q12,O13,-P13) -> 7000 | R13: 46111 | AB13: =SUM(AB12,Z13,-AA13) -> 12000 | AC13: 46111 | AM13: =SUM(AM12,AK13,-AL13) -> 5000 | AN13: 46111 | AV13: =SUM(AV12,AT13,-AU13) -> 0 | AW13: 46111 | BD13: =SUM(BD12,BB13,-BC13) -> 0 | BE13: 46111
F14: =SUM(F13,D14,-E14) -> 7000 | G14: 46127 | Q14: =SUM(Q13,O14,-P14) -> 7000 | R14: 46127 | AB14: =SUM(AB13,Z14,-AA14) -> 12000 | AC14: 46127 | AG14: Nuevo Saldo | AH14: =AG7+AI7 -> 12150 | AM14: =SUM(AM13,AK14,-AL14) -> 5000 | AN14: 46127 | AV14: =SUM(AV13,AT14,-AU14) -> 0 | AW14: 46127 | BD14: =SUM(BD13,BB14,-BC14) -> 0 | BE14: 46127
F15: =SUM(F14,D15,-E15) -> 7000 | G15: 46142 | M15: *$500 Mache | Q15: =SUM(Q14,O15,-P15) -> 7000 | R15: 46142 | AB15: =SUM(AB14,Z15,-AA15) -> 12000 | AC15: 46142 | AM15: =SUM(AM14,AK15,-AL15) -> 5000 | AN15: 46142 | AV15: =SUM(AV14,AT15,-AU15) -> 0 | AW15: 46142 | BD15: =SUM(BD14,BB15,-BC15) -> 0 | BE15: 46142
F16: =SUM(F15,D16,-E16) -> 7000 | G16: 46157 | Q16: =SUM(Q15,O16,-P16) -> 7000 | R16: 46157 | AB16: =SUM(AB15,Z16,-AA16) -> 12000 | AC16: 46157 | AM16: =SUM(AM15,AK16,-AL16) -> 5000 | AN16: 46157 | AV16: =SUM(AV15,AT16,-AU16) -> 0 | AW16: 46157 | BD16: =SUM(BD15,BB16,-BC16) -> 0 | BE16: 46157
F17: =SUM(F16,D17,-E17) -> 7000 | G17: 46172 | Q17: =SUM(Q16,O17,-P17) -> 7000 | R17: 46172 | AB17: =SUM(AB16,Z17,-AA17) -> 12000 | AC17: 46172 | AM17: =SUM(AM16,AK17,-AL17) -> 5000 | AN17: 46172 | AV17: =SUM(AV16,AT17,-AU17) -> 0 | AW17: 46172 | BD17: =SUM(BD16,BB17,-BC17) -> 0 | BE17: 46172
F18: =SUM(F17,D18,-E18) -> 7000 | G18: 46188 | Q18: =SUM(Q17,O18,-P18) -> 7000 | R18: 46188 | AB18: =SUM(AB17,Z18,-AA18) -> 12000 | AC18: 46188 | AM18: =SUM(AM17,AK18,-AL18) -> 5000 | AN18: 46188 | AV18: =SUM(AV17,AT18,-AU18) -> 0 | AW18: 46188 | BD18: =SUM(BD17,BB18,-BC18) -> 0 | BE18: 46188
F19: =SUM(F18,D19,-E19) -> 7000 | G19: 46203 | Q19: =SUM(Q18,O19,-P19) -> 7000 | R19: 46203 | AB19: =SUM(AB18,Z19,-AA19) -> 12000 | AC19: 46203 | AM19: =SUM(AM18,AK19,-AL19) -> 5000 | AN19: 46203 | AV19: =SUM(AV18,AT19,-AU19) -> 0 | AW19: 46203 | BD19: =SUM(BD18,BB19,-BC19) -> 0 | BE19: 46203
F20: =SUM(F19,D20,-E20) -> 7000 | G20: 46218 | Q20: =SUM(Q19,O20,-P20) -> 7000 | R20: 46218 | AB20: =SUM(AB19,Z20,-AA20) -> 12000 | AC20: 46218 | AM20: =SUM(AM19,AK20,-AL20) -> 5000 | AN20: 46218 | AV20: =SUM(AV19,AT20,-AU20) -> 0 | AW20: 46218 | BD20: =SUM(BD19,BB20,-BC20) -> 0 | BE20: 46218
F21: =SUM(F20,D21,-E21) -> 7000 | G21: 46233 | Q21: =SUM(Q20,O21,-P21) -> 7000 | R21: 46233 | AB21: =SUM(AB20,Z21,-AA21) -> 12000 | AC21: 46233 | AM21: =SUM(AM20,AK21,-AL21) -> 5000 | AN21: 46233 | AV21: =SUM(AV20,AT21,-AU21) -> 0 | AW21: 46233 | BD21: =SUM(BD20,BB21,-BC21) -> 0 | BE21: 46233
F22: =SUM(F21,D22,-E22) -> 7000 | G22: 46249 | Q22: =SUM(Q21,O22,-P22) -> 7000 | R22: 46249 | AB22: =SUM(AB21,Z22,-AA22) -> 12000 | AC22: 46249 | AM22: =SUM(AM21,AK22,-AL22) -> 5000 | AN22: 46249 | AV22: =SUM(AV21,AT22,-AU22) -> 0 | AW22: 46249 | BD22: =SUM(BD21,BB22,-BC22) -> 0 | BE22: 46249
F23: =SUM(F22,D23,-E23) -> 7000 | G23: 46264 | Q23: =SUM(Q22,O23,-P23) -> 7000 | R23: 46264 | AB23: =SUM(AB22,Z23,-AA23) -> 12000 | AC23: 46264 | AM23: =SUM(AM22,AK23,-AL23) -> 5000 | AN23: 46264 | AV23: =SUM(AV22,AT23,-AU23) -> 0 | AW23: 46264 | BD23: =SUM(BD22,BB23,-BC23) -> 0 | BE23: 46264
F24: =SUM(F23,D24,-E24) -> 7000 | G24: 46280 | Q24: =SUM(Q23,O24,-P24) -> 7000 | R24: 46280 | AB24: =SUM(AB23,Z24,-AA24) -> 12000 | AC24: 46280 | AM24: =SUM(AM23,AK24,-AL24) -> 5000 | AN24: 46280 | AV24: =SUM(AV23,AT24,-AU24) -> 0 | AW24: 46280 | BD24: =SUM(BD23,BB24,-BC24) -> 0 | BE24: 46280
F25: =SUM(F24,D25,-E25) -> 7000 | G25: 46295 | Q25: =SUM(Q24,O25,-P25) -> 7000 | R25: 46295 | AB25: =SUM(AB24,Z25,-AA25) -> 12000 | AC25: 46295 | AL25: 500 | AM25: =SUM(AM24,AK25,-AL25) -> 4500 | AN25: 46295 | AV25: =SUM(AV24,AT25,-AU25) -> 0 | AW25: 46295 | BD25: =SUM(BD24,BB25,-BC25) -> 0 | BE25: 46295
F26: =SUM(F25,D26,-E26) -> 7000 | G26: 46310 | Q26: =SUM(Q25,O26,-P26) -> 7000 | R26: 46310 | AB26: =SUM(AB25,Z26,-AA26) -> 12000 | AC26: 46310 | AM26: =SUM(AM25,AK26,-AL26) -> 4500 | AN26: 46310 | AV26: =SUM(AV25,AT26,-AU26) -> 0 | AW26: 46310 | BD26: =SUM(BD25,BB26,-BC26) -> 0 | BE26: 46310
F27: =SUM(F26,D27,-E27) -> 7000 | G27: 46325 | Q27: =SUM(Q26,O27,-P27) -> 7000 | R27: 46325 | AB27: =SUM(AB26,Z27,-AA27) -> 12000 | AC27: 46325 | AM27: =SUM(AM26,AK27,-AL27) -> 4500 | AN27: 46325 | AV27: =SUM(AV26,AT27,-AU27) -> 0 | AW27: 46325 | BD27: =SUM(BD26,BB27,-BC27) -> 0 | BE27: 46325
F28: =SUM(F27,D28,-E28) -> 7000 | G28: 46341 | Q28: =SUM(Q27,O28,-P28) -> 7000 | R28: 46341 | AB28: =SUM(AB27,Z28,-AA28) -> 12000 | AC28: 46341 | AM28: =SUM(AM27,AK28,-AL28) -> 4500 | AN28: 46341 | AV28: =SUM(AV27,AT28,-AU28) -> 0 | AW28: 46341 | BD28: =SUM(BD27,BB28,-BC28) -> 0 | BE28: 46341
F29: =SUM(F28,D29,-E29) -> 7000 | G29: 46356 | Q29: =SUM(Q28,O29,-P29) -> 7000 | R29: 46356 | AB29: =SUM(AB28,Z29,-AA29) -> 12000 | AC29: 46356 | AL29: 1500 | AM29: =SUM(AM28,AK29,-AL29) -> 3000 | AN29: 46356 | AV29: =SUM(AV28,AT29,-AU29) -> 0 | AW29: 46356 | BD29: =SUM(BD28,BB29,-BC29) -> 0 | BE29: 46356
F30: =SUM(F29,D30,-E30) -> 7000 | G30: 46371 | Q30: =SUM(Q29,O30,-P30) -> 7000 | R30: 46371 | AB30: =SUM(AB29,Z30,-AA30) -> 12000 | AC30: 46371 | AM30: =SUM(AM29,AK30,-AL30) -> 3000 | AN30: 46371 | AV30: =SUM(AV29,AT30,-AU30) -> 0 | AW30: 46371 | BD30: =SUM(BD29,BB30,-BC30) -> 0 | BE30: 46371
F31: =SUM(F30,D31,-E31) -> 7000 | G31: 46386 | Q31: =SUM(Q30,O31,-P31) -> 7000 | R31: 46386 | AB31: =SUM(AB30,Z31,-AA31) -> 12000 | AC31: 46386 | AM31: =SUM(AM30,AK31,-AL31) -> 3000 | AN31: 46386 | AV31: =SUM(AV30,AT31,-AU31) -> 0 | AW31: 46386 | BD31: =SUM(BD30,BB31,-BC31) -> 0 | BE31: 46386
F32: =SUM(F31,D32,-E32) -> 7000 | Q32: =SUM(Q31,O32,-P32) -> 7000 | AB32: =SUM(AB31,Z32,-AA32) -> 12000 | AM32: =SUM(AM31,AK32,-AL32) -> 3000 | AV32: =SUM(AV31,AT32,-AU32) -> 0 | BD32: =SUM(BD31,BB32,-BC32) -> 0
F33: =SUM(F32,D33,-E33) -> 7000 | Q33: =SUM(Q32,O33,-P33) -> 7000 | AB33: =SUM(AB32,Z33,-AA33) -> 12000 | AM33: =SUM(AM32,AK33,-AL33) -> 3000 | AV33: =SUM(AV32,AT33,-AU33) -> 0 | BD33: =SUM(BD32,BB33,-BC33) -> 0
F34: =SUM(F33,D34,-E34) -> 7000 | Q34: =SUM(Q33,O34,-P34) -> 7000 | AB34: =SUM(AB33,Z34,-AA34) -> 12000 | AL34: 200 | AM34: =SUM(AM33,AK34,-AL34) -> 2800 | AV34: =SUM(AV33,AT34,-AU34) -> 0 | BD34: =SUM(BD33,BB34,-BC34) -> 0
F35: =SUM(F34,D35,-E35) -> 7000 | Q35: =SUM(Q34,O35,-P35) -> 7000 | AB35: =SUM(AB34,Z35,-AA35) -> 12000 | AM35: =SUM(AM34,AK35,-AL35) -> 2800 | AV35: =SUM(AV34,AT35,-AU35) -> 0 | BD35: =SUM(BD34,BB35,-BC35) -> 0
F36: =SUM(F35,D36,-E36) -> 7000 | Q36: =SUM(Q35,O36,-P36) -> 7000 | AB36: =SUM(AB35,Z36,-AA36) -> 12000 | AF36: $100 | AM36: =SUM(AM35,AK36,-AL36) -> 2800 | AV36: =SUM(AV35,AT36,-AU36) -> 0 | BD36: =SUM(BD35,BB36,-BC36) -> 0
F37: =SUM(F36,D37,-E37) -> 7000 | Q37: =SUM(Q36,O37,-P37) -> 7000 | AB37: =SUM(AB36,Z37,-AA37) -> 12000 | AM37: =SUM(AM36,AK37,-AL37) -> 2800 | AV37: =SUM(AV36,AT37,-AU37) -> 0 | BD37: =SUM(BD36,BB37,-BC37) -> 0
